Workbook
Name Company_Name: #REF!
Name Company_Name: [1]Dashboard!$B$2
Name LF: #REF!
Name LF: #REF!
Name LF: #REF!
Name locked: #REF!
Name locked: #REF!
Name locked: #REF!
Name locked: #REF!
Name MPM: #REF!
Name MPM: #REF!
Name MPM: #REF!
Name MPM: #REF!
Name QBCANSUPPORTUPDATE: TRUE
Name QBCOMPANYFILENAME: "\\server1\QBData\QuickbooksData\Gorilla Marketing.qbw"
Name QBENDDATE: 20190831
Name QBHEADERSONSCREEN: FALSE
Name QBMETADATASIZE: 5914
Name QBPRESERVECOLOR: TRUE
Name QBPRESERVEFONT: TRUE
Name QBPRESERVEROWHEIGHT: TRUE
Name QBPRESERVESPACE: TRUE
Name QBREPORTCOLAXIS: 0
Name QBREPORTCOMPANYID: "db4700d490074202ab8a7fff4c5b1188"
Name QBREPORTCOMPARECOL_ANNUALBUDGET: FALSE
Name QBREPORTCOMPARECOL_AVGCOGS: FALSE
Name QBREPORTCOMPARECOL_AVGPRICE: FALSE
Name QBREPORTCOMPARECOL_BUDDIFF: FALSE
Name QBREPORTCOMPARECOL_BUDGET: FALSE
Name QBREPORTCOMPARECOL_BUDPCT: FALSE
Name QBREPORTCOMPARECOL_COGS: FALSE
Name QBREPORTCOMPARECOL_EXCLUDEAMOUNT: FALSE
Name QBREPORTCOMPARECOL_EXCLUDECURPERIOD: FALSE
Name QBREPORTCOMPARECOL_FORECAST: FALSE
Name QBREPORTCOMPARECOL_GROSSMARGIN: FALSE
Name QBREPORTCOMPARECOL_GROSSMARGINPCT: FALSE
Name QBREPORTCOMPARECOL_HOURS: FALSE
Name QBREPORTCOMPARECOL_PCTCOL: FALSE
Name QBREPORTCOMPARECOL_PCTEXPENSE: FALSE
Name QBREPORTCOMPARECOL_PCTINCOME: FALSE
Name QBREPORTCOMPARECOL_PCTOFSALES: FALSE
Name QBREPORTCOMPARECOL_PCTROW: FALSE
Name QBREPORTCOMPARECOL_PPDIFF: FALSE
Name QBREPORTCOMPARECOL_PPPCT: FALSE
Name QBREPORTCOMPARECOL_PREVPERIOD: FALSE
Name QBREPORTCOMPARECOL_PREVYEAR: FALSE
Name QBREPORTCOMPARECOL_PYDIFF: FALSE
Name QBREPORTCOMPARECOL_PYPCT: FALSE
Name QBREPORTCOMPARECOL_QTY: FALSE
Name QBREPORTCOMPARECOL_RATE: FALSE
Name QBREPORTCOMPARECOL_TRIPBILLEDMILES: FALSE
Name QBREPORTCOMPARECOL_TRIPBILLINGAMOUNT: FALSE
Name QBREPORTCOMPARECOL_TRIPMILES: FALSE
Name QBREPORTCOMPARECOL_TRIPNOTBILLABLEMILES: FALSE
Name QBREPORTCOMPARECOL_TRIPTAXDEDUCTIBLEAMOUNT: FALSE
Name QBREPORTCOMPARECOL_TRIPUNBILLEDMILES: FALSE
Name QBREPORTCOMPARECOL_YTD: FALSE
Name QBREPORTCOMPARECOL_YTDBUDGET: FALSE
Name QBREPORTCOMPARECOL_YTDPCT: FALSE
Name QBREPORTROWAXIS: 9

Sheet Docket
A1: MONTHLY ACCOUNTING FILE DOCKET SHEET
A4: NAME OF ENTITY: | C4: Aura
A6: MONTH: | C6: 45474
A10: FINANCIAL REPORT PROCESSING
D12: BY | F12: DATE
A13: ACCOUNTING WORK PAPERS PREPARED | D13: XY
A15: REVIEW OF ACCOUNTING WORK PAPERS - SUPERVISOR
A17: REVIEW OF ACCOUNTING WORK PAPERS - MANAGER
A19: FINAL REVIEW & APPROVAL
A21: SPECIAL INSTRUCTIONS, QUARTER END
D22: BY | F22: DATE
A23: TYPE FINANCIAL REPORTS FOR INVESTORS
A25: OBTAIN FIXED ASSETS FORECAST
A27: DETERMINE DISTRIBUTION AMOUNT
A29: CREATE NEWSLETTER FINANCIALS, SAVE TO SHARED FOLDER
A31: COMMENTS:

Sheet Notes
E1: Date: | F1: =NOW() -> 46065.348
E2: Prepared By: | F2: =Docket!D13 -> XY | G2: =NOW() -> 46065.348
E3: Approved By:
F4: Initial | G4: Date
A5: =+Docket!C4 -> Aura
A6: Accountant Notes for Month End
A8: Month: | C8: =+Docket!C6 -> 45474
A11: Overall notes for entire book:
B14: GL Acct # | C14: GL Name | D14: Notes
B16: 1126 | C16: A/R - Vendors
B18: 1128 | C18: A/R - Payroll
B20: 1155
B22: 1163
B24: 1875 | C24: Security Deposit
B26: 2036 | C26: Employee Trust
B28: 2038 | C28: Other Payroll Liabilities
A36: Note:

Sheet Access List
A1: CLIENT NAME:
A3: BANK / CC NAME | B3: OTHER PLATFORM | C3: ACCOUNT NUMBER | D3: ITEM NEEDED | E3: ACCESS (Y/N) | F3: NOTES
A4: Bank of America | C4: 3251-5870-1020 | D4: Bank Statements | E4: Y
A5: ADP - AuraAccounting
A6: ADP - SeedCMS (Socal)

Sheet Contact List
A1: CLIENT NAME:
A3: CONTACT | B3: ITEMS NEEDED (add acct # if needed)
A4: Carlos Roman <carlos@carefreeboats.com> | B4: main contact for month-end questions
A5: Peter Yanakiev <peter@carefreeboats.com> | B5: for bank and cc statements

Sheet TB Match
B1: 46022
B2: Debit | C2: Credit | E2: Debit | F2: Credit
A3: 10000 Business Adv Relationship - 1020 | B3: ='10000 - BofA CHK 1020'!$O$45 -> 25944.2 | E3: 25944.2 | G3: =(B3+C3)-(E3+F3) -> 0 | H3: =IF(ROUND(B3-E3,1)= 0, "Match","No Match") -> Match | I3: =IF(ROUND(C3-F3,1)= 0, "Match","No Match") -> Match
A4: 11000 Accounts Receivable | B4: ='11000 Accounts Receivable'!C11 -> 0 | E4: 0 | G4: =(B4+C4)-(E4+F4) -> 0 | H4: =IF(ROUND(B4-E4,1)= 0, "Match","No Match") -> Match | I4: =IF(ROUND(C4-F4,1)= 0, "Match","No Match") -> Match
A5: 11600 Prepaid expenses | B5: ='11600 - Prepaid Expenses (OLD)'!E19 -> 39826.575 | E5: 39826.57 | G5: =(B5+C5)-(E5+F5) -> 0.0049544403 | H5: =IF(ROUND(B5-E5,1)= 0, "Match","No Match") -> Match | I5: =IF(ROUND(C5-F5,1)= 0, "Match","No Match") -> Match
A6: 13000 Axopar Suntop 37 | B6: ='15500-Acc Depreciation'!AM8 -> 269900 | E6: 269900 | G6: =(B6+C6)-(E6+F6) -> 0 | H6: =IF(ROUND(B6-E6,1)= 0, "Match","No Match") -> Match | I6: =IF(ROUND(C6-F6,1)= 0, "Match","No Match") -> Match
A7: 13100 Beneteau Flyer 9 | B7: ='15500-Acc Depreciation'!AM7 -> 263992.78 | E7: 263992.78 | G7: =(B7+C7)-(E7+F7) -> 0 | H7: =IF(ROUND(B7-E7,1)= 0, "Match","No Match") -> Match | I7: =IF(ROUND(C7-F7,1)= 0, "Match","No Match") -> Match
A8: 13200 Manitou 25 Oasis | B8: ='15500-Acc Depreciation'!AM4 -> 66464 | E8: 66464 | G8: =(B8+C8)-(E8+F8) -> 0 | H8: =IF(ROUND(B8-E8,1)= 0, "Match","No Match") -> Match | I8: =IF(ROUND(C8-F8,1)= 0, "Match","No Match") -> Match
A9: 13400 NX 340 Sport Coupe | B9: ='15500-Acc Depreciation'!AM10 -> 272754.5 | E9: 272754.5 | G9: =(B9+C9)-(E9+F9) -> 0 | H9: =IF(ROUND(B9-E9,1)= 0, "Match","No Match") -> Match | I9: =IF(ROUND(C9-F9,1)= 0, "Match","No Match") -> Match
A10: 13500 Axopar T-Top 28 | B10: ='15500-Acc Depreciation'!AM9 -> 140000 | E10: 140000 | G10: =(B10+C10)-(E10+F10) -> 0 | H10: =IF(ROUND(B10-E10,1)= 0, "Match","No Match") -> Match | I10: =IF(ROUND(C10-F10,1)= 0, "Match","No Match") -> Match
A11: 15000 Pacific Boat Club Fleet | B11: ='15500-Acc Depreciation'!AP6 -> 68219.69 | E11: 68219.69 | G11: =(B11+C11)-(E11+F11) -> 0 | H11: =IF(ROUND(B11-E11,1)= 0, "Match","No Match") -> Match | I11: =IF(ROUND(C11-F11,1)= 0, "Match","No Match") -> Match
A12: 15500 Accumulated Depreciation | C12: =_xlfn.XLOOKUP(B1,'15500-Acc Depreciation'!33:33,'15500-Acc Depreciation'!43:43) -> 530560.76 | F12: 530560.76 | G12: =(B12+C12)-(E12+F12) -> 0.0016666667 | H12: =IF(ROUND(B12-E12,1)= 0, "Match","No Match") -> Match | I12: =IF(ROUND(C12-F12,1)= 0, "Match","No Match") -> Match
A13: 17000 Goodwill | B13: ='17000 - Goodwill'!B3 -> 174500 | E13: 174500 | G13: =(B13+C13)-(E13+F13) -> 0 | H13: =IF(ROUND(B13-E13,1)= 0, "Match","No Match") -> Match | I13: =IF(ROUND(C13-F13,1)= 0, "Match","No Match") -> Match
A14: 18000 Accumulated Amortization | C14: =_xlfn.XLOOKUP(B1,'17000 - Goodwill'!A:A,'17000 - Goodwill'!D:D) -> 51357 | F14: 51357 | G14: =(B14+C14)-(E14+F14) -> 0 | H14: =IF(ROUND(B14-E14,1)= 0, "Match","No Match") -> Match | I14: =IF(ROUND(C14-F14,1)= 0, "Match","No Match") -> Match
A15: 21000 Accrued Expenses | C15: ='21000 - Accrued Expenses'!H23 -> 3149.75 | F15: 3149.75 | G15: =(B15+C15)-(E15+F15) -> 0 | H15: =IF(ROUND(B15-E15,1)= 0, "Match","No Match") -> Match | I15: =IF(ROUND(C15-F15,1)= 0, "Match","No Match") -> Match
A16: 21050 Accrued Interest | C16: ='21050 - Accrued Interest'!E8 -> 794.18231 | F16: 794.17 | G16: =(B16+C16)-(E16+F16) -> 0.012310814 | H16: =IF(ROUND(B16-E16,1)= 0, "Match","No Match") -> Match | I16: =IF(ROUND(C16-F16,1)= 0, "Match","No Match") -> Match
A17: 21100 Accrued Payroll | C17: 0 | F17: 0 | G17: =(B17+C17)-(E17+F17) -> 0 | H17: =IF(ROUND(B17-E17,1)= 0, "Match","No Match") -> Match | I17: =IF(ROUND(C17-F17,1)= 0, "Match","No Match") -> Match
A18: 21101 Accrued Payroll:Officer Wages Payable | C18: ='21100 - Accrued Payroll'!J21 -> 2245.52 | F18: 2245.52 | G18: =(B18+C18)-(E18+F18) -> 4.0927262e-12 | H18: =IF(ROUND(B18-E18,1)= 0, "Match","No Match") -> Match | I18: =IF(ROUND(C18-F18,1)= 0, "Match","No Match") -> Match
A19: 21102 Accrued Payroll:Contractor Wages Payable | C19: ='21100 - Accrued Payroll'!B31 -> 7930.81 | F19: 7930.81 | G19: =(B19+C19)-(E19+F19) -> 0 | H19: =IF(ROUND(B19-E19,1)= 0, "Match","No Match") -> Match | I19: =IF(ROUND(C19-F19,1)= 0, "Match","No Match") -> Match
A20: 21125 Unearned Revenue | C20: =_xlfn.XLOOKUP(B1,'21125 - Unearned Revenue'!3:3,'21125 - Unearned Revenue'!133:133) -> 442379.08 | F20: 442379.08 | G20: =(B20+C20)-(E20+F20) -> 0.0033333332 | H20: =IF(ROUND(B20-E20,1)= 0, "Match","No Match") -> Match | I20: =IF(ROUND(C20-F20,1)= 0, "Match","No Match") -> Match
A21: 21150 Loan From Shareholder - CCM Integrated | C21: =F21 -> 26221.5 | F21: 26221.5 | G21: =(B21+C21)-(E21+F21) -> 0 | H21: =IF(ROUND(B21-E21,1)= 0, "Match","No Match") -> Match | I21: =IF(ROUND(C21-F21,1)= 0, "Match","No Match") -> Match
A22: 21200 Loan From Shareholder - Carlos Roman | C22: =F22 -> 55668.06 | F22: 55668.06 | G22: =(B22+C22)-(E22+F22) -> 0 | H22: =IF(ROUND(B22-E22,1)= 0, "Match","No Match") -> Match | I22: =IF(ROUND(C22-F22,1)= 0, "Match","No Match") -> Match
A23: 21300 Due To/From SoCal Nautical | C23: =_xlfn.XLOOKUP("TOTAL",'21300 - Due to.from Socal'!I22,'21300 - Due to.from Socal'!J22) -> 53375.07 | F23: 53375.07 | G23: =(B23+C23)-(E23+F23) -> 0 | H23: =IF(ROUND(B23-E23,1)= 0, "Match","No Match") -> Match | I23: =IF(ROUND(C23-F23,1)= 0, "Match","No Match") -> Match
A24: 21350 Insurance Payable | C24: =_xlfn.XLOOKUP(B1,'23500 - Insurance Payable'!A:A,'23500 - Insurance Payable'!N:N,) -> 31127.185 | F24: 31127.18 | G24: =(B24+C24)-(E24+F24) -> 0.0050043987 | H24: =IF(ROUND(B24-E24,1)= 0, "Match","No Match") -> Match | I24: =IF(ROUND(C24-F24,1)= 0, "Match","No Match") -> Match
A25: 22000 Short-term business loans:ST - Axopar Suntop 37 Loan | C25: ='22000 & 23000 - Axopar Suntop37'!N5 -> 0.00045266328 | F25: 0 | G25: =(B25+C25)-(E25+F25) -> 0.00045266328 | H25: =IF(ROUND(B25-E25,1)= 0, "Match","No Match") -> Match | I25: =IF(ROUND(C25-F25,1)= 0, "Match","No Match") -> Match
A26: 22050 Short-term business loans:ST - Beneteau Flyer 9 | C26: ='22050 & 23050 - Beneteau'!N5 -> 0.00012240116 | F26: 0 | G26: =(B26+C26)-(E26+F26) -> 0.00012240116 | H26: =IF(ROUND(B26-E26,1)= 0, "Match","No Match") -> Match | I26: =IF(ROUND(C26-F26,1)= 0, "Match","No Match") -> Match
A27: 22100 Short-term business loans:ST - Manitou 25 Oasis Loan | C27: ='22100 & 23100 -Manitou (Stacey)'!N5 -> 0.00041830339 | F27: 0 | G27: =(B27+C27)-(E27+F27) -> 0.00041830339 | H27: =IF(ROUND(B27-E27,1)= 0, "Match","No Match") -> Match | I27: =IF(ROUND(C27-F27,1)= 0, "Match","No Match") -> Match
A28: 22150 Short-term business loans:ST - Scott Tiernan Note | C28: ='22150 & 23150 - Scott Tiernan'!N7 -> 5990.5163 | F28: 5990.53 | G28: =(B28+C28)-(E28+F28) -> -0.013738853 | H28: =IF(ROUND(B28-E28,1)= 0, "Match","No Match") -> Match | I28: =IF(ROUND(C28-F28,1)= 0, "Match","No Match") -> Match
A29: 22250 Short-term business loans:ST - NX 340 Sport Coupe Loan | C29: ='22250 & 23250 - NX 340'!N5 -> -0.00020420778 | F29: 0 | G29: =(B29+C29)-(E29+F29) -> -0.00020420778 | H29: =IF(ROUND(B29-E29,1)= 0, "Match","No Match") -> Match | I29: =IF(ROUND(C29-F29,1)= 0, "Match","No Match") -> Match
A30: 22300 Short-term business loans:ST - Axopar T-Top 28 Loan | C30: ='22300 & 23300 - Axopar T-TOP28'!O5 -> 4.9079157e-05 | F30: 0 | G30: =(B30+C30)-(E30+F30) -> 4.9079157e-05 | H30: =IF(ROUND(B30-E30,1)= 0, "Match","No Match") -> Match | I30: =IF(ROUND(C30-F30,1)= 0, "Match","No Match") -> Match
A31: 23000 Long-term business loans:LT - Axopar Suntop 37 Loan | C31: ='22000 & 23000 - Axopar Suntop37'!N6 -> -0.0043644141 | F31: 0 | G31: =(B31+C31)-(E31+F31) -> -0.0043644141 | H31: =IF(ROUND(B31-E31,1)= 0, "Match","No Match") -> Match | I31: =IF(ROUND(C31-F31,1)= 0, "Match","No Match") -> Match
A32: Short-term business loans:22350 ST - CCJ True, LLC Loan | C32: ='23350 - CCJ True Loan'!N5 -> 130327.01 | F32: 130327.01 | G32: =(B32+C32)-(E32+F32) -> 0.0028861333 | H32: =IF(ROUND(B32-E32,1)= 0, "Match","No Match") -> Match | I32: =IF(ROUND(C32-F32,1)= 0, "Match","No Match") -> Match
A33: Short-term business loans:22400 ST - CCJ True, LLC Loan (2) | C33: ='23400 - CCJ True Loan (2)'!N5 -> 18327.425 | F33: 18327.44 | G33: =(B33+C33)-(E33+F33) -> -0.015373183 | H33: =IF(ROUND(B33-E33,1)= 0, "Match","No Match") -> Match | I33: =IF(ROUND(C33-F33,1)= 0, "Match","No Match") -> Match
A34: 23050 Long-term business loans:LT - Beneteau Flyer 9 | C34: ='22050 & 23050 - Beneteau'!N6 -> -0.0011801475 | F34: 0 | G34: =(B34+C34)-(E34+F34) -> -0.0011801475 | H34: =IF(ROUND(B34-E34,1)= 0, "Match","No Match") -> Match | I34: =IF(ROUND(C34-F34,1)= 0, "Match","No Match") -> Match
A35: 23100 Long-term business loans:LT - Manitou 25 Oasis Loan | C35: ='22100 & 23100 -Manitou (Stacey)'!N6 -> -0.0052525712 | F35: =0 -> 0 | G35: =(B35+C35)-(E35+F35) -> -0.0052525712 | H35: =IF(ROUND(B35-E35,1)= 0, "Match","No Match") -> Match | I35: =IF(ROUND(C35-F35,1)= 0, "Match","No Match") -> Match
A36: 23150 Long-term business loans:LT - Scott Tiernan Note | C36: 0 | F36: =0 -> 0 | G36: =(B36+C36)-(E36+F36) -> 0 | H36: =IF(ROUND(B36-E36,1)= 0, "Match","No Match") -> Match | I36: =IF(ROUND(C36-F36,1)= 0, "Match","No Match") -> Match
A37: 23250 Long-term business loans:LT - NX 340 Sport Coupe Loan | C37: ='22250 & 23250 - NX 340'!N6 -> 0.0023811026 | F37: 0 | G37: =(B37+C37)-(E37+F37) -> 0.0023811026 | H37: =IF(ROUND(B37-E37,1)= 0, "Match","No Match") -> Match | I37: =IF(ROUND(C37-F37,1)= 0, "Match","No Match") -> Match
A38: 23300 Long-term business loans:LT - Axopar T-Top 28 Loan | C38: ='22300 & 23300 - Axopar T-TOP28'!O6 -> -0.00043606231 | F38: 0 | G38: =(B38+C38)-(E38+F38) -> -0.00043606231 | H38: =IF(ROUND(B38-E38,1)= 0, "Match","No Match") -> Match | I38: =IF(ROUND(C38-F38,1)= 0, "Match","No Match") -> Match
A39: Long-term business loans:23350 LT - CCJ True, LLC Loan | C39: ='23350 - CCJ True Loan'!N6 -> 332358.97 | F39: 332358.97 | G39: =(B39+C39)-(E39+F39) -> -0.00054299622 | H39: =IF(ROUND(B39-E39,1)= 0, "Match","No Match") -> Match | I39: =IF(ROUND(C39-F39,1)= 0, "Match","No Match") -> Match
A40: Long-term business loans:23400 LT - CCJ True, LLC Loan (2) | C40: ='23400 - CCJ True Loan (2)'!N6 -> 49058.992 | F40: 49058.99 | G40: =(B40+C40)-(E40+F40) -> 0.0018441177 | H40: =IF(ROUND(B40-E40,1)= 0, "Match","No Match") -> Match | I40: =IF(ROUND(C40-F40,1)= 0, "Match","No Match") -> Match
A41: 30000 Paid In Capital - CCM | C41: =F41 -> 300000 | F41: 300000 | G41: =(B41+C41)-(E41+F41) -> 0 | H41: =IF(ROUND(B41-E41,1)= 0, "Match","No Match") -> Match | I41: =IF(ROUND(C41-F41,1)= 0, "Match","No Match") -> Match
A42: 31000 Paid in Capital - SoCal Nautical | C42: =F42 -> 49823.62 | F42: 49823.62 | G42: =(B42+C42)-(E42+F42) -> 0 | H42: =IF(ROUND(B42-E42,1)= 0, "Match","No Match") -> Match | I42: =IF(ROUND(C42-F42,1)= 0, "Match","No Match") -> Match
A43: 32000 Shareholder Distributions - CCM Integrated | B43: =E43 -> 21000 | E43: 21000 | G43: =(B43+C43)-(E43+F43) -> 0 | H43: =IF(ROUND(B43-E43,1)= 0, "Match","No Match") -> Match | I43: =IF(ROUND(C43-F43,1)= 0, "Match","No Match") -> Match
A44: 34000 Retained Earnings | B44: =E44 -> 794004.76 | E44: 794004.76 | G44: =(B44+C44)-(E44+F44) -> 0 | H44: =IF(ROUND(B44-E44,1)= 0, "Match","No Match") -> Match | I44: =IF(ROUND(C44-F44,1)= 0, "Match","No Match") -> Match

Sheet 10000 - BofA CHK 1020
A1: 10000 - Bank of America Checking 1020 | O1: **add screenshot of bank stmt
A3: Beginning Balance | O3: 62443.29
A5: Checks & Payments | O5: -93222.5
A8: Deposits & Credits | O8: 56723.41
A10: Service Charges | O10: 0
A12: Statement Balance | O12: =O3+O5+O8+O10 -> 25944.2
A14: Uncleared Transactions | O14: =G41 -> 0
A16: Cleared Balance Uncleared Transactions Checks and Payments - 0 items
A41: Total Checks and Payments | G41: =SUM(F17:F39) -> 0
A42: Total Uncleared Transactions | G42: =G41 -> 0
A43: Expand for detail
A45: Book Balance | O45: =O12+O14 -> 25944.2

Sheet 11000 Accounts Receivable
A1: PLEASE REFER TO PAYSIMPLE QB WORKPAPER
B5: Bank Deposits | C5: 0 | D5: Hits in next month
B6: initiation fees not paid | C6: 0
B7: Not Cleared | C7: 0
B8: WRITE OFF AMOUNT | C8: 0
B11: A/R ENDING BALANCE | C11: 0
B12: G/L | C12: 0
B13: Difference | C13: 0

Sheet 11600 - Prepaid Expenses
A1: GL Date | B1: Name | C1: Amount | D1: Period | E1: Total Amortized | F1: 45261 | G1: 45292 | H1: 45323 | I1: 45352 | J1: 45383 | K1: 45413 | L1: 45444 | M1: 45474 | N1: 45505 | O1: 45536 | P1: 45566 | Q1: 45597 | R1: 45627 | S1: 45658 | T1: 45689 | U1: 45717 | V1: 45748 | W1: 45778 | X1: 45809 | Y1: 45839 | Z1: 45870 | AA1: 45901 | AB1: 45931 | AC1: 45962 | AD1: 45992 | AE1: 46023 | AF1: 46054 | AG1: 46082 | AH1: 46113 | AI1: 46143 | AJ1: 46174 | AK1: 46204 | AL1: 46235 | AM1: 46266 | AN1: 46296 | AO1: 46327 | AP1: 46357 | AQ1: remaining
A2: 45627 | B2: First Insurance | C2: 39809.21 | D2: 1/1/25-12/31-2025 | E2: =SUM(G2:AD2) -> 39809.21 | S2: =C2/12 -> 3317.4342 | T2: =S2 -> 3317.4342 | U2: =T2 -> 3317.4342 | V2: =U2 -> 3317.4342 | W2: =V2 -> 3317.4342 | X2: =W2 -> 3317.4342 | Y2: =X2 -> 3317.4342 | Z2: =Y2 -> 3317.4342 | AA2: =Z2 -> 3317.4342 | ... AD2: =AC2 -> 3317.4342 | AQ2: =C2-SUM(F2:AD2) -> 0
A3: 45864 | B3: GoDaddy Renewal | C3: 1159.06 | D3: 45870 | E3: =SUM(G3:AD3) -> 241.47083 | Z3: =C3/24 -> 48.294167 | AA3: =Z3 -> 48.294167 | AB3: =AA3 -> 48.294167 | AC3: =AB3 -> 48.294167 | AD3: =AC3 -> 48.294167 | AE3: =AD3 -> 48.294167 | AF3: =AE3 -> 48.294167 | AG3: =AF3 -> 48.294167 | AH3: =AG3 -> 48.294167 | ... AP3: =AO3 -> 48.294167 | AQ3: =C3-SUM(F3:AD3) -> 917.58917
A4: 45873 | B4: STATE COMP INSURANCE | C4: 1402.46 | D4: 45901 | E4: =SUM(G4:AD4) -> 1402.46 | AA4: 288.43 | AB4: 288.43 | AC4: =825.6-226 -> 599.6 | AD4: 226 | AQ4: =C4-SUM(F4:AD4) -> 0
A5: 45961 | B5: First Insurance (Adjustment) | C5: =-'21350 - Insurance Payable'!M44 -> -1942.5955 | D5: 10/1/25-12/31/25 | E5: =SUM(G5:AD5) -> -1942.6 | AB5: =-1942.6/3 -> -647.53333 | AC5: =AB5 -> -647.53333 | AD5: =AC5 -> -647.53333 | AQ5: =C5-SUM(F5:AD5) -> 0.0045322752
A6: 45991 | B6: First Insurance | C6: 38908.981 | D6: 1/1/26-12/31-2026 | E6: =SUM(G6:AD6) -> 0 | AE6: =38908.98/12 -> 3242.415 | AF6: =AE6 -> 3242.415 | AG6: =AF6 -> 3242.415 | AH6: =AG6 -> 3242.415 | AI6: =AH6 -> 3242.415 | AJ6: =AI6 -> 3242.415 | AK6: =AJ6 -> 3242.415 | AL6: =AK6 -> 3242.415 | AM6: =AL6 -> 3242.415 | ... AP6: =AO6 -> 3242.415 | AQ6: =C6-SUM(F6:AD6) -> 38908.981
C7: =SUM(C2:C6) -> 79337.116 | E7: =SUM(E2:E6) -> 39510.541 | F7: 0 | G7: =SUM(G2:G6) -> 0 | H7: =SUM(H2:H6) -> 0 | I7: =SUM(I2:I6) -> 0 | J7: =SUM(J2:J6) -> 0 | K7: =SUM(K2:K6) -> 0 | L7: =SUM(L2:L6) -> 0 | M7: =SUM(M2:M6) -> 0 | N7: =SUM(N2:N6) -> 0 | ... AQ7: =SUM(AQ2:AQ6) -> 39826.575
X9: The balance is now a payable - paid this on 12/30/25.
D12: Total Prepaid | E12: =C7-E7 -> 39826.575
D13: Sitting in G/L | E13: 39826.57
D14: Difference | E14: =E12-E13 -> 0.0049544402
X30: Expense prior payroll journal matches premium premium charge of $356.01

Sheet 11600 - Prepaid Expenses (OLD)
A1: GL Date | B1: Name | C1: Amount | D1: Period | E1: Total Amortized | F1: 45261 | G1: 45292 | H1: 45323 | I1: 45352 | J1: 45383 | K1: 45413 | L1: 45444 | M1: 45474 | N1: 45505 | O1: 45536 | P1: 45566 | Q1: 45597 | R1: 45627 | S1: 45658 | T1: 45689 | U1: 45717 | V1: 45748 | W1: 45778 | X1: 45809 | Y1: 45839 | Z1: 45870 | AA1: 45901 | AB1: 45931 | AC1: 45962 | AD1: 45992 | AE1: 46023 | AF1: 44958 | AG1: remaining
A2: 45277 | B2: First Insurance | C2: 51710 | D2: 1/1/24-12/31/24 | E2: =SUM(G2:AD2) -> 51710 | G2: 4309.17 | H2: =G2 -> 4309.17 | I2: =H2 -> 4309.17 | J2: =I2 -> 4309.17 | K2: =J2 -> 4309.17 | L2: =K2 -> 4309.17 | M2: =L2 -> 4309.17 | N2: =M2 -> 4309.17 | O2: =N2 -> 4309.17 | ... Q2: =P2 -> 4309.17 | R2: =Q2-0.04 -> 4309.13 | AG2: =C2-SUM(F2:AF2) -> 0
A3: 45488 | B3: First Insurance | C3: -993.2 | D3: 7/1-12/31 | E3: =SUM(G3:AD3) -> -993.2 | M3: -165.53333 | N3: -165.53333 | O3: -165.53333 | P3: -165.53333 | Q3: -165.53333 | R3: -165.53333 | AG3: =C3-SUM(F3:AF3) -> 0
A4: 45627 | B4: First Insurance | C4: 39809.21 | D4: 1/1/25-12/31-2025 | E4: =SUM(G4:AD4) -> 39809.21 | S4: =C4/12 -> 3317.4342 | T4: =S4 -> 3317.4342 | U4: =T4 -> 3317.4342 | V4: =U4 -> 3317.4342 | W4: =V4 -> 3317.4342 | X4: =W4 -> 3317.4342 | Y4: =X4 -> 3317.4342 | Z4: =Y4 -> 3317.4342 | AA4: =Z4 -> 3317.4342 | ... AD4: =AC4 -> 3317.4342 | AG4: =C4-SUM(F4:AF4) -> 0
A5: 45656 | B5: STATE COMP INSURANCE | C5: 501.75 | D5: 45658 | E5: =SUM(G5:AD5) -> 501.75 | S5: =C5 -> 501.75 | AG5: =C5-SUM(F5:AF5) -> 0
A6: 45747 | B6: AURA ACCOUNTING | C6: 2287.69 | D6: 45748 | E6: =SUM(G6:AD6) -> 2287.69 | V6: =C6 -> 2287.69 | AG6: =C6-SUM(F6:AF6) -> 0
A7: 45775 | B7: Newport International Boat Show | C7: 5870.57 | D7: 45778 | E7: =SUM(G7:AD7) -> 5870.57 | W7: =C7 -> 5870.57 | AG7: =C7-SUM(F7:AF7) -> 0
A8: 45864 | B8: GoDaddy Renewal | C8: 1159.06 | D8: 45870 | E8: =SUM(G8:AD8) -> 241.47083 | Z8: =C8/24 -> 48.294167 | AA8: =Z8 -> 48.294167 | AB8: =AA8 -> 48.294167 | AC8: =AB8 -> 48.294167 | AD8: =AC8 -> 48.294167 | AE8: =AD8 -> 48.294167 | AF8: =AE8 -> 48.294167 | AG8: =C8-SUM(F8:AF8) -> 821.00083
A9: 45873 | B9: STATE COMP INSURANCE | C9: 1402.46 | D9: 45901 | E9: =SUM(G9:AD9) -> 1402.46 | AA9: 288.43 | AB9: 288.43 | AC9: =825.6-226 -> 599.6 | AD9: 226 | AG9: =C9-SUM(F9:AF9) -> 0
A10: 45961 | B10: AURA ACCOUNTING | C10: 2402.07 | D10: 45962 | E10: =SUM(G10:AD10) -> 2402.07 | AC10: 2402.07 | AG10: =C10-SUM(F10:AF10) -> 0
A11: 45961 | B11: First Insurance (Adjustment) | C11: =-'21350 - Insurance Payable'!M44 -> -1942.5955 | D11: 10/1/25-12/31/25 | E11: =SUM(G11:AD11) -> -1942.6 | AB11: =-1942.6/3 -> -647.53333 | AC11: =AB11 -> -647.53333 | AD11: =AC11 -> -647.53333 | AG11: =C11-SUM(F11:AF11) -> 0.0045322752
A12: 45991 | B12: First Insurance | C12: 38908.981 | D12: 1/1/26-12/31-2026 | E12: =SUM(G12:AD12) -> 0 | AE12: =38908.98/12 -> 3242.415 | AF12: =AE12 -> 3242.415 | AG12: =C12-SUM(F12:AF12) -> 32424.151
E13: =SUM(G13:AD13) -> 0 | AG13: =C13-SUM(F13:AF13) -> 0
C14: =SUM(C2:C13) -> 141116 | E14: =SUM(E2:E13) -> 101289.42 | F14: 0 | G14: =SUM(G2:G13) -> 4309.17 | H14: =SUM(H2:H13) -> 4309.17 | I14: =SUM(I2:I13) -> 4309.17 | J14: =SUM(J2:J13) -> 4309.17 | K14: =SUM(K2:K13) -> 4309.17 | L14: =SUM(L2:L13) -> 4309.17 | M14: =SUM(M2:M13) -> 4143.6367 | N14: =SUM(N2:N13) -> 4143.6367 | ... AF14: =SUM(AF2:AF13) -> 3290.7092
X16: The balance is now a payable - paid this on 12/30/25.
D19: Total Prepaid | E19: =C14-E14 -> 39826.575
D20: Sitting in G/L | E20: 39826.57
D21: Difference | E21: =E19-E20 -> 0.0049544403
X37: Expense prior payroll journal matches premium premium charge of $356.01

Sheet 15500-Acc Depreciation
A2: Assets
B3: Life | C3: 44439 | D3: =EOMONTH(C3,1) -> 44469 | E3: =EOMONTH(D3,1) -> 44500 | F3: =EOMONTH(E3,1) -> 44530 | G3: =EOMONTH(F3,1) -> 44561 | H3: =EOMONTH(G3,1) -> 44592 | I3: =EOMONTH(H3,1) -> 44620 | J3: =EOMONTH(I3,1) -> 44651 | K3: =EOMONTH(J3,1) -> 44681 | ... EQ3: =EOMONTH(EP3,1) -> 48822
A4: MANITOU 25 OASIS | B4: 7 | C4: 66464 | D4: =C4 -> 66464 | E4: =D4 -> 66464 | F4: =E4 -> 66464 | G4: =F4 -> 66464 | H4: =G4 -> 66464 | I4: =H4 -> 66464 | J4: =I4 -> 66464 | K4: =J4 -> 66464 | ... EQ4: =EP4 -> 66464
A5: SEA RAY 34 SUNDANCER | B5: 7 | C5: 65000 | D5: =C5 -> 65000 | E5: =D5 -> 65000 | F5: =E5 -> 65000 | G5: =F5 -> 65000 | H5: =G5 -> 65000 | I5: =H5 -> 65000 | J5: =I5 -> 65000 | K5: =J5 -> 65000 | ... AJ5: =AI5 -> 65000
A6: PACIFIC BOAT CLUB FLEET | B6: 7 | H6: 150000 | I6: =H6 -> 150000 | J6: =I6 -> 150000 | K6: =J6 -> 150000 | L6: =K6 -> 150000 | M6: =L6 -> 150000 | N6: =M6 -> 150000 | O6: =N6 -> 150000 | P6: =O6 -> 150000 | ... T6: =S6 -> 150000 | U6: =T6-32069 -> 117931 | V6: =U6 -> 117931 | W6: =V6 -> 117931 | X6: =W6-27648 -> 90283 | Y6: =X6 -> 90283 | Z6: =Y6 -> 90283 | AA6: =Z6 -> 90283 | AB6: =AA6 -> 90283 | AC6: =AB6 -> 90283 | AD6: =AC6 -> 90283 | AE6: =AD6 -> 90283 | AF6: =AE6 -> 90283 | ... AO6: =AN6 -> 90283 | AP6: =AO6-22063.31 -> 68219.69 | AQ6: =AP6 -> 68219.69 | AR6: =AQ6 -> 68219.69 | AS6: =AR6 -> 68219.69 | AT6: =AS6 -> 68219.69 | AU6: =AT6 -> 68219.69 | AV6: =AU6 -> 68219.69 | AW6: =AV6 -> 68219.69 | AX6: =AW6 -> 68219.69 | ... EQ6: =EP6 -> 68219.69
A7: BENETEAU FLYER 9 | B7: 7 | I7: 263992.78 | J7: =I7 -> 263992.78 | K7: =J7 -> 263992.78 | L7: =K7 -> 263992.78 | M7: =L7 -> 263992.78 | N7: =M7 -> 263992.78 | O7: =N7 -> 263992.78 | P7: =O7 -> 263992.78 | Q7: =P7 -> 263992.78 | ... EQ7: =EP7 -> 263992.78
A8: AXOPAR SUNTOP 37 | B8: 7 | J8: 269900 | K8: =J8 -> 269900 | L8: =K8 -> 269900 | M8: =L8 -> 269900 | N8: =M8 -> 269900 | O8: =N8 -> 269900 | P8: =O8 -> 269900 | Q8: =P8 -> 269900 | R8: =Q8 -> 269900 | ... EQ8: =EP8 -> 269900
A9: Axopar T-Top 28 | B9: 7 | Z9: 140000 | AA9: =Z9 -> 140000 | AB9: =AA9 -> 140000 | AC9: =AB9 -> 140000 | AD9: =AC9 -> 140000 | AE9: =AD9 -> 140000 | AF9: =AE9 -> 140000 | AG9: =AF9 -> 140000 | AH9: =AG9 -> 140000 | ... EQ9: =EP9 -> 140000
A10: NX 340 Sport Cruisr | B10: 7 | Z10: 272754.5 | AA10: =Z10 -> 272754.5 | AB10: =AA10 -> 272754.5 | AC10: =AB10 -> 272754.5 | AD10: =AC10 -> 272754.5 | AE10: =AD10 -> 272754.5 | AF10: =AE10 -> 272754.5 | AG10: =AF10 -> 272754.5 | AH10: =AG10 -> 272754.5 | ... EQ10: =EP10 -> 272754.5
A12: Total | C12: =SUM(C4:C11) -> 131464 | D12: =SUM(D4:D11) -> 131464 | E12: =SUM(E4:E11) -> 131464 | F12: =SUM(F4:F11) -> 131464 | G12: =SUM(G4:G11) -> 131464 | H12: =SUM(H4:H11) -> 281464 | I12: =SUM(I4:I11) -> 545456.78 | J12: =SUM(J4:J11) -> 815356.78 | ... EQ12: =SUM(EQ4:EQ11) -> 1081331
A15: Monthly Depreciation
C17: =C3 -> 44439 | D17: =EOMONTH(C17,1) -> 44469 | E17: =EOMONTH(D17,1) -> 44500 | F17: =EOMONTH(E17,1) -> 44530 | G17: =EOMONTH(F17,1) -> 44561 | H17: =EOMONTH(G17,1) -> 44592 | I17: =EOMONTH(H17,1) -> 44620 | J17: =EOMONTH(I17,1) -> 44651 | K17: =EOMONTH(J17,1) -> 44681 | ... EQ17: =EOMONTH(EP17,1) -> 48822
A18: MANITOU 25 OASIS | C18: =IFERROR(C4/(12*$B4),0)+5538.67 -> 6329.9081 | D18: =IFERROR(D4/(12*$B4),0) -> 791.2381 | E18: =IFERROR(E4/(12*$B4),0) -> 791.2381 | F18: =IFERROR(F4/(12*$B4),0) -> 791.2381 | G18: =IFERROR(G4/(12*$B4),0) -> 791.2381 | H18: =IFERROR(H4/(12*$B4),0) -> 791.2381 | I18: =IFERROR(I4/(12*$B4),0) -> 791.2381 | J18: =IFERROR(J4/(12*$B4),0) -> 791.2381 | K18: =IFERROR(K4/(12*$B4),0) -> 791.2381 | ... CA18: =IFERROR(CA4/(12*$B4),0) -> 791.2381
A19: SEA RAY 34 SUNDANCER | C19: 6190.47 | D19: =IFERROR(D5/(12*$B5),0) -> 773.80952 | E19: =IFERROR(E5/(12*$B5),0) -> 773.80952 | F19: =IFERROR(F5/(12*$B5),0) -> 773.80952 | G19: =IFERROR(G5/(12*$B5),0) -> 773.80952 | H19: =IFERROR(H5/(12*$B5),0) -> 773.80952 | I19: =IFERROR(I5/(12*$B5),0) -> 773.80952 | J19: =IFERROR(J5/(12*$B5),0) -> 773.80952 | K19: =IFERROR(K5/(12*$B5),0) -> 773.80952 | ... EQ19: =IFERROR(EQ5/(12*$B5),0) -> 0
A20: PACIFIC BOAT CLUB FLEET | D20: =IFERROR(D6/(12*$B6),0) -> 0 | E20: =IFERROR(E6/(12*$B6),0) -> 0 | F20: =IFERROR(F6/(12*$B6),0) -> 0 | G20: =IFERROR(G6/(12*$B6),0) -> 0 | H20: =IFERROR(H6/(12*$B6),0) -> 1785.7143 | I20: =IFERROR(I6/(12*$B6),0) -> 1785.7143 | J20: =IFERROR(J6/(12*$B6),0) -> 1785.7143 | K20: =IFERROR(K6/(12*$B6),0) -> 1785.7143 | ... T20: =IFERROR(T6/(12*$B6),0) -> 1785.7143 | U20: =IFERROR(U6/(12*$B6),0)+381.77 -> 1785.7105 | V20: =IFERROR(V6/(12*$B6),0) -> 1403.9405 | W20: =IFERROR(W6/(12*$B6),0) -> 1403.9405 | X20: =IFERROR(X6/(12*$B6),0)+329.14 -> 1403.9376 | Y20: =IFERROR(Y6/(12*$B6),0) -> 1074.7976 | Z20: =IFERROR(Z6/(12*$B6),0) -> 1074.7976 | AA20: =IFERROR(AA6/(12*$B6),0) -> 1074.7976 | AB20: =IFERROR(AB6/(12*$B6),0) -> 1074.7976 | AC20: =IFERROR(AC6/(12*$B6),0) -> 1074.7976 | AD20: =IFERROR(AD6/(12*$B6),0) -> 1074.7976 | AE20: =IFERROR(AE6/(12*$B6),0) -> 1074.7976 | AF20: =IFERROR(AF6/(12*$B6),0) -> 1074.7976 | ... AO20: =IFERROR(AO6/(12*$B6),0) -> 1074.7976 | AP20: 1074.8 | AQ20: 902.82 | AR20: 902.82 | AS20: 902.82 | AT20: 902.82 | AU20: 902.82 | AV20: 902.82 | AW20: 902.82 | AX20: 902.82 | AY20: 902.82 | AZ20: 902.82 | BA20: 902.82 | BB20: 902.82 | BC20: 902.82 | BD20: 902.82 | BE20: 902.82 | BF20: 902.82 | BG20: 902.82 | BH20: 902.82 | BI20: 902.82 | BJ20: 902.82 | BK20: 902.82 | BL20: 902.82 | BM20: 902.82 | BN20: 902.82 | BO20: 902.82 | BP20: 902.82 | BQ20: 902.82 | BR20: 902.82 | BS20: 902.82 | BT20: 902.82 | BU20: 902.82 | BV20: 902.82 | BW20: 902.82 | BX20: 902.82 | BY20: 902.82 | BZ20: 902.82 | CA20: 902.82 | CB20: 902.82 | CC20: 902.82 | CD20: 902.82 | CE20: 902.82 | CF20: 902.82 | CG20: 902.82 | CH20: 902.82 | CI20: 902.82 | CJ20: 902.82 | CK20: 902.82 | CL20: 902.82 | CM20: 902.82
A21: BENETEAU FLYER 9 | D21: =IFERROR(D7/(12*$B7),0) -> 0 | E21: =IFERROR(E7/(12*$B7),0) -> 0 | F21: =IFERROR(F7/(12*$B7),0) -> 0 | G21: =IFERROR(G7/(12*$B7),0) -> 0 | H21: =IFERROR(H7/(12*$B7),0) -> 0 | I21: =IFERROR(I7/(12*$B7),0) -> 3142.7712 | J21: =IFERROR(J7/(12*$B7),0) -> 3142.7712 | K21: =IFERROR(K7/(12*$B7),0) -> 3142.7712 | ... CN21: =IFERROR(CN7/(12*$B7),0) -> 3142.7712
A22: AXOPAR SUNTOP 37 | D22: =IFERROR(D8/(12*$B8),0) -> 0 | E22: =IFERROR(E8/(12*$B8),0) -> 0 | F22: =IFERROR(F8/(12*$B8),0) -> 0 | G22: =IFERROR(G8/(12*$B8),0) -> 0 | H22: =IFERROR(H8/(12*$B8),0) -> 0 | I22: =IFERROR(I8/(12*$B8),0) -> 0 | J22: =IFERROR(J8/(12*$B8),0) -> 3213.0952 | K22: =IFERROR(K8/(12*$B8),0) -> 3213.0952 | ... CO22: =IFERROR(CO8/(12*$B8),0) -> 3213.0952
A23: Axopar T-Top 28 | D23: =IFERROR(D9/(12*$B9),0) -> 0 | E23: =IFERROR(E9/(12*$B9),0) -> 0 | F23: =IFERROR(F9/(12*$B9),0) -> 0 | G23: =IFERROR(G9/(12*$B9),0) -> 0 | H23: =IFERROR(H9/(12*$B9),0) -> 0 | I23: =IFERROR(I9/(12*$B9),0) -> 0 | J23: =IFERROR(J9/(12*$B9),0) -> 0 | K23: =IFERROR(K9/(12*$B9),0) -> 0 | ... DE23: =IFERROR(DE9/(12*$B9),0) -> 1666.6667
A24: NX 340 Sport Cruisr | D24: =IFERROR(D10/(12*$B10),0) -> 0 | E24: =IFERROR(E10/(12*$B10),0) -> 0 | F24: =IFERROR(F10/(12*$B10),0) -> 0 | G24: =IFERROR(G10/(12*$B10),0) -> 0 | H24: =IFERROR(H10/(12*$B10),0) -> 0 | J24: =IFERROR(J10/(12*$B10),0) -> 0 | K24: =IFERROR(K10/(12*$B10),0) -> 0 | L24: =IFERROR(L10/(12*$B10),0) -> 0 | M24: =IFERROR(M10/(12*$B10),0) -> 0 | N24: =IFERROR(N10/(12*$B10),0) -> 0 | O24: =IFERROR(O10/(12*$B10),0) -> 0 | P24: =IFERROR(P10/(12*$B10),0) -> 0 | Q24: =IFERROR(Q10/(12*$B10),0) -> 0 | ... DE24: =IFERROR(DE10/(12*$B10),0) -> 3247.0774
A28: Total Depreciation | C28: =SUM(C18:C27) -> 12520.378 | D28: =SUM(D18:D27) -> 1565.0476 | E28: =SUM(E18:E27) -> 1565.0476 | F28: =SUM(F18:F27) -> 1565.0476 | G28: =SUM(G18:G27) -> 1565.0476 | H28: =SUM(H18:H27) -> 3350.7619 | I28: =SUM(I18:I27) -> 6493.5331 | J28: =SUM(J18:J27) -> 9706.6283 | ... EQ28: =SUM(EQ18:EQ27) -> 0
X30: =W20-X20 -> 0.0028571429
A31: Acc Depreciation
C33: =C17 -> 44439 | D33: =EOMONTH(C33,1) -> 44469 | E33: =EOMONTH(D33,1) -> 44500 | F33: =EOMONTH(E33,1) -> 44530 | G33: =EOMONTH(F33,1) -> 44561 | H33: =EOMONTH(G33,1) -> 44592 | I33: =EOMONTH(H33,1) -> 44620 | J33: =EOMONTH(I33,1) -> 44651 | K33: =EOMONTH(J33,1) -> 44681 | ... EQ33: =EOMONTH(EP33,1) -> 48822
A34: MANITOU 25 OASIS | C34: =C18+B34 -> 6329.9081 | D34: =D18+C34 -> 7121.1462 | E34: =E18+D34 -> 7912.3843 | F34: =F18+E34 -> 8703.6224 | G34: =G18+F34 -> 9494.8605 | H34: =H18+G34 -> 10286.099 | I34: =I18+H34 -> 11077.337 | J34: =J18+I34 -> 11868.575 | ... EQ34: =EQ18+EP34 -> 66464.003
A35: SEA RAY 34 SUNDANCER | C35: =C19+B35 -> 6190.47 | D35: =D19+C35 -> 6964.2795 | E35: =E19+D35 -> 7738.089 | F35: =F19+E35 -> 8511.8986 | G35: =G19+F35 -> 9285.7081 | H35: =H19+G35 -> 10059.518 | I35: =I19+H35 -> 10833.327 | J35: =J19+I35 -> 11607.137 | ... AJ35: =AJ19+AI35 -> 31726.184
A36: PACIFIC BOAT CLUB FLEET | C36: =C20+B36 -> 0 | D36: =D20+C36 -> 0 | E36: =E20+D36 -> 0 | F36: =F20+E36 -> 0 | G36: =G20+F36 -> 0 | H36: =H20+G36 -> 1785.7143 | I36: =I20+H36 -> 3571.4286 | J36: =J20+I36 -> 5357.1429 | ... T36: =T20+S36 -> 23214.286 | U36: =U20+T36-3869.05 -> 21130.946 | V36: =V20+U36 -> 22534.887 | W36: =W20+V36 -> 23938.827 | X36: =X20+W36-5595.43-1475.78 -> 18271.555 | Y36: =Y20+X36 -> 19346.352 | Z36: =Z20+Y36 -> 20421.15 | AA36: =AA20+Z36 -> 21495.948 | AB36: =AB20+AA36 -> 22570.745 | AC36: =AC20+AB36 -> 23645.543 | AD36: =AD20+AC36 -> 24720.34 | AE36: =AE20+AD36 -> 25795.138 | AF36: =AF20+AE36 -> 26869.936 | ... AO36: =AO20+AN36 -> 36543.114 | AP36: =AP20+AO36-9193.05 -> 28424.864 | AQ36: =AQ20+AP36 -> 29327.684 | AR36: =AR20+AQ36 -> 30230.504 | AS36: =AS20+AR36 -> 31133.324 | AT36: =AT20+AS36 -> 32036.144 | AU36: =AU20+AT36 -> 32938.964 | AV36: =AV20+AU36 -> 33841.784 | AW36: =AW20+AV36 -> 34744.604 | AX36: =AX20+AW36 -> 35647.424 | ... EQ36: =EQ20+EP36 -> 72663.044
A37: BENETEAU FLYER 9 | C37: =C21+B37 -> 0 | D37: =D21+C37 -> 0 | E37: =E21+D37 -> 0 | F37: =F21+E37 -> 0 | G37: =G21+F37 -> 0 | H37: =H21+G37 -> 0 | I37: =I21+H37 -> 3142.7712 | J37: =J21+I37 -> 6285.5424 | ... EQ37: =EQ21+EP37 -> 263992.78
A38: AXOPAR SUNTOP 37 | C38: =C22+B38 -> 0 | D38: =D22+C38 -> 0 | E38: =E22+D38 -> 0 | F38: =F22+E38 -> 0 | G38: =G22+F38 -> 0 | H38: =H22+G38 -> 0 | I38: =I22+H38 -> 0 | J38: =J22+I38 -> 3213.0952 | ... EQ38: =EQ22+EP38 -> 269900
A39: Axopar T-Top 28 | C39: =C23+B39 -> 0 | D39: =D23+C39 -> 0 | E39: =E23+D39 -> 0 | F39: =F23+E39 -> 0 | G39: =G23+F39 -> 0 | H39: =H23+G39 -> 0 | I39: =I23+H39 -> 0 | J39: =J23+I39 -> 0 | ... EQ39: =EQ23+EP39 -> 140000
A40: NX 340 Sport Cruisr | C40: =C24+B40 -> 0 | D40: =D24+C40 -> 0 | E40: =E24+D40 -> 0 | F40: =F24+E40 -> 0 | G40: =G24+F40 -> 0 | H40: =H24+G40 -> 0 | I40: =I24+H40 -> 0 | J40: =J24+I40 -> 0 | ... EQ40: =EQ24+EP40 -> 272754.5
A43: Total Depreciation | C43: =SUM(C34:C40) -> 12520.378 | D43: =SUM(D34:D40) -> 14085.426 | E43: =SUM(E34:E40) -> 15650.473 | F43: =SUM(F34:F40) -> 17215.521 | G43: =SUM(G34:G40) -> 18780.569 | H43: =SUM(H34:H40) -> 22131.33 | I43: =SUM(I34:I40) -> 28624.864 | J43: =SUM(J34:J40) -> 38331.492 | ... EQ43: =SUM(EQ34:EQ40) -> 1085774.3
A46: NBV
C48: =C33 -> 44439 | D48: =EOMONTH(C48,1) -> 44469 | E48: =EOMONTH(D48,1) -> 44500 | F48: =EOMONTH(E48,1) -> 44530 | G48: =EOMONTH(F48,1) -> 44561 | H48: =EOMONTH(G48,1) -> 44592 | I48: =EOMONTH(H48,1) -> 44620 | J48: =EOMONTH(I48,1) -> 44651 | K48: =EOMONTH(J48,1) -> 44681 | ... EQ48: =EOMONTH(EP48,1) -> 48822
A49: MANITOU 25 OASIS | C49: =C4-C34 -> 60134.092 | D49: =D4-D34 -> 59342.854 | E49: =E4-E34 -> 58551.616 | F49: =F4-F34 -> 57760.378 | G49: =G4-G34 -> 56969.14 | H49: =H4-H34 -> 56177.901 | I49: =I4-I34 -> 55386.663 | J49: =J4-J34 -> 54595.425 | ... EQ49: =EQ4-EQ34 -> -0.0033333332
A50: SEA RAY 34 SUNDANCER | C50: =C5-C35 -> 58809.53 | D50: =D5-D35 -> 58035.72 | E50: =E5-E35 -> 57261.911 | F50: =F5-F35 -> 56488.101 | G50: =G5-G35 -> 55714.292 | H50: =H5-H35 -> 54940.482 | I50: =I5-I35 -> 54166.673 | J50: =J5-J35 -> 53392.863 | ... EQ50: =EQ5-EQ35 -> 0
A51: PACIFIC BOAT CLUB FLEET | C51: =C6-C36 -> 0 | D51: =D6-D36 -> 0 | E51: =E6-E36 -> 0 | F51: =F6-F36 -> 0 | G51: =G6-G36 -> 0 | H51: =H6-H36 -> 148214.29 | I51: =I6-I36 -> 146428.57 | J51: =J6-J36 -> 144642.86 | ... EQ51: =EQ6-EQ36 -> -4443.3543
A52: BENETEAU FLYER 9 | C52: =C7-C37 -> 0 | D52: =D7-D37 -> 0 | E52: =E7-E37 -> 0 | F52: =F7-F37 -> 0 | G52: =G7-G37 -> 0 | H52: =H7-H37 -> 0 | I52: =I7-I37 -> 260850.01 | J52: =J7-J37 -> 257707.24 | ... EQ52: =EQ7-EQ37 -> 0
A53: AXOPAR SUNTOP 37 | C53: =C8-C38 -> 0 | D53: =D8-D38 -> 0 | E53: =E8-E38 -> 0 | F53: =F8-F38 -> 0 | G53: =G8-G38 -> 0 | H53: =H8-H38 -> 0 | I53: =I8-I38 -> 0 | J53: =J8-J38 -> 266686.9 | ... EQ53: =EQ8-EQ38 -> 0
A54: Axopar T-Top 28 | C54: =C9-C39 -> 0 | D54: =D9-D39 -> 0 | E54: =E9-E39 -> 0 | F54: =F9-F39 -> 0 | G54: =G9-G39 -> 0 | H54: =H9-H39 -> 0 | I54: =I9-I39 -> 0 | J54: =J9-J39 -> 0 | ... EQ54: =EQ9-EQ39 -> 0
A55: NX 340 Sport Cruisr | C55: =C10-C40 -> 0 | D55: =D10-D40 -> 0 | E55: =E10-E40 -> 0 | F55: =F10-F40 -> 0 | G55: =G10-G40 -> 0 | H55: =H10-H40 -> 0 | I55: =I10-I40 -> 0 | J55: =J10-J40 -> 0 | ... EQ55: =EQ10-EQ40 -> 5.8207661e-10
A57: Total NBV | C57: =SUM(C49:C55) -> 118943.62 | D57: =SUM(D49:D55) -> 117378.57 | E57: =SUM(E49:E55) -> 115813.53 | F57: =SUM(F49:F55) -> 114248.48 | G57: =SUM(G49:G55) -> 112683.43 | H57: =SUM(H49:H55) -> 259332.67 | I57: =SUM(I49:I55) -> 516831.92 | J57: =SUM(J49:J55) -> 777025.29 | ... BR57: =SUM(BR49:BR55) -> 356315.18 | BS57: =SUM(BS49:BS55)-8932.46 -> 334419.05 | BT57: =SUM(BT49:BT55)-7145.97 -> 323241.87 | BU57: =SUM(BU49:BU55)-5359.48 -> 312064.69 | BV57: =SUM(BV49:BV55)-3572.99 -> 300887.52 | BW57: =SUM(BW49:BW55)-1786.5 -> 289710.34 | BX57: =SUM(BX49:BX55) -> 278533.17 | BY57: =SUM(BY49:BY55) -> 265569.5 | BZ57: =SUM(BZ49:BZ55) -> 252605.83 | CA57: =SUM(CA49:CA55) -> 239642.16 | CB57: =SUM(CB49:CB55) -> 227469.73 | CC57: =SUM(CC49:CC55) -> 215297.3 | CD57: =SUM(CD49:CD55) -> 203124.87 | CE57: =SUM(CE49:CE55) -> 190952.44 | ... EQ57: =SUM(EQ49:EQ55) -> -4443.3576
A58: Total book Value

Sheet 17000 - Goodwill
A1: Goodwill
A3: Amount | B3: 174500
B4: =15*12 -> 180
A5: Monthly Amortiz | B5: =B3/B4 -> 969.44444
A6: Accumulated Amortiz | B6: =-SUM(B8:B47) -> 38760 | C6: ENDING BALANCE | D6: ACCUM AMORT
C7: =B3 -> 174500
A8: 44409 | B8: -969 | C8: =C7+B8 -> 173531 | D8: =-B8 -> 969
A9: 44440 | B9: -969 | C9: =C8+B9 -> 172562 | D9: =D8-B9 -> 1938
A10: 44470 | B10: -969 | C10: =C9+B10 -> 171593 | D10: =D9-B10 -> 2907
A11: 44501 | B11: -969 | C11: =C10+B11 -> 170624 | D11: =D10-B11 -> 3876
A12: 44531 | B12: -969 | C12: =C11+B12 -> 169655 | D12: =D11-B12 -> 4845
A13: 44562 | B13: -969 | C13: =C12+B13 -> 168686 | D13: =D12-B13 -> 5814
A14: 44593 | B14: -969 | C14: =C13+B14 -> 167717 | D14: =D13-B14 -> 6783
A15: 44621 | B15: -969 | C15: =C14+B15 -> 166748 | D15: =D14-B15 -> 7752
A16: 44652 | B16: -969 | C16: =C15+B16 -> 165779 | D16: =D15-B16 -> 8721
A17: 44682 | B17: -969 | C17: =C16+B17 -> 164810 | D17: =D16-B17 -> 9690
A18: 44713 | B18: -969 | C18: =C17+B18 -> 163841 | D18: =D17-B18 -> 10659
A19: 44743 | B19: -969 | C19: =C18+B19 -> 162872 | D19: =D18-B19 -> 11628
A20: 44774 | B20: -969 | C20: =C19+B20 -> 161903 | D20: =D19-B20 -> 12597
... A48: 45657 | B48: -969 | C48: =C47+B48 -> 134771 | D48: =D47-B48 -> 39729
A49: =EOMONTH(A48,1) -> 45688 | B49: -969 | C49: =C48+B49 -> 133802 | D49: =D48-B49 -> 40698
A50: =EOMONTH(A49,1) -> 45716 | B50: -969 | C50: =C49+B50 -> 132833 | D50: =D49-B50 -> 41667
A51: =EOMONTH(A50,1) -> 45747 | B51: -969 | C51: =C50+B51 -> 131864 | D51: =D50-B51 -> 42636
A52: =EOMONTH(A51,1) -> 45777 | B52: -969 | C52: =C51+B52 -> 130895 | D52: =D51-B52 -> 43605
A53: =EOMONTH(A52,1) -> 45808 | B53: -969 | C53: =C52+B53 -> 129926 | D53: =D52-B53 -> 44574
A54: =EOMONTH(A53,1) -> 45838 | B54: -969 | C54: =C53+B54 -> 128957 | D54: =D53-B54 -> 45543
A55: =EOMONTH(A54,1) -> 45869 | B55: -969 | C55: =C54+B55 -> 127988 | D55: =D54-B55 -> 46512
A56: =EOMONTH(A55,1) -> 45900 | B56: -969 | C56: =C55+B56 -> 127019 | D56: =D55-B56 -> 47481
A57: =EOMONTH(A56,1) -> 45930 | B57: -969 | C57: =C56+B57 -> 126050 | D57: =D56-B57 -> 48450
A58: =EOMONTH(A57,1) -> 45961 | B58: -969 | C58: =C57+B58 -> 125081 | D58: =D57-B58 -> 49419
A59: =EOMONTH(A58,1) -> 45991 | B59: -969 | C59: =C58+B59 -> 124112 | D59: =D58-B59 -> 50388
A60: =EOMONTH(A59,1) -> 46022 | B60: -969 | C60: =C59+B60 -> 123143 | D60: =D59-B60 -> 51357
... A187: =EOMONTH(A186,1) -> 49887 | B187: -969 | C187: =C186+B187 -> 80 | D187: =D186-B187 -> 174420

Sheet 21000 - Accrued Expenses
A1: Accrued Exp
A4: Vendor | B4: Adj T/B | C4: GL Date | D4: Period | E4: Accrued | F4: Date Paid | G4: Paid | H4: Remaining | I4: Notes
A5: Sales Commission | B5: 12186.5 | C5: 45657 | D5: 45657 | E5: =SUM('Sales commission detail'!I2:I20) -> 12186.5 | G5: 12186.5 | H5: =E5-G5 -> 0
A6: Sales Commission | B6: 609 | C6: 45688 | D6: 45688 | E6: ='Sales commission detail'!I21 -> 609 | G6: 609 | H6: =E6-G6 -> 0
A7: Sales Commission | B7: 174.75 | C7: 45688 | D7: 45688 | E7: =B7 -> 174.75 | H7: =E7-G7 -> 174.75
A8: ADP | B8: 468.66 | C8: 45716 | D8: 45716 | E8: =B8 -> 468.66 | F8: 45768 | G8: 468.66 | H8: =E8-G8 -> 0
A9: ADP | B9: 468.66 | C9: 45747 | D9: 45747 | E9: =B9 -> 468.66 | G9: 468.66 | H9: =E9-G9 -> 0
A10: ADP | B10: 468.66 | C10: 45777 | D10: 45777 | E10: =B10 -> 468.66 | G10: 468.66 | H10: =E10-G10 -> 0
A11: Sales Commission | B11: 2375 | C11: 45777 | D11: 45777 | E11: =B11 -> 2375 | H11: =E11-G11 -> 2375
A12: Sales Commission | B12: 600 | C12: 45808 | D12: 45808 | E12: =B12 -> 600 | H12: =E12-G12 -> 600
A13: ADP | B13: 468.66 | C13: 45808 | D13: 45808 | E13: =B13 -> 468.66 | G13: 468.66 | H13: =E13-G13 -> 0
A14: ADP | B14: 468.66 | C14: 45838 | D14: 45838 | E14: =B14 -> 468.66 | F14: 45887 | G14: 468.66 | H14: =E14-G14 -> 0
A15: ADP Tax | B15: 649.59 | E15: =B15 -> 649.59 | G15: 649.59 | H15: =E15-G15 -> 0
A16: STATE COMP | B16: 456.25 | C16: 45869 | D16: 45930 | E16: =B16 -> 456.25 | G16: 456.25 | H16: =E16-G16 -> 0
A17: ADP | B17: 468.66 | C17: 45869 | D17: 45869 | E17: =B17 -> 468.66 | G17: 468.66 | H17: =E17-G17 -> 0
A18: ADP | B18: 468.66 | C18: 45900 | D18: 45900 | E18: =B18 -> 468.66 | G18: 468.66 | H18: =E18-G18 -> 0
A19: ADP | B19: 468.66 | C19: 45930 | D19: 45930 | E19: =B19 -> 468.66 | G19: 468.66 | H19: =E19-G19 -> 0 | I19: reversed all ADP fees
A20: ADP | B20: 468.66 | C20: 45961 | D20: 45961 | E20: =B20 -> 468.66 | G20: 468.66 | H20: =E20-G20 -> 0 | I20: reversed all ADP fees
A21: ADP | B21: 468.66 | C21: 45991 | D21: 45991 | E21: =B21 -> 468.66 | G21: 468.66 | H21: =E21-G21 -> 0 | I21: reversed all ADP fees
H22: =E22-G22 -> 0 | I22: No sales commission in the master sheet for December
A23: Total | B23: =SUM(B5:B12) -> 17351.23 | G23: Prepaid Total | H23: =SUM(H5:H22) -> 3149.75
G25: GL Total | H25: 3149.75
G26: Difference | H26: =H23-H25 -> 0

Sheet Sheet1

Sheet Sales commission detail
A1: Date Sold | B1: Customer name | C1: initiation | D1: commission due | E1: Salesperson | F1: Commission % (Determined by monthly sales volume | G1: Ryan commishpaid | H1: peter and carlos
A2: 45295 | B2: Leon Weathersby and Lauren Hobb | C2: 8500 | D2: 850 | E2: carlos/peter | F2: 0.1 | G2: paid or NA | H2: UNPAID | I2: =D2 -> 850
A3: 45299 | B3: David Durant and Omar Othman | C3: 12250 | D3: 1225 | E3: carlos/peter | F3: 0.1 | G3: paid or NA | H3: UNPAID | I3: 1225
A4: 45301 | B4: Brian Walrod and Skip kingery | C4: 19000 | D4: 1900 | E4: Carlos/peter | F4: 0.1 | G4: paid or NA | H4: UNPAID | I4: 1900
A5: 45340 | B5: Scott Dixon | C5: 12250 | D5: 1250 | E5: Ryan | F5: 0.1 | G5: paid or NA | I5: 0
A6: 45390 | B6: Joe Faruqui | C6: 20000 | D6: 1000 | E6: Ryan | F6: 0.05 | G6: paid or NA | I6: 0
A7: 45392 | B7: Autumn Lemon | C7: 12500 | D7: 625 | E7: Ryan | F7: 0.05 | G7: paid or NA | I7: 0
A8: 45444 | B8: Scott Javore | C8: 8000 | D8: 800 | E8: Peter Carlos | F8: 0.1 | G8: paid or NA | H8: UNPAID | I8: 800
A9: 45426 | B9: Ken Fait and Jimmy Sabatino | C9: 24500 | D9: 1225 | E9: Ryan referral | F9: 0.05 | G9: 1225 | I9: 0
A10: 45444 | B10: Bruce and Jackie Gulbas | C10: 22500 | D10: 2250 | E10: Split | F10: 0.1 | G10: 1125 | H10: UNPAID | I10: 1125
A11: 45792 | B11: Dave Groth/Ralph Dion half membership paired with Adrian Heffernan | C11: 11000 | D11: 1100 | E11: Split | F11: 0.1 | G11: 550 | H11: UNPAID | I11: 550
A12: 45432 | B12: Adrian and Meghan Heffernan | C12: 12250 | D12: 1225 | E12: Carlos Peter | F12: 0.1 | H12: UNPAID | I12: 1225
A13: 45435 | B13: Blake Bollen and John Bollen (needs second half filled) | C13: 11360 | D13: 1136 | E13: Split | F13: 0.1 | G13: 568 | H13: UNPAID | I13: 568
A14: 45444 | B14: West Capital Lending CORPORATE (Daniel, Eric, Tony, Amir) | C14: 26000 | D14: 1300 | E14: Ryan referral | F14: 0.05 | G14: 1300 | I14: 0
A15: 45466 | B15: Nik Kafetzopoulos | C15: 10500 | D15: 1050 | E15: Peter/Carlos | F15: 0.1 | H15: UNPAID | I15: 1050
A16: 45474 | B16: Eric Dall | C16: 12000 | D16: 1200 | E16: Peter/Carlos | F16: 0.1 | H16: UNPAID | I16: 1200
A17: 45589 | B17: Joe DeCosta (half yacht paired with Finke) | C17: 3045 | D17: 304.5 | E17: Peter/Carlos | F17: 0.1 | H17: UNPAID | I17: 304.5
A18: 45594 | B18: David and Eric Finke (paired w Joe decosta) | C18: 3495 | D18: 349.5 | E18: Peter/Carlos | F18: 0.1 | H18: UNPAID | I18: 349.5
A19: 45597 | B19: Jack Biehl (half yacht needs partner) | C19: 3495 | D19: 349.5 | E19: Peter/Carlos | F19: 0.1 | H19: UNPAID | I19: 349.5
A20: 45597 | B20: Blake Andrew and Geoff | C20: 6900 | D20: 690 | E20: Peter/Carlos | F20: 0.1 | H20: UNPAID | I20: 690
A21: 1/17/2025 | B21: Ray and Brooke Wood | C21: $6,090.00 | D21: $609.00 | E21: Split | F21: 0.1 | G21: 609 | H21: UNPAID | I21: 609
A22: 45741 | B22: Ehsan Sadri (partnered with Jack Biehl) | C22: 3495 | D22: 349.5 | E22: Split | F22: 0.1 | H22: 174.75 | I22: =H22 -> 174.75
A23: 45750 | B23: Megan Brenner (paired with Sarah Sibia) | C23: 11500 | D23: 1150 | E23: Carlos | F23: 0.1 | H23: 1150
A24: 45750 | B24: Sarah Sibia (paired with Megan Brenner) | C24: 11500 | D24: 1150 | E24: Split | F24: 0.1 | H24: 575
A25: 45753 | B25: Marco Vezjak | C25: 5000 | D25: 500 | E25: Split | F25: 0.1 | H25: 250
A26: 45779 | B26: Kyle Dilger (partnered with David and Omar) | C26: 12000 | D26: 1200 | E26: Split w Ryan | F26: 0.1 | H26: 600
A27: 45768 | B27: Larry Davis | C27: 12250 | D27: 1225 | E27: 3 way split | F27: 0.1 | H27: 400
E32: =D27*0.1 -> 122.5 | I32: =SUM(I2:I22) -> 12970.25

Sheet 21050 - Accrued Interest
A1: Name | B1: Beg Balance | C1: interest | D1: payment | E1: ending balance
A2: Manitou Boat | B2: 0.00049864309 | C2: 0 | D2: 0 | E2: =SUM(B2:D2) -> 0.00049864309
A3: Scott Tiernan | B3: 346.74543 | C3: ='22150 & 23150 - Scott Tiernan'!E61 -> 21.124206 | E3: =SUM(B3:D3) -> 367.86964
A4: CCJ True Loan 2 | B4: 861.57436 | C4: ='23400 - CCJ True Loan (2)'!E18 -> 426.31218 | D4: =-'23400 - CCJ True Loan (2)'!E17-'23400 - CCJ True Loan (2)'!E16 -> -861.57436 | E4: =SUM(B4:D4) -> 426.31218
A5: CCJ True Loan | B5: 2913.5176 | C5: 0 | D5: =-'23350 - CCJ True Loan'!E17 -> -2913.5176 | E5: =SUM(B5:D5) -> 0
B6: 0 | E6: =SUM(B6:D6) -> 0
B7: 0 | E7: =SUM(B7:D7) -> 0
A8: Total | B8: =SUM(B2:B7) -> 4121.8379 | E8: =SUM(E2:E7) -> 794.18231
A9: Sitting in G/L | B9: 4121.84 | E9: 794.17
A10: Difference | B10: =B8-B9 -> -0.0020708486 | E10: =E8-E9 -> 0.012310814

Sheet 21100 - Accrued Payroll
A1: PR Accrual
A2: PR End Date | B2: 46007
A3: Month End Date | B3: 46022 | C3: 0 | P3: =5000+567.36+951.3+500 -> 7018.66
A5: Outstanding Days | B5: =NETWORKDAYS(B2+2,B3,0) -> 10 | I5: OFFICER PAYROLL NOT PAID OUT
A6: Total Payroll | B6: 0 | I6: DATE | J6: AMOUNT
A7: Payroll Days | B7: 10 | I7: JANUARY | J7: 5562.5 | K7: =2500 -> 2500 | M7: =J7-5000 -> 562.5
A8: Pay per day | B8: =B6/B7 -> 0 | I8: FEBRUARY | J8: 5382.5 | K8: =K7 -> 2500 | M8: =J8-5000 -> 382.5
A9: Salaries Accrual | B9: =B8*B5 -> 0 | I9: MARCH | J9: 5382.5 | K9: =K8 -> 2500 | M9: =J9-5000 -> 382.5
I10: APRIL | J10: 5382.5 | K10: =K9 -> 2500 | M10: =J10-5000 -> 382.5
A11: Total Taxes | B11: 0 | C11: *Employer taxes only | I11: OCTOBER | J11: 5267.76 | K11: =K10 -> 2500 | M11: =J11-5000 -> 267.76
A12: Pay per day | B12: =B11/B7 -> 0 | I12: NOVEMBER | J12: 5267.76 | K12: =K11 -> 2500 | M12: =J12-5000 -> 267.76
A13: Taxes Accrual | B13: =B5*B12 -> 0
I14: PAID IN APRIL | J14: -30000 | K14: =SUM(K7:K13) -> 15000
A15: 1099 Payroll | B15: 6602.33 | I15: JUNE PETER NOT PAID | J15: =SUM(K15,M15) -> 2691.25 | K15: 2500 | M15: 191.25
A16: Payroll Days | B16: 10 | I16: PAID IN JULY | J16: =-J15 -> -2691.25 | M16: =-M15 -> -191.25
A17: Pay per day | B17: =B15/B16 -> 660.233
A18: 1099 Accrual | B18: =B17*B5 -> 6602.33
A20: COMMISSION | B20: 0
J21: =SUM(J7:J20) -> 2245.52 | L21: Employer taxes | M21: =SUM(M7:M20) -> 2245.52
A22: ACCRUAL | B22: =SUM(B9,B13,B18,B20) -> 6602.33
A23: Bonus
A25: Total Payroll Accrual | B25: =B9+B13+B18+B20+B23 -> 6602.33
A26: Undeposited Checks | B26: 1100 | C26: manual payment to Javier Osores
A27: Undeposited Checks | B27: 228.48 | C27: Manual Check # 902 for Preston, Bond
A31: Total Payroll Accrual | B31: =SUM(B25:B30) -> 7930.81
A34: Officer Wages
A35: Officer Taxes
A36: Officer Commissions

Sheet 21125 - Unearned Revenue
F1: 2021 RECOGNITION | G1: =SUM(E4:E21)-SUM(I4:M21) -> 101459.33
B3: JOIN DATE | C3: MEMBER | D3: DUES | E3: COLLECTED | F3: MONTHLY RECOGNITION | G3: END DATE | I3: 44439 | J3: =EOMONTH(I3,1) -> 44469 | K3: =EOMONTH(J3,1) -> 44500 | L3: =EOMONTH(K3,1) -> 44530 | M3: =EOMONTH(L3,1) -> 44561 | N3: =EOMONTH(M3,1) -> 44592 | O3: =EOMONTH(N3,1) -> 44620 | P3: =EOMONTH(O3,1) -> 44651 | Q3: =EOMONTH(P3,1) -> 44681 | ... DP3: =EOMONTH(DO3,1) -> 47817
A4: =A3+1 -> 1 | B4: 44421 | C4: Michale Kurland and Jerry Jon Thomas | D4: Initiation Fees | E4: 15000 | F4: =E4/60 -> 250 | G4: 46233 | H4: =E4-SUM(I4:DP4) -> 0 | I4: =$F$4 -> 250 | J4: =$F$4 -> 250 | K4: =$F$4 -> 250 | L4: =$F$4 -> 250 | M4: =$F$4 -> 250 | N4: =$F$4 -> 250 | O4: =$F$4 -> 250 | P4: =$F$4 -> 250 | ... BP4: =$F$4 -> 250
A5: =A4+1 -> 2 | B5: 44440 | C5: Greg and Karen Castro | D5: Initiation Fees | E5: 5000 | F5: =E5/60 -> 83.333333 | G5: 46265 | H5: =E5-SUM(I5:DP5) -> 0 | J5: =$F$5 -> 83.333333 | K5: =$F$5 -> 83.333333 | L5: =$F$5 -> 83.333333 | M5: =$F$5 -> 83.333333 | N5: =$F$5 -> 83.333333 | O5: =$F$5 -> 83.333333 | P5: =$F$5 -> 83.333333 | Q5: =$F$5 -> 83.333333 | ... BQ5: =$F$5 -> 83.333333
A6: =A5+1 -> 3 | B6: 44440 | C6: Joe and Maryela Pinkston | D6: Initiation Fees | E6: 5000 | F6: =E6/60 -> 83.333333 | G6: 46265 | H6: =E6-SUM(I6:DP6) -> 0 | J6: =$F$6 -> 83.333333 | K6: =$F$6 -> 83.333333 | L6: =$F$6 -> 83.333333 | M6: =$F$6 -> 83.333333 | N6: =$F$6 -> 83.333333 | O6: =$F$6 -> 83.333333 | P6: =$F$6 -> 83.333333 | Q6: =$F$6 -> 83.333333 | ... BQ6: =$F$6 -> 83.333333
A7: =A6+1 -> 4 | B7: 44440 | C7: J. Paul Kovacs and Karen & George Parmenter | D7: Initiation Fees | E7: 5150 | F7: =E7/60 -> 85.833333 | G7: 46265 | H7: =E7-SUM(I7:DP7) -> 0 | J7: =$F$7 -> 85.833333 | K7: =$F$7 -> 85.833333 | L7: =$F$7 -> 85.833333 | M7: =$F$7 -> 85.833333 | N7: =$F$7 -> 85.833333 | O7: =$F$7 -> 85.833333 | P7: =$F$7 -> 85.833333 | Q7: =$F$7 -> 85.833333 | ... BQ7: =$F$7 -> 85.833333
A8: =A7+1 -> 5 | B8: 44441 | C8: Jack Yao and Mike Chen | D8: Initiation Fees | E8: 6000 | F8: =E8/60 -> 100 | G8: 46265 | H8: =E8-SUM(I8:DP8) -> 0 | J8: =$F$8 -> 100 | K8: =$F$8 -> 100 | L8: =$F$8 -> 100 | M8: =$F$8 -> 100 | N8: =$F$8 -> 100 | O8: =$F$8 -> 100 | P8: =$F$8 -> 100 | Q8: =$F$8 -> 100 | ... BQ8: =$F$8 -> 100
A9: =A8+1 -> 6 | B9: 44444 | C9: Cory Freeman / Rebecca Smith | D9: Initiation Fees | E9: 5000 | F9: =E9/60 -> 83.333333 | G9: 46265 | H9: =E9-SUM(I9:DP9) -> 0 | J9: =$F$9 -> 83.333333 | K9: =$F$9 -> 83.333333 | L9: =$F$9 -> 83.333333 | M9: =$F$9 -> 83.333333 | N9: =$F$9 -> 83.333333 | O9: =$F$9 -> 83.333333 | P9: =$F$9 -> 83.333333 | Q9: =$F$9 -> 83.333333 | ... BQ9: =$F$9 -> 83.333333
A10: =A9+1 -> 7 | B10: 44446 | C10: Sherif El Dabe and Michael Yeung | D10: Initiation Fees | E10: 2575 | F10: =E10/60 -> 42.916667 | G10: 46265 | H10: =E10-SUM(I10:DP10) -> 0 | J10: =$F$10 -> 42.916667 | K10: =$F$10 -> 42.916667 | L10: =$F$10 -> 42.916667 | M10: =$F$10 -> 42.916667 | N10: =$F$10 -> 42.916667 | O10: =$F$10 -> 42.916667 | P10: =$F$10 -> 42.916667 | Q10: =$F$10 -> 42.916667 | ... BQ10: =$F$10 -> 42.916667
A11: =A10+1 -> 8 | B11: 44460 | C11: Andy Stavros and Travis Smith | D11: Initiation Fees | E11: 3605 | F11: =E11/60 -> 60.083333 | G11: 46265 | H11: =E11-SUM(I11:DP11) -> 0 | J11: =$F$11 -> 60.083333 | K11: =$F$11 -> 60.083333 | L11: =$F$11 -> 60.083333 | M11: =$F$11 -> 60.083333 | N11: =$F$11 -> 60.083333 | O11: =$F$11 -> 60.083333 | P11: =$F$11 -> 60.083333 | Q11: =$F$11 -> 60.083333 | ... BQ11: =$F$11 -> 60.083333
A12: =A11+1 -> 9 | B12: 44460 | C12: Andy Stavros and Travis Smith | D12: Monthly Membership Dues | E12: 6798 | F12: =E12/16 -> 424.875 | G12: 44896 | H12: =E12-SUM(I12:DP12) -> 0 | J12: =$F$12 -> 424.875 | K12: =$F$12 -> 424.875 | L12: =$F$12 -> 424.875 | M12: =$F$12 -> 424.875 | N12: =$F$12 -> 424.875 | O12: =$F$12 -> 424.875 | P12: =$F$12 -> 424.875 | Q12: =$F$12 -> 424.875 | ... Y12: =$F$12 -> 424.875
A13: =A12+1 -> 10 | B13: 44460 | C13: Andy Stavros and Travis Smith | D13: Initiation Fees | E13: =7000-3605 -> 3395 | F13: =E13/60 -> 56.583333 | G13: 46265 | H13: =E13-SUM(I13:DP13) -> 0 | J13: =$F$13 -> 56.583333 | K13: =$F$13 -> 56.583333 | L13: =$F$13 -> 56.583333 | M13: =$F$13 -> 56.583333 | N13: =$F$13 -> 56.583333 | O13: =$F$13 -> 56.583333 | P13: =$F$13 -> 56.583333 | Q13: =$F$13 -> 56.583333 | ... BQ13: =$F$13 -> 56.583333
A14: =A13+1 -> 11 | B14: 44460 | C14: Andy Stavros and Travis Smith | D14: Monthly Membership Dues | E14: =10100-3395 -> 6705 | F14: =E14/16 -> 419.0625 | G14: 44896 | H14: =E14-SUM(I14:DP14) -> 0 | J14: =$F$14 -> 419.0625 | K14: =$F$14 -> 419.0625 | L14: =$F$14 -> 419.0625 | M14: =$F$14 -> 419.0625 | N14: =$F$14 -> 419.0625 | O14: =$F$14 -> 419.0625 | P14: =$F$14 -> 419.0625 | Q14: =$F$14 -> 419.0625 | ... Y14: =$F$14 -> 419.0625
A15: =A14+1 -> 12 | B15: 44465 | C15: Sam Kasbar | D15: Initiation Fees | E15: 5150 | F15: =E15/60 -> 85.833333 | G15: 46265 | H15: =E15-SUM(I15:DP15) -> 0 | J15: =$F$15 -> 85.833333 | K15: =$F$15 -> 85.833333 | L15: =$F$15 -> 85.833333 | M15: =$F$15 -> 85.833333 | N15: =$F$15 -> 85.833333 | O15: =$F$15 -> 85.833333 | P15: =$F$15 -> 85.833333 | Q15: =$F$15 -> 85.833333 | ... BQ15: =$F$15 -> 85.833333
A16: =A15+1 -> 13 | B16: 44469 | C16: Dean Miles | D16: Initiation Fees | E16: 6775 | F16: =E16/60 -> 112.91667 | G16: 46265 | H16: =E16-SUM(I16:DP16) -> 0 | J16: =$F$16 -> 112.91667 | K16: =$F$16 -> 112.91667 | L16: =$F$16 -> 112.91667 | M16: =$F$16 -> 112.91667 | N16: =$F$16 -> 112.91667 | O16: =$F$16 -> 112.91667 | P16: =$F$16 -> 112.91667 | Q16: =$F$16 -> 112.91667 | ... BQ16: =$F$16 -> 112.91667
A17: =A16+1 -> 14 | B17: 44470 | C17: Vincent Huang | D17: Initiation Fees | E17: 5150 | F17: =E17/60 -> 85.833333 | G17: 46295 | H17: =E17-SUM(I17:DP17) -> 0 | K17: =$F$17 -> 85.833333 | L17: =$F$17 -> 85.833333 | M17: =$F$17 -> 85.833333 | N17: =$F$17 -> 85.833333 | O17: =$F$17 -> 85.833333 | P17: =$F$17 -> 85.833333 | Q17: =$F$17 -> 85.833333 | R17: =$F$17 -> 85.833333 | ... BR17: =$F$17 -> 85.833333
A18: =A17+1 -> 15 | B18: 44470 | C18: Nany Caruso | D18: Initiation Fees | E18: 2575 | F18: =E18/60 -> 42.916667 | G18: 46295 | H18: =E18-SUM(I18:DP18) -> 0 | K18: =$F$18 -> 42.916667 | L18: =$F$18 -> 42.916667 | M18: =$F$18 -> 42.916667 | N18: =$F$18 -> 42.916667 | O18: =$F$18 -> 42.916667 | P18: =$F$18 -> 42.916667 | Q18: =$F$18 -> 42.916667 | R18: =$F$18 -> 42.916667 | ... BR18: =$F$18 -> 42.916667
A19: =A18+1 -> 16 | B19: 44484 | C19: David Pann and Alex Razo | D19: Initiation Fees | E19: 15000 | F19: =E19/60 -> 250 | G19: 46295 | H19: =E19-SUM(I19:DP19) -> 0 | K19: =$F$19 -> 250 | L19: =$F$19 -> 250 | M19: =$F$19 -> 250 | N19: =$F$19 -> 250 | O19: =$F$19 -> 250 | P19: =$F$19 -> 250 | Q19: =$F$19 -> 250 | R19: =$F$19 -> 250 | ... BR19: =$F$19 -> 250
A20: =A19+1 -> 17 | B20: 44518 | C20: Terri Eisenberg | D20: Initiation Fees | E20: 5000 | F20: =E20/60 -> 83.333333 | G20: 46326 | H20: =E20-SUM(I20:DP20) -> 0 | L20: =$F$20 -> 83.333333 | M20: =$F$20 -> 83.333333 | N20: =$F$20 -> 83.333333 | O20: =$F$20 -> 83.333333 | P20: =$F$20 -> 83.333333 | Q20: =$F$20 -> 83.333333 | R20: =$F$20 -> 83.333333 | S20: =$F$20 -> 83.333333 | ... BS20: =$F$20 -> 83.333333
A21: =A20+1 -> 18 | B21: 44531 | C21: Diyonne and Manny Rojas | D21: Initiation Fees | E21: 6800 | F21: =E21/60 -> 113.33333 | G21: 46356 | H21: =E21-SUM(I21:DP21) -> 0 | M21: =$F$21 -> 113.33333 | N21: =$F$21 -> 113.33333 | O21: =$F$21 -> 113.33333 | P21: =$F$21 -> 113.33333 | Q21: =$F$21 -> 113.33333 | R21: =$F$21 -> 113.33333 | S21: =$F$21 -> 113.33333 | T21: =$F$21 -> 113.33333 | ... BT21: =$F$21 -> 113.33333
A22: =A21+1 -> 19 | B22: 44585 | C22: Robert LaMattina | D22: Initiation Fees | E22: 15000 | F22: =E22/60 -> 250 | G22: 46387 | H22: =E22-SUM(I22:DP22) -> 0 | N22: =$F$22 -> 250 | O22: =$F$22 -> 250 | P22: =$F$22 -> 250 | Q22: =$F$22 -> 250 | R22: =$F$22 -> 250 | S22: =$F$22 -> 250 | T22: =$F$22 -> 250 | U22: =$F$22 -> 250 | ... BU22: =$F$22 -> 250
A23: =A22+1 -> 20 | B23: 44621 | C23: Nathan and Renee Linder | D23: Initiation Fees | E23: 15000 | F23: =E23/60 -> 250 | G23: 46418 | H23: =E23-SUM(I23:DP23) -> 0 | O23: =$F$23 -> 250 | P23: =$F$23 -> 250 | Q23: =$F$23 -> 250 | R23: =$F$23 -> 250 | S23: =$F$23 -> 250 | T23: =$F$23 -> 250 | U23: =$F$23 -> 250 | V23: =$F$23 -> 250 | ... BV23: =$F$23 -> 250
A24: =A23+1 -> 21 | B24: 44621 | C24: Jeff Schaffer, David McReynolds | D24: Initiation Fees | E24: 11333 | F24: =E24/60 -> 188.88333 | G24: 46446 | H24: =E24-SUM(I24:DP24) -> 0 | P24: =$F$24 -> 188.88333 | Q24: =$F$24 -> 188.88333 | R24: =$F$24 -> 188.88333 | S24: =$F$24 -> 188.88333 | T24: =$F$24 -> 188.88333 | U24: =$F$24 -> 188.88333 | V24: =$F$24 -> 188.88333 | W24: =$F$24 -> 188.88333 | ... BW24: =$F$24 -> 188.88333
A25: =A24+1 -> 22 | B25: 44621 | C25: Andy Peters | D25: Initiation Fees | E25: 5667 | F25: =E25/60 -> 94.45 | G25: 46446 | H25: =E25-SUM(I25:DP25) -> 0 | P25: =$F$25 -> 94.45 | Q25: =$F$25 -> 94.45 | R25: =$F$25 -> 94.45 | S25: =$F$25 -> 94.45 | T25: =$F$25 -> 94.45 | U25: =$F$25 -> 94.45 | V25: =$F$25 -> 94.45 | W25: =$F$25 -> 94.45 | ... BW25: =$F$25 -> 94.45
A26: =A25+1 -> 23 | B26: 44644 | C26: Jeff and Wendy Azevedo | D26: Initiation Fees | E26: 15000 | F26: =E26/60 -> 250 | G26: 46446 | H26: =E26-SUM(I26:DP26) -> 0 | P26: =$F$26 -> 250 | Q26: =$F$26 -> 250 | R26: =$F$26 -> 250 | S26: =$F$26 -> 250 | T26: =$F$26 -> 250 | U26: =$F$26 -> 250 | V26: =$F$26 -> 250 | W26: =$F$26 -> 250 | ... BW26: =$F$26 -> 250
A27: =A26+1 -> 24 | B27: 44644 | C27: Gary and Laura McArdell | D27: Monthly Membership Dues | E27: 11000 | F27: =E27/12 -> 916.66667 | G27: 44985 | H27: =E27-SUM(I27:DP27) -> 0 | P27: =$F$27 -> 916.66667 | Q27: =$F$27 -> 916.66667 | R27: =$F$27 -> 916.66667 | S27: =$F$27 -> 916.66667 | T27: =$F$27 -> 916.66667 | U27: =$F$27 -> 916.66667 | V27: =$F$27 -> 916.66667 | W27: =$F$27 -> 916.66667 | ... AA27: =$F$27 -> 916.66667
A28: =A27+1 -> 25 | B28: 44644 | C28: Gary and Laura McArdell | D28: Initiation Fees | E28: 15000 | F28: =E28/60 -> 250 | G28: 46446 | H28: =E28-SUM(I28:DP28) -> 0 | P28: =$F$28 -> 250 | Q28: =$F$28 -> 250 | R28: =$F$28 -> 250 | S28: =$F$28 -> 250 | T28: =$F$28 -> 250 | U28: =$F$28 -> 250 | V28: =$F$28 -> 250 | W28: =$F$28 -> 250 | ... BW28: =$F$28 -> 250
A29: =A28+1 -> 26 | B29: 44651 | C29: Chuck Le | D29: Initiation Fees | E29: 8755 | F29: =E29/60 -> 145.91667 | G29: 46446 | H29: =E29-SUM(I29:DP29) -> 0 | P29: =$F$29 -> 145.91667 | Q29: =$F$29 -> 145.91667 | R29: =$F$29 -> 145.91667 | S29: =$F$29 -> 145.91667 | T29: =$F$29 -> 145.91667 | U29: =$F$29 -> 145.91667 | V29: =$F$29 -> 145.91667 | W29: =$F$29 -> 145.91667 | ... BW29: =$F$29 -> 145.91667
A30: =A29+1 -> 27 | B30: 44651 | C30: Mark Jones | D30: Initiation Fees | E30: 8500 | F30: =E30/60 -> 141.66667 | G30: 46446 | H30: =E30-SUM(I30:DP30) -> 0 | P30: =$F$30 -> 141.66667 | Q30: =$F$30 -> 141.66667 | R30: =$F$30 -> 141.66667 | S30: =$F$30 -> 141.66667 | T30: =$F$30 -> 141.66667 | U30: =$F$30 -> 141.66667 | V30: =$F$30 -> 141.66667 | W30: =$F$30 -> 141.66667 | ... BW30: =$F$30 -> 141.66667
A31: =A30+1 -> 28 | B31: 44651 | C31: Audrey Few | D31: Initiation Fees | E31: 15450 | F31: =E31/60 -> 257.5 | G31: 46446 | H31: =E31-SUM(I31:DP31) -> 0 | P31: =$F$31 -> 257.5 | Q31: =$F$31 -> 257.5 | R31: =$F$31 -> 257.5 | S31: =$F$31 -> 257.5 | T31: =$F$31 -> 257.5 | U31: 14162.5
A32: =A31+1 -> 29 | B32: 44659 | C32: Piero Broccardo | D32: Initiation Fees | E32: 22500 | F32: =E32/60 -> 375 | G32: 46477 | H32: =E32-SUM(I32:DP32) -> 0 | Q32: =$F$32 -> 375 | R32: =$F$32 -> 375 | S32: =$F$32 -> 375 | T32: =$F$32 -> 375 | U32: =$F$32 -> 375 | V32: =$F$32 -> 375 | W32: =$F$32 -> 375 | X32: =$F$32 -> 375 | ... BX32: =$F$32 -> 375
A33: =A32+1 -> 30 | B33: 44689 | C33: Purvis Payne | D33: Initiation Fees | E33: 24500 | F33: =E33/60 -> 408.33333 | G33: 46507 | H33: =E33-SUM(I33:DP33) -> 0 | R33: =$F$33 -> 408.33333 | S33: =$F$33 -> 408.33333 | T33: =$F$33 -> 408.33333 | U33: =$F$33 -> 408.33333 | V33: =$F$33 -> 408.33333 | W33: =$F$33 -> 408.33333 | X33: =$F$33 -> 408.33333 | Y33: =$F$33 -> 408.33333 | ... BY33: =$F$33 -> 408.33333
A34: =A33+1 -> 31 | B34: 44772 | C34: Shawn and Julia Edwards | D34: Initiation Fees | E34: 19000 | F34: =E34/60 -> 316.66667 | G34: 46568 | H34: =E34-SUM(I34:DP34) -> 0 | T34: =$F$34 -> 316.66667 | U34: =$F$34 -> 316.66667 | V34: =$F$34 -> 316.66667 | W34: =$F$34 -> 316.66667 | X34: =$F$34 -> 316.66667 | Y34: =$F$34 -> 316.66667 | Z34: =$F$34 -> 316.66667 | AA34: =$F$34 -> 316.66667 | ... CA34: =$F$34 -> 316.66667
A35: =A34+1 -> 32 | B35: 44804 | C35: Kerry and Sirenia Sabo | D35: Initiation Fees | E35: 10500 | F35: =E35/60 -> 175 | G35: 46599 | H35: =E35-SUM(I35:DP35) -> 0 | U35: =$F$35 -> 175 | V35: =$F$35 -> 175 | W35: =$F$35 -> 175 | X35: =$F$35 -> 175 | Y35: =$F$35 -> 175 | Z35: =$F$35 -> 175 | AA35: =$F$35 -> 175 | AB35: =$F$35 -> 175 | ... CB35: =$F$35 -> 175
A36: =A35+1 -> 33 | B36: 44851 | C36: Jeremy Rhyne | D36: Initiation Fees | E36: 22500 | F36: =E36/60 -> 375 | G36: 46660 | H36: =E36-SUM(I36:DP36) -> 0 | W36: =$F$36 -> 375 | X36: =$F$36 -> 375 | Y36: =$F$36 -> 375 | Z36: =$F$36 -> 375 | AA36: =$F$36 -> 375 | AB36: =$F$36 -> 375 | AC36: =$F$36 -> 375 | AD36: =$F$36 -> 375 | ... CD36: =$F$36 -> 375
A37: =A36+1 -> 34 | B37: 44872 | C37: Jeremy Buckman and Marim Abdul | D37: Initiation Fees | E37: 21000 | F37: =E37/60 -> 350 | G37: 46691 | H37: =E37-SUM(I37:DP37) -> 0 | X37: =$F$37 -> 350 | Y37: =$F$37 -> 350 | Z37: =$F$37 -> 350 | AA37: =$F$37 -> 350 | AB37: =$F$37 -> 350 | AC37: =$F$37 -> 350 | AD37: =$F$37 -> 350 | AE37: =$F$37 -> 350 | ... CE37: =$F$37 -> 350
A38: 35 | B38: 44929 | C38: Ken Sunshine | D38: Initiation Fees | E38: 10000 | F38: =E38/60 -> 166.66667 | G38: 46722 | H38: =E38-SUM(I38:DP38) -> 0 | Z38: =$F$38 -> 166.66667 | AA38: =$F$38 -> 166.66667 | AB38: =$F$38 -> 166.66667 | AC38: =$F$38 -> 166.66667 | AD38: =$F$38 -> 166.66667 | AE38: =$F$38 -> 166.66667 | AF38: =$F$38 -> 166.66667 | AG38: =$F$38 -> 166.66667 | ... CG38: =$F$38 -> 166.66667
A39: 36 | B39: 44929 | C39: Ken Sunshine | D39: Monthly Membership Dues | E39: 8250 | F39: =E39/12 -> 687.5 | G39: 45261 | H39: =E39-SUM(I39:DP39) -> 0 | Z39: =$F$39 -> 687.5 | AA39: =$F$39 -> 687.5 | AB39: =$F$39 -> 687.5 | AC39: =$F$39 -> 687.5 | AD39: =$F$39 -> 687.5 | AE39: =$F$39 -> 687.5 | AF39: =$F$39 -> 687.5 | AG39: =$F$39 -> 687.5 | ... AK39: =$F$39 -> 687.5
A40: 37 | B40: 44943 | C40: Nancy Caruso | D40: Monthly Membership Dues | E40: 11000 | F40: =E40/12 -> 916.66667 | G40: 45261 | H40: =E40-SUM(I40:DP40) -> 0 | Z40: =$F$40 -> 916.66667 | AA40: =$F$40 -> 916.66667 | AB40: =$F$40 -> 916.66667 | AC40: =$F$40 -> 916.66667 | AD40: =$F$40 -> 916.66667 | AE40: =$F$40 -> 916.66667 | AF40: =$F$40 -> 916.66667 | AG40: =$F$40 -> 916.66667 | ... AK40: =$F$40 -> 916.66667
A41: 38 | B41: 45005 | C41: Gary and Laura McArdell | D41: Monthly Membership Dues | E41: 11000 | F41: =E41/12 -> 916.66667 | G41: 45341 | H41: =E41-SUM(I41:DP41) -> 0 | AB41: =$F$41 -> 916.66667 | AC41: =$F$41 -> 916.66667 | AD41: =$F$41 -> 916.66667 | AE41: =$F$41 -> 916.66667 | AF41: =$F$41 -> 916.66667 | AG41: =$F$41 -> 916.66667 | AH41: =$F$41 -> 916.66667 | AI41: =$F$41 -> 916.66667 | ... AM41: =$F$41 -> 916.66667
A42: 39 | B42: 45016 | C42: Sebastian Ocuilleanian | D42: Initiation Fees | E42: 21000 | F42: =E42/60 -> 350 | G42: 46842 | H42: =E42-SUM(I42:DP42) -> 0 | AC42: =$F$42 -> 350 | AD42: =$F$42 -> 350 | AE42: =$F$42 -> 350 | AF42: =$F$42 -> 350 | AG42: =$F$42 -> 350 | AH42: =$F$42 -> 350 | AI42: =$F$42 -> 350 | AJ42: =$F$42 -> 350 | ... CJ42: =$F$42 -> 350
A43: 40 | B43: 45017 | C43: Sebastian Ocuilleanian | D43: Monthly Membership Dues | E43: 16500 | F43: =E43/12 -> 1375 | G43: 44986 | H43: =E43-SUM(I43:DP43) -> 0 | AC43: =$F$43 -> 1375 | AD43: =$F$43 -> 1375 | AE43: =$F$43 -> 1375 | AF43: =$F$43 -> 1375 | AG43: =$F$43 -> 1375 | AH43: =$F$43 -> 1375 | AI43: =$F$43 -> 1375 | AJ43: =$F$43 -> 1375 | ... AN43: =$F$43 -> 1375
A44: 41 | B44: 45043 | C44: Todd Fox | D44: Initiation Fees | E44: 12000 | F44: =E44/12 -> 1000 | G44: 45442 | H44: =E44-SUM(I44:DP44) -> 0 | AE44: =$F$44 -> 1000 | AF44: =$F$44 -> 1000 | AG44: =$F$44 -> 1000 | AH44: =$F$44 -> 1000 | AI44: =$F$44 -> 1000 | AJ44: =$F$44 -> 1000 | AK44: =$F$44 -> 1000 | AL44: =$F$44 -> 1000 | ... AP44: =$F$44 -> 1000
A45: 42 | B45: 45043 | C45: Todd Fox | D45: Monthly Membership Dues | E45: 18000 | F45: =E45/12 -> 1500 | G45: 45442 | H45: =E45-SUM(I45:DP45) -> 0 | AE45: =$F$45 -> 1500 | AF45: =$F$45 -> 1500 | AG45: =$F$45 -> 1500 | AH45: =$F$45 -> 1500 | AI45: =$F$45 -> 1500 | AJ45: =$F$45 -> 1500 | AK45: =$F$45 -> 1500 | AL45: =$F$45 -> 1500 | ... AP45: =$F$45 -> 1500
A46: 43 | B46: 45045 | C46: David Melo | D46: Initiation Fees | E46: 12250 | F46: =E46/60 -> 204.16667 | G46: 46873 | H46: =E46-SUM(I46:DP46) -> 0 | AC46: =$F$46 -> 204.16667 | AD46: =$F$46 -> 204.16667 | AE46: =$F$46 -> 204.16667 | AF46: =$F$46 -> 204.16667 | AG46: =$F$46 -> 204.16667 | AH46: =$F$46 -> 204.16667 | AI46: =$F$46 -> 204.16667 | AJ46: =$F$46 -> 204.16667 | ... CJ46: =$F$46 -> 204.16667
A47: 44 | B47: 45045 | C47: David Melo | D47: Monthly Membership Dues | E47: 9185 | F47: =E47/12 -> 765.41667 | G47: 45382 | H47: =E47-SUM(I47:DP47) -> 0 | AC47: =$F$47 -> 765.41667 | AD47: =$F$47 -> 765.41667 | AE47: =$F$47 -> 765.41667 | AF47: =$F$47 -> 765.41667 | AG47: =$F$47 -> 765.41667 | AH47: =$F$47 -> 765.41667 | AI47: =$F$47 -> 765.41667 | AJ47: =$F$47 -> 765.41667 | ... AN47: =$F$47 -> 765.41667
A48: 45 | B48: 45047 | C48: Joseph and Ryan Bonacci | D48: Initiation Fees | E48: 12250 | F48: =E48/60 -> 204.16667 | G48: 46871 | H48: =E48-SUM(I48:DP48) -> 0 | AD48: =$F$48 -> 204.16667 | AE48: =$F$48 -> 204.16667 | AF48: =$F$48 -> 204.16667 | AG48: =$F$48 -> 204.16667 | AH48: =$F$48 -> 204.16667 | AI48: =$F$48 -> 204.16667 | AJ48: =$F$48 -> 204.16667 | AK48: =$F$48 -> 204.16667 | ... CK48: =$F$48 -> 204.16667
A49: 46 | B49: 45047 | C49: Joseph and Ryan Bonacci | D49: Monthly Membership Dues | E49: 9350 | F49: =E49/12 -> 779.16667 | G49: 45412 | H49: =E49-SUM(I49:DP49) -> 0 | AD49: =$F$49 -> 779.16667 | AE49: =$F$49 -> 779.16667 | AF49: =$F$49 -> 779.16667 | AG49: =$F$49 -> 779.16667 | AH49: =$F$49 -> 779.16667 | AI49: =$F$49 -> 779.16667 | AJ49: =$F$49 -> 779.16667 | AK49: =$F$49 -> 779.16667 | ... AO49: =$F$49 -> 779.16667
A50: 47 | B50: 45049 | C50: Charles Chacon | D50: Initiation Fees | E50: 10500 | F50: =E50/60 -> 175 | G50: 46873 | H50: =E50-SUM(I50:DP50) -> 0 | AD50: =$F$50 -> 175 | AE50: =$F$50 -> 175 | AF50: =$F$50 -> 175 | AG50: =$F$50 -> 175 | AH50: =$F$50 -> 175 | AI50: =$F$50 -> 175 | AJ50: =$F$50 -> 175 | AK50: =$F$50 -> 175 | ... CK50: =$F$50 -> 175
A51: 48 | B51: 45049 | C51: Charles Chacon | D51: Monthly Membership Dues | E51: 9515 | F51: =E51/12 -> 792.91667 | G51: 45412 | H51: =E51-SUM(I51:DP51) -> 0 | AD51: =$F$51 -> 792.91667 | AE51: =$F$51 -> 792.91667 | AF51: =$F$51 -> 792.91667 | AG51: =$F$51 -> 792.91667 | AH51: =$F$51 -> 792.91667 | AI51: =$F$51 -> 792.91667 | AJ51: =$F$51 -> 792.91667 | AK51: =$F$51 -> 792.91667 | ... AO51: =$F$51 -> 792.91667
A52: 49 | B52: 45077 | C52: Jay Wyatt and Evan Nickel | D52: Initiation Fees | E52: 12250 | F52: =E52/30 -> 408.33333 | G52: 46873 | H52: =E52-SUM(I52:DP52) -> 0 | AD52: =$F$52 -> 408.33333 | AE52: =$F$52 -> 408.33333 | AF52: =$F$52 -> 408.33333 | AG52: =$F$52 -> 408.33333 | AH52: =$F$52 -> 408.33333 | AI52: =$F$52 -> 408.33333 | AJ52: =$F$52 -> 408.33333 | AK52: =$F$52 -> 408.33333 | ... BG52: =$F$52 -> 408.33333
A53: 50 | B53: 45077 | C53: Karim Gobran | D53: Initiation Fees | E53: 12250 | F53: =E53/60 -> 204.16667 | G53: 46873 | H53: =E53-SUM(I53:DP53) -> 0 | AE53: =$F$53 -> 204.16667 | AF53: =$F$53 -> 204.16667 | AG53: =$F$53 -> 204.16667 | AH53: =$F$53 -> 204.16667 | AI53: =$F$53 -> 204.16667 | AJ53: =$F$53 -> 204.16667 | AK53: =$F$53 -> 204.16667 | AL53: =$F$53 -> 204.16667 | ... CL53: =$F$53 -> 204.16667
A54: 51 | B54: 45092 | C54: Kathleen and Enrique Conterno | D54: Initiation Fees | E54: 10500 | F54: =E54/60 -> 175 | G54: 46874 | H54: =E54-SUM(I54:DP54) -> 0 | AE54: =$F$54 -> 175 | AF54: =$F$54 -> 175 | AG54: =$F$54 -> 175 | AH54: =$F$54 -> 175 | AI54: =$F$54 -> 175 | AJ54: =$F$54 -> 175 | AK54: =$F$54 -> 175 | AL54: =$F$54 -> 175 | ... CL54: =$F$54 -> 175
A55: 52 | B55: 45106 | C55: David and Ryan Buynak | D55: Initiation Fees | E55: 22500 | F55: =E55/60 -> 375 | G55: 46875 | H55: =E55-SUM(I55:DP55) -> 0 | AE55: =$F$55 -> 375 | AF55: =$F$55 -> 375 | AG55: =$F$55 -> 375 | AH55: =$F$55 -> 375 | AI55: =$F$55 -> 375 | AJ55: =$F$55 -> 375 | AK55: =$F$55 -> 375 | AL55: =$F$55 -> 375 | ... CL55: =$F$55 -> 375
A56: 53 | B56: 45142 | C56: Sam and David Khorramshahi | D56: Initiation Fees | E56: 22500 | F56: =E56/60 -> 375 | G56: 46964 | H56: =E56-SUM(I56:DP56) -> 0 | AG56: =$F$56 -> 375 | AH56: =$F$56 -> 375 | AI56: =$F$56 -> 375 | AJ56: =$F$56 -> 375 | AK56: =$F$56 -> 375 | AL56: =$F$56 -> 375 | AM56: =$F$56 -> 375 | AN56: =$F$56 -> 375 | ... CN56: =$F$56 -> 375
A57: 54 | B57: 45155 | C57: Gary Highland | D57: Initiation Fees | E57: =22500/2 -> 11250 | F57: =E57/30 -> 375 | G57: 46964 | H57: =E57-SUM(I57:DP57) -> 0 | AG57: =$F$57 -> 375 | AH57: =$F$57 -> 375 | AI57: =$F$57 -> 375 | AJ57: =$F$57 -> 375 | AK57: =$F$57 -> 375 | AL57: =$F$57 -> 375 | AM57: =$F$57 -> 375 | AN57: =$F$57 -> 375 | ... BJ57: =$F$57 -> 375
A58: 55 | B58: 45155 | C58: Gary Highland | D58: Monthly Membership Dues | E58: 16500 | F58: =E58/12 -> 1375 | G58: 45503 | H58: =E58-SUM(I58:DP58) -> 0 | AG58: =$F$58 -> 1375 | AH58: =$F$58 -> 1375 | AI58: =$F$58 -> 1375 | AJ58: =$F$58 -> 1375 | AK58: =$F$58 -> 1375 | AL58: =$F$58 -> 1375 | AM58: =$F$58 -> 1375 | AN58: =$F$58 -> 1375 | ... AR58: =$F$58 -> 1375
A59: 56 | B59: 45170 | C59: Debra Strougo | D59: Initiation Fees | E59: 12250 | F59: =E59/60 -> 204.16667 | G59: 46996 | H59: =E59-SUM(I59:DP59) -> 0 | AH59: =$F$59 -> 204.16667 | AI59: =$F$59 -> 204.16667 | AJ59: =$F$59 -> 204.16667 | AK59: =$F$59 -> 204.16667 | AL59: =$F$59 -> 204.16667 | AM59: =$F$59 -> 204.16667 | AN59: =$F$59 -> 204.16667 | AO59: =$F$59 -> 204.16667 | ... CO59: =$F$59 -> 204.16667
A60: 57 | B60: 45200 | C60: Martin Lopez | D60: Initiation Fees | E60: 12000 | F60: =E60/60 -> 200 | G60: 46997 | H60: =E60-SUM(I60:DP60) -> 0 | AI60: =$F$60 -> 200 | AJ60: =$F$60 -> 200 | AK60: =$F$60 -> 200 | AL60: =$F$60 -> 200 | AM60: =$F$60 -> 200 | AN60: =$F$60 -> 200 | AO60: =$F$60 -> 200 | AP60: =$F$60 -> 200 | ... CP60: =$F$60 -> 200
A61: 58 | B61: 45200 | C61: Martin Lopez | D61: Monthly Membership Dues | E61: 9515 | F61: =E61/12 -> 792.91667 | G61: 45536 | H61: =E61-SUM(I61:DP61) -> 0 | AI61: =$F$61 -> 792.91667 | AJ61: =$F$61 -> 792.91667 | AK61: =$F$61 -> 792.91667 | AL61: =$F$61 -> 792.91667 | AM61: =$F$61 -> 792.91667 | AN61: =$F$61 -> 792.91667 | AO61: =$F$61 -> 792.91667 | AP61: =$F$61 -> 792.91667 | ... AT61: =$F$61 -> 792.91667
A62: 59 | B62: 45231 | C62: James F. Lineback | D62: Initiation Fees | E62: 14500 | F62: =E62/60 -> 241.66667 | G62: 47057 | H62: =E62-SUM(I62:DP62) -> 0 | AJ62: =$F$62 -> 241.66667 | AK62: =$F$62 -> 241.66667 | AL62: =$F$62 -> 241.66667 | AM62: =$F$62 -> 241.66667 | AN62: =$F$62 -> 241.66667 | AO62: =$F$62 -> 241.66667 | AP62: =$F$62 -> 241.66667 | AQ62: =$F$62 -> 241.66667 | ... CQ62: =$F$62 -> 241.66667
A63: 60 | B63: 45280 | C63: Colton Whitney Brian Barbour | D63: Initiation Fees | E63: 15000 | F63: =E63/60 -> 250 | G63: 47087 | H63: =E63-SUM(I63:DP63) -> 0 | AK63: =$F$63 -> 250 | AL63: =$F$63 -> 250 | AM63: =$F$63 -> 250 | AN63: =$F$63 -> 250 | AO63: =$F$63 -> 250 | AP63: =$F$63 -> 250 | AQ63: =$F$63 -> 250 | AR63: =$F$63 -> 250 | ... CR63: =$F$63 -> 250
A64: 61 | B64: 45280 | C64: Kelly Oconnell and Shelley Lacona | D64: Initiation Fees | E64: 18000 | F64: =E64/60 -> 300 | G64: 47087 | H64: =E64-SUM(I64:DP64) -> 0 | AK64: =F64 -> 300 | AL64: =AK64 -> 300 | AM64: =AL64 -> 300 | AN64: =AM64 -> 300 | AO64: =AN64 -> 300 | AP64: =AO64 -> 300 | AQ64: =AP64 -> 300 | AR64: =AQ64 -> 300 | AS64: =AR64 -> 300 | ... CR64: =CQ64 -> 300
A65: 62 | B65: 45274 | C65: Nancy Caruso | D65: Monthly Membership Dues | E65: 11000 | F65: =E65/12 -> 916.66667 | G65: 45626 | H65: =E65-SUM(I65:DP65) -> 0 | AK65: =$F$65 -> 916.66667 | AL65: =$F$65 -> 916.66667 | AM65: =$F$65 -> 916.66667 | AN65: =$F$65 -> 916.66667 | AO65: =$F$65 -> 916.66667 | AP65: =$F$65 -> 916.66667 | AQ65: =$F$65 -> 916.66667 | AR65: =$F$65 -> 916.66667 | ... AV65: =$F$65 -> 916.66667
A66: 63 | B66: 45291 | C66: Ken Sunshine | D66: Monthly Membership Dues | E66: 8250 | F66: =E66/12 -> 687.5 | G66: 45261 | H66: =E66-SUM(I66:DP66) -> 0 | AL66: =$F$66 -> 687.5 | AM66: =$F$66 -> 687.5 | AN66: =$F$66 -> 687.5 | AO66: =$F$66 -> 687.5 | AP66: =$F$66 -> 687.5 | AQ66: =$F$66 -> 687.5 | AR66: =$F$66 -> 687.5 | AS66: =$F$66 -> 687.5 | ... AW66: =$F$66 -> 687.5
A67: 64 | B67: 44930 | C67: Leon Weathersby and Lauren Hobb | D67: Initiation Fees | E67: 8500 | F67: =E67/60 -> 141.66667 | G67: 47118 | H67: =E67-SUM(I67:DP67) -> 0 | AL67: =$F$67 -> 141.66667 | AM67: =$F$67 -> 141.66667 | AN67: =$F$67 -> 141.66667 | AO67: =$F$67 -> 141.66667 | AP67: =$F$67 -> 141.66667 | AQ67: =$F$67 -> 141.66667 | AR67: =$F$67 -> 141.66667 | AS67: =$F$67 -> 141.66667 | ... CS67: =$F$67 -> 141.66667
A68: 65 | B68: 45299 | C68: David Durant and Omar Othman | D68: Initiation Fees | E68: 12250 | F68: =E68/60 -> 204.16667 | G68: 47118 | H68: =E68-SUM(I68:DP68) -> 0 | AL68: =$F$68 -> 204.16667 | AM68: =$F$68 -> 204.16667 | AN68: =$F$68 -> 204.16667 | AO68: =$F$68 -> 204.16667 | AP68: =$F$68 -> 204.16667 | AQ68: =$F$68 -> 204.16667 | AR68: =$F$68 -> 204.16667 | AS68: =$F$68 -> 204.16667 | ... CS68: =$F$68 -> 204.16667
A69: 66 | B69: 45301 | C69: Brian Walrod and Skip Kingery | D69: Initiation Fees | E69: 19000 | F69: =E69/60 -> 316.66667 | G69: 47118 | H69: =E69-SUM(I69:DP69) -> 0 | AL69: =$F$69 -> 316.66667 | AM69: =$F$69 -> 316.66667 | AN69: =$F$69 -> 316.66667 | AO69: =$F$69 -> 316.66667 | AP69: =$F$69 -> 316.66667 | AQ69: =$F$69 -> 316.66667 | AR69: =$F$69 -> 316.66667 | AS69: =$F$69 -> 316.66667 | ... CS69: =$F$69 -> 316.66667
A70: 67 | B70: 45322 | C70: Dean Miles | D70: Monthly Membership Dues | E70: 1000 | F70: =E70 -> 1000 | G70: 45350 | H70: =E70-SUM(I70:DP70) -> 0 | AM70: =F70 -> 1000
A71: 68 | B71: 45340 | C71: Scott Dixon | D71: Initiation Fees | E71: 12250 | F71: =E71/60 -> 204.16667 | G71: 47149 | H71: =E71-SUM(I71:DP71) -> 0 | AM71: =$F$71 -> 204.16667 | AN71: =$F$71 -> 204.16667 | AO71: =$F$71 -> 204.16667 | AP71: =$F$71 -> 204.16667 | AQ71: =$F$71 -> 204.16667 | AR71: =$F$71 -> 204.16667 | AS71: =$F$71 -> 204.16667 | AT71: =$F$71 -> 204.16667 | ... CT71: =$F$71 -> 204.16667
A72: 69 | B72: 45350 | C72: Dean Miles | D72: Monthly Membership Dues | E72: 1000 | F72: 1000 | G72: 45382 | H72: =E72-SUM(I72:DP72) -> 0 | AN72: =F72 -> 1000
A73: 70 | B73: 45350 | C73: Gary McArdell | D73: Monthly Membership Dues | E73: 11000 | F73: =E73/12 -> 916.66667 | G73: 45717 | H73: =E73-SUM(I73:DP73) -> 0 | AM73: =$F$73 -> 916.66667 | AN73: =$F$73 -> 916.66667 | AO73: =$F$73 -> 916.66667 | AP73: =$F$73 -> 916.66667 | AQ73: =$F$73 -> 916.66667 | AR73: =$F$73 -> 916.66667 | AS73: =$F$73 -> 916.66667 | AT73: =$F$73 -> 916.66667 | ... AX73: =$F$73 -> 916.66667
A74: 71 | B74: 45350 | C74: Brian Walrod and Skip Kingery | D74: Monthly Membership Dues | E74: 1500 | F74: 1500 | G74: 45376 | H74: =E74-SUM(I74:DP74) -> 0 | AN74: =E74 -> 1500
A75: 72 | B75: 45390 | C75: Joe Faruqui | D75: Initiation Fees | E75: 20000 | F75: =E75/60 -> 333.33333 | G75: 47208 | H75: =E75-SUM(I75:DP75) -> 0 | AO75: =$F$75 -> 333.33333 | AP75: =$F$75 -> 333.33333 | AQ75: =$F$75 -> 333.33333 | AR75: =$F$75 -> 333.33333 | AS75: =$F$75 -> 333.33333 | AT75: =$F$75 -> 333.33333 | AU75: =$F$75 -> 333.33333 | AV75: =$F$75 -> 333.33333 | ... CV75: =$F$75 -> 333.33333
A76: 73 | B76: 45392 | C76: Autumn Lemon | D76: Initiation Fees | E76: 12500 | F76: =E76/60 -> 208.33333 | G76: 47208 | H76: =E76-SUM(I76:DP76) -> 0 | AO76: =$F$76 -> 208.33333 | AP76: =$F$76 -> 208.33333 | AQ76: =$F$76 -> 208.33333 | AR76: =$F$76 -> 208.33333 | AS76: =$F$76 -> 208.33333 | AT76: =$F$76 -> 208.33333 | AU76: =$F$76 -> 208.33333 | AV76: =$F$76 -> 208.33333 | ... CV76: =$F$76 -> 208.33333
A77: 74 | B77: 45397 | C77: Sebastian Ocuilleanian | D77: Monthly Membership Dues | E77: 16140 | F77: =E77/12 -> 1345 | G77: 45747 | H77: =E77-SUM(I77:DP77) -> 0 | AO77: =$F$77 -> 1345 | AP77: =$F$77 -> 1345 | AQ77: =$F$77 -> 1345 | AR77: =$F$77 -> 1345 | AS77: =$F$77 -> 1345 | AT77: =$F$77 -> 1345 | AU77: =$F$77 -> 1345 | AV77: =$F$77 -> 1345 | ... AZ77: =$F$77 -> 1345
A78: 75 | B78: 45407 | C78: Charles Chacon | D78: Monthly Membership Dues | E78: 9185 | F78: =E78/12 -> 765.41667 | G78: 45747 | H78: =E78-SUM(I78:DP78) -> 0 | AO78: =$F$78 -> 765.41667 | AP78: =$F$78 -> 765.41667 | AQ78: =$F$78 -> 765.41667 | AR78: =$F$78 -> 765.41667 | AS78: =$F$78 -> 765.41667 | AT78: =$F$78 -> 765.41667 | AU78: =$F$78 -> 765.41667 | AV78: =$F$78 -> 765.41667 | ... AZ78: =$F$78 -> 765.41667
A79: 76 | B79: 45412 | C79: Scott Javore | D79: Initiation Fees | E79: 8000 | F79: =E79/60 -> 133.33333 | G79: 47268 | H79: =E79-SUM(I79:DP79) -> 7.2759576e-12 | AQ79: =$F$79 -> 133.33333 | AR79: =$F$79 -> 133.33333 | AS79: =$F$79 -> 133.33333 | AT79: =$F$79 -> 133.33333 | AU79: =$F$79 -> 133.33333 | AV79: =$F$79 -> 133.33333 | AW79: =$F$79 -> 133.33333 | AX79: =$F$79 -> 133.33333 | ... CX79: =$F$79 -> 133.33333
A80: 77 | B80: 45427 | C80: Jay Wyatt and Evan Nickel | D80: Initiation Fees | E80: 12250 | F80: =E80/30 -> 408.33333 | G80: 46873 | H80: =E80-SUM(I80:DP80) -> 0 | BH80: =$F$80 -> 408.33333 | BI80: =$F$80 -> 408.33333 | BJ80: =$F$80 -> 408.33333 | BK80: =$F$80 -> 408.33333 | BL80: =$F$80 -> 408.33333 | BM80: =$F$80 -> 408.33333 | BN80: =$F$80 -> 408.33333 | BO80: =$F$80 -> 408.33333 | ... CK80: =$F$80 -> 408.33333
A81: 78 | B81: 45431 | C81: Ralph Dion and David Groth | D81: Initiation Fees | E81: 11000 | F81: =E81/60 -> 183.33333 | G81: 47238 | H81: =E81-SUM(I81:DP81) -> 0 | AP81: =$F$81 -> 183.33333 | AQ81: =$F$81 -> 183.33333 | AR81: =$F$81 -> 183.33333 | AS81: =$F$81 -> 183.33333 | AT81: =$F$81 -> 183.33333 | AU81: =$F$81 -> 183.33333 | AV81: =$F$81 -> 183.33333 | AW81: =$F$81 -> 183.33333 | ... CW81: =$F$81 -> 183.33333
A82: 79 | B82: 45415 | C82: Joe Bonacci | D82: Monthly Membership Dues | E82: 9350 | F82: =E82/12 -> 779.16667 | G82: 45777 | H82: =E82-SUM(I82:DP82) -> 0 | AP82: =$F$82 -> 779.16667 | AQ82: =$F$82 -> 779.16667 | AR82: =$F$82 -> 779.16667 | AS82: =$F$82 -> 779.16667 | AT82: =$F$82 -> 779.16667 | AU82: =$F$82 -> 779.16667 | AV82: =$F$82 -> 779.16667 | AW82: =$F$82 -> 779.16667 | ... BA82: =$F$82 -> 779.16667
A83: 80 | B83: 45440 | C83: Adrian heffernan | D83: Initiation Fees | E83: 12250 | F83: =E83/60 -> 204.16667 | G83: 47238 | H83: =E83-SUM(I83:DP83) -> 0 | AP83: =$F$83 -> 204.16667 | AQ83: =$F$83 -> 204.16667 | AR83: =$F$83 -> 204.16667 | AS83: =$F$83 -> 204.16667 | AT83: =$F$83 -> 204.16667 | AU83: =$F$83 -> 204.16667 | AV83: =$F$83 -> 204.16667 | AW83: =$F$83 -> 204.16667 | ... CW83: =$F$83 -> 204.16667
A84: 81 | B84: 45443 | C84: West Coast Lending | D84: Initiation Fees | E84: 26000 | F84: =E84/60 -> 433.33333 | G84: 47238 | H84: =E84-SUM(I84:DP84) -> 0 | AP84: =$F$84 -> 433.33333 | AQ84: =$F$84 -> 433.33333 | AR84: =$F$84 -> 433.33333 | AS84: =$F$84 -> 433.33333 | AT84: =$F$84 -> 433.33333 | AU84: =$F$84 -> 433.33333 | AV84: =$F$84 -> 433.33333 | AW84: =$F$84 -> 433.33333 | ... CW84: =$F$84 -> 433.33333
A85: 82 | B85: 45435 | C85: Blake Bollen and John Bollen | D85: Initiation Fees | E85: 11360 | F85: =E85/60 -> 189.33333 | G85: 47238 | H85: =E85-SUM(I85:DP85) -> 0 | AP85: =$F$85 -> 189.33333 | AQ85: =$F$85 -> 189.33333 | AR85: =$F$85 -> 189.33333 | AS85: =$F$85 -> 189.33333 | AT85: =$F$85 -> 189.33333 | AU85: =$F$85 -> 189.33333 | AV85: =$F$85 -> 189.33333 | AW85: =$F$85 -> 189.33333 | ... CW85: =$F$85 -> 189.33333
A86: 83 | B86: 45426 | C86: Ken Fait and Jimmyu Sabatino | D86: Initiation Fees | E86: 24500 | F86: =E86/60 -> 408.33333 | G86: 47238 | H86: =E86-SUM(I86:DP86) -> 0 | AP86: =$F$86 -> 408.33333 | AQ86: =$F$86 -> 408.33333 | AR86: =$F$86 -> 408.33333 | AS86: =$F$86 -> 408.33333 | AT86: =$F$86 -> 408.33333 | AU86: =$F$86 -> 408.33333 | AV86: =$F$86 -> 408.33333 | AW86: =$F$86 -> 408.33333 | ... CW86: =$F$86 -> 408.33333
A87: 84 | B87: 45443 | C87: Bruce and Jackie Gulbas | D87: Initiation Fees | E87: 22500 | F87: =E87/60 -> 375 | G87: 47238 | H87: =E87-SUM(I87:DP87) -> 0 | AQ87: =$F$87 -> 375 | AR87: =$F$87 -> 375 | AS87: =$F$87 -> 375 | AT87: =$F$87 -> 375 | AU87: =$F$87 -> 375 | AV87: =$F$87 -> 375 | AW87: =$F$87 -> 375 | AX87: =$F$87 -> 375 | ... CX87: =$F$87 -> 375
A88: 85 | B88: 45443 | C88: Dean Miles | D88: Monthly Membership Dues | E88: 1000 | F88: 1000 | G88: 45444 | H88: =E88-SUM(I88:DP88) -> 0 | AQ88: =F88 -> 1000
A89: 86 | B89: 45466 | C89: Nik Kafetzopoulos | D89: Initiation Fees | E89: 10500 | F89: =E89/60 -> 175 | G89: 47269 | H89: =E89-SUM(I89:DP89) -> 0 | AQ89: =$F$89 -> 175 | AR89: =$F$89 -> 175 | AS89: =$F$89 -> 175 | AT89: =$F$89 -> 175 | AU89: =$F$89 -> 175 | AV89: =$F$89 -> 175 | AW89: =$F$89 -> 175 | AX89: =$F$89 -> 175 | ... CX89: =$F$89 -> 175
A90: 87 | B90: 45453 | C90: Eric Dall | D90: Initiation Fees | E90: 12000 | F90: =E90/60 -> 200 | G90: 47290 | H90: =E90-SUM(I90:DP90) -> 0 | AQ90: =$F$90 -> 200 | AR90: =$F$90 -> 200 | AS90: =$F$90 -> 200 | AT90: =$F$90 -> 200 | AU90: =$F$90 -> 200 | AV90: =$F$90 -> 200 | AW90: =$F$90 -> 200 | AX90: =$F$90 -> 200 | ... CX90: =$F$90 -> 200
A91: 88 | B91: 45453 | C91: Eric Dall | D91: Monthly Membership Dues | E91: 18000 | F91: =E91/12 -> 1500 | G91: 45808 | H91: =E91-SUM(I91:DP91) -> 0 | AQ91: =$F$91 -> 1500 | AR91: =$F$91 -> 1500 | AS91: =$F$91 -> 1500 | AT91: =$F$91 -> 1500 | AU91: =$F$91 -> 1500 | AV91: =$F$91 -> 1500 | AW91: =$F$91 -> 1500 | AX91: =$F$91 -> 1500 | ... BB91: =$F$91 -> 1500
A92: 89 | B92: 45523 | C92: Gary Highland | D92: Monthly Membership Dues | E92: 9155 | F92: =E92/12 -> 762.91667 | G92: 45857 | H92: =E92-SUM(I92:DP92) -> 0 | AS92: =$F$92 -> 762.91667 | AT92: =$F$92 -> 762.91667 | AU92: =$F$92 -> 762.91667 | AV92: =$F$92 -> 762.91667 | AW92: =$F$92 -> 762.91667 | AX92: =$F$92 -> 762.91667 | AY92: =$F$92 -> 762.91667 | AZ92: =$F$92 -> 762.91667 | ... BD92: =$F$92 -> 762.91667
A93: 90 | B93: 45572 | C93: Martin Lopez | D93: Monthly Membership Dues | E93: 9515 | F93: =E93/12 -> 792.91667 | G93: 45907 | H93: =E93-SUM(I93:DP93) -> 0 | AU93: =F93 -> 792.91667 | AV93: =AU93 -> 792.91667 | AW93: =AV93 -> 792.91667 | AX93: =AW93 -> 792.91667 | AY93: =AX93 -> 792.91667 | AZ93: =AY93 -> 792.91667 | BA93: =AZ93 -> 792.91667 | BB93: =BA93 -> 792.91667 | BC93: =BB93 -> 792.91667 | ... BF93: =BE93 -> 792.91667
A94: 91 | B94: 45589 | C94: Joe DeCosta | D94: Monthly Membership Dues | E94: 11820 | F94: =E94/12 -> 985 | G94: 45559 | H94: =E94-SUM(I94:DP94) -> 0 | AU94: =F94 -> 985 | AV94: =AU94 -> 985 | AW94: =AV94 -> 985 | AX94: =AW94 -> 985 | AY94: =AX94 -> 985 | AZ94: =AY94 -> 985 | BA94: =AZ94 -> 985 | BB94: =BA94 -> 985 | BC94: =BB94 -> 985 | ... BF94: =BE94 -> 985
A95: 92 | B95: 45595 | C95: David Finke | D95: Monthly Membership Dues | E95: 3495 | F95: =E95/3 -> 1165 | G95: 45322 | H95: =E95-SUM(I95:DP95) -> 0 | AU95: =F95 -> 1165 | AV95: =AU95 -> 1165 | AW95: =AV95 -> 1165
A96: 93 | B96: 45596 | C96: Dean Miles | D96: Monthly Membership Dues | E96: 1000 | F96: 1000 | G96: 45626 | H96: =E96-SUM(I96:DP96) -> 0 | AV96: =F96 -> 1000
A97: 94 | B97: 45597 | C97: John (Jack) Biehl | D97: Monthly Membership Dues | E97: 3495 | F97: =E97/3 -> 1165 | G97: 45322 | H97: =E97-SUM(I97:DP97) -> 0 | AV97: =F97 -> 1165 | AW97: =AV97 -> 1165 | AX97: =AW97 -> 1165
A98: 95 | B98: 45597 | C98: Blake R Hite (Andrew & Goeff) | D98: Monthly Membership Dues | E98: 6900 | F98: =E98/3 -> 2300 | G98: 45322 | H98: =E98-SUM(I98:DP98) -> 0 | AV98: =F98 -> 2300 | AW98: =AV98 -> 2300 | AX98: =AW98 -> 2300
A99: 96 | B99: 45638 | C99: Ken Sunshine | D99: Monthly Membership Dues | E99: 8250 | F99: =E99/12 -> 687.5 | G99: 45991 | H99: =E99-SUM(I99:DP99) -> 0 | AW99: =F99 -> 687.5 | AX99: =AW99 -> 687.5 | AY99: =AX99 -> 687.5 | AZ99: =AY99 -> 687.5 | BA99: =AZ99 -> 687.5 | BB99: =BA99 -> 687.5 | BC99: =BB99 -> 687.5 | BD99: =BC99 -> 687.5 | BE99: =BD99 -> 687.5 | ... BH99: =BG99 -> 687.5
A100: 97 | B100: 45638 | C100: Nancy Caruso | D100: Monthly Membership Dues | E100: 11000 | F100: =E100/12 -> 916.66667 | G100: 45991 | H100: =E100-SUM(I100:DP100) -> 0 | AW100: =F100 -> 916.66667 | AX100: =F100 -> 916.66667 | AY100: =AX100 -> 916.66667 | AZ100: =AY100 -> 916.66667 | BA100: =AZ100 -> 916.66667 | BB100: =BA100 -> 916.66667 | BC100: =BB100 -> 916.66667 | BD100: =BC100 -> 916.66667 | BE100: =BD100 -> 916.66667 | BF100: =BE100 -> 916.66667 | ... BH100: =BG100 -> 916.66667
A101: 98 | B101: 45650 | C101: Kelly Oconnell and Shelley Lacona | D101: Initiation Fees | E101: -8000 | F101: =E101/48 -> -166.66667 | H101: =E101-SUM(I101:DP101) -> 0 | AW101: =F101 -> -166.66667 | AX101: =AW101 -> -166.66667 | AY101: =AX101 -> -166.66667 | AZ101: =AY101 -> -166.66667 | BA101: =AZ101 -> -166.66667 | BB101: =BA101 -> -166.66667 | BC101: =BB101 -> -166.66667 | BD101: =BC101 -> -166.66667 | BE101: =BD101 -> -166.66667 | ... CR101: =CQ101 -> -166.66667
...

Sheet 21300 - Due to.from Socal
A1: Transaction Report
A2: Carefree Newport
A3: October 1-31, 2025
B5: Transaction date | C5: Transaction type | D5: Num | E5: Name | F5: Memo/Description | G5: Account full name | H5: Item split account | I5: Amount | J5: Balance
A6: 21300 Due To/From SoCal Nautical
B7: Beginning Balance | J7: 52906.41
B8: 10/31/2025 | C8: Journal Entry | D8: AURA 739 | F8: ADP - Payroll 8.31.25 | G8: 21300 Due To/From SoCal Nautical | I8: 468.66 | J8: 53375.07
A9: Total for 21300 Due To/From SoCal Nautical | I9: =I7+I8 -> 468.66
B10: TOTAL | I10: 468.66
B11: NO MOVEMENT FOR NOVEMBER
I22: Total | J22: =J8 -> 53375.07

Sheet Loan pmt Breakdown

Sheet 21350 - Insurance Payable
A2: First Insurance Policy | D2: Boat fees | R2: =A27*0.4 -> 44539.66
B3: Total Policy Amount | C3: Per Entity | D3: =4759 -> 4759 | F3: Total Amount Per Entity
A4: OMO0038329 | B4: 110530 | C4: =73257+14620 -> 87877 | D4: =C4/C6 -> 0.69611058 | E4: =D3*D4 -> 3312.7903 | F4: =C4+E4 -> 91189.79 | K4: =130999 -> 130999
A5: XLO0034678 | B5: 20469 | C5: =32514+5849 -> 38363 | D5: =C5/C6 -> 0.30388942 | E5: =D5*D3 -> 1446.2097 | F5: =C5+E5 -> 39809.21 | J5: Socal Insurance Liability | K5: =F4 -> 91189.79 | R5: Carefree END
B6: =SUM(B4:B5) -> 130999 | C6: =SUM(C4:C5) -> 126240 | J6: Carefree Insurance Liabilty | K6: =F5 -> 39809.21
K8: Downpayment | L8: Fees | M8: DOWNPAYMENT PER ENTITY
A9: Socal(SD) Portion 70% | B9: =F4 -> 91189.79 | D9: Carefreee(Newport) Portion 30% | E9: =F5 -> 39809.21 | J9: Down payment | K9: =19649.85 -> 19649.85 | L9: 589.5
A10: Amortization | B10: =B9/12 -> 7599.1492 | D10: Amortization | E10: =E9/12 -> 3317.4341
J11: Socal Portion | K11: =K9*0.7 -> 13754.895 | L11: =L9*0.7 -> 412.65 | M11: =SUM(K11:L11) -> 14167.545
A12: January | B12: =$B$10 -> 7599.1492 | D12: January | E12: =$E$10 -> 3317.4341 | J12: Carefree Portion | K12: =K9*0.3 -> 5894.955 | L12: =L9*0.3 -> 176.85 | M12: =SUM(K12:L12) -> 6071.805
A13: February | B13: =$B$10 -> 7599.1492 | D13: February | E13: =$E$10 -> 3317.4341
A14: March | B14: =$B$10 -> 7599.1492 | D14: March | E14: =$E$10 -> 3317.4341
A15: April | B15: =$B$10 -> 7599.1492 | D15: April | E15: =$E$10 -> 3317.4341
A16: May | B16: =$B$10 -> 7599.1492 | D16: May | E16: =$E$10 -> 3317.4341
A17: June | B17: =$B$10 -> 7599.1492 | D17: June | E17: =$E$10 -> 3317.4341
A18: July | B18: =$B$10 -> 7599.1492 | D18: July | E18: =$E$10 -> 3317.4341
A19: August | B19: =$B$10 -> 7599.1492 | D19: August | E19: =$E$10 -> 3317.4341
A20: September | B20: =$B$10 -> 7599.1492 | D20: September | E20: =$E$10 -> 3317.4341
A21: October | B21: =$B$10 -> 7599.1492 | D21: October | E21: =$E$10 -> 3317.4341
A22: November | B22: =$B$10 -> 7599.1492 | D22: November | E22: =$E$10 -> 3317.4341
A23: December | B23: =$B$10 -> 7599.1492 | D23: December | E23: =$E$10 -> 3317.4341
B25: =SUM(B12:B24) -> 91189.79 | E25: =SUM(E12:E24) -> 39809.21
A27: =K4-K9 -> 111349.15
A28: 0.1085
A29: 11696.12
C30: =SUM(C34:C35)*0.4 -> 8590.1303
F31: Ending Balance | R31: SoCal | S31: Carefree
B32: PAYMENT | C32: PRINCIPAL | D32: INTEREST | F32: =A27 -> 111349.15 | G32: SOCAL PORTION | H32: SOCAL PORTION | I32: ADJUSTMENT | J32: SOCAL END BALANCE | K32: CAREFREE PORTION | L32: CAREFREE PORTION | M32: ADJUSTMENT | N32: CAREFREE END BALANCE | Q32: 7905.37 | R32: 0.7 | S32: 0.3
A33: 45657 | J33: =K5-K11 -> 77434.895 | N33: =E9-K12 -> 33914.255
A34: =EOMONTH(A33,1) -> 45688 | B34: =$A$29 -> 11696.12 | C34: =B34-D34 -> 10689.338 | D34: =((F32*$A$28)/12) -> 1006.7819 | F34: =F32-C34 -> 100659.81 | G34: =C34*$D$4 -> 7440.9614 | H34: =D34*$D$4 -> 700.83153 | J34: =J33-G34 -> 69993.934 | K34: =C34*$D$5 -> 3248.3767 | L34: =D34*$D$5 -> 305.95036 | N34: =N33-K34 -> 30665.878 | O34: =N33-K34 -> 30665.878 | P34: Over-Payment Late Fee | Q34: =Q32-B43 -> 0 | R34: =Q34*R32 -> 0 | S34: =Q34*S32 -> 0
A35: =EOMONTH(A34,1) -> 45716 | B35: =$A$29 -> 11696.12 | C35: =B35-D35 -> 10785.988 | D35: =((F34*$A$28)/12) -> 910.13247 | F35: =F34-C35 -> 89873.824 | G35: =C35*$D$4 -> 7508.2401 | H35: =D35*$D$4 -> 633.55284 | J35: =J34-G35 -> 62485.694 | K35: =C35*$D$5 -> 3277.7475 | L35: =D35*$D$5 -> 276.57962 | N35: =N34-K35 -> 27388.131 | P35: Security & Delivery Fee | Q35: 237.16 | R35: =Q35*R32 -> 166.012 | S35: =Q35*S32 -> 71.148
A36: =EOMONTH(A35,1) -> 45747 | B36: =$A$29 -> 11696.12 | C36: =B36-D36 -> 10883.511 | D36: =((F35*$A$28)/12) -> 812.60916 | F36: =F35-C36 -> 78990.314 | G36: =C36*$D$4 -> 7576.1271 | H36: =D36*$D$4 -> 565.66584 | J36: =J35-G36 -> 54909.567 | K36: =C36*$D$5 -> 3307.3838 | L36: =D36*$D$5 -> 246.94332 | N36: =N35-K36 -> 24080.747
A37: =EOMONTH(A36,1) -> 45777 | B37: =$A$29 -> 11696.12 | C37: =B37-D37 -> 10981.916 | D37: =((F36*$A$28)/12) -> 714.20408 | F37: =F36-C37 -> 68008.398 | G37: =C37*$D$4 -> 7644.6279 | H37: =D37*$D$4 -> 497.16502 | J37: =J36-G37 -> 47264.939 | K37: =C37*$D$5 -> 3337.288 | L37: =D37*$D$5 -> 217.03906 | N37: =N36-K37 -> 20743.459 | R37: =SUM(R34:R36) -> 166.012 | S37: =SUM(S34:S36) -> 71.148
A38: =EOMONTH(A37,1) -> 45808 | B38: =$A$29 -> 11696.12 | C38: =B38-D38 -> 11081.211 | D38: =((F37*$A$28)/12) -> 614.90926 | F38: =F37-C38 -> 56927.187 | G38: =C38*$D$4 -> 7713.7481 | H38: =D38*$D$4 -> 428.04484 | J38: =J37-G38 -> 39551.191 | K38: =C38*$D$5 -> 3367.4627 | L38: =D38*$D$5 -> 186.86442 | N38: =N37-K38 -> 17375.996
A39: =EOMONTH(A38,1) -> 45838 | B39: =$A$29 -> 11696.12 | C39: =B39-D39 -> 11181.403 | D39: =((F38*$A$28)/12) -> 514.71665 | F39: =F38-C39 -> 45745.784 | G39: =C39*$D$4 -> 7783.4932 | H39: =D39*$D$4 -> 358.29971 | J39: =J38-G39 -> 31767.698 | K39: =C39*$D$5 -> 3397.9101 | L39: =D39*$D$5 -> 156.41694 | N39: =N38-K39 -> 13978.086
A40: =EOMONTH(A39,1) -> 45869 | B40: =$A$29 -> 11696.12 | C40: =B40-D40 -> 11282.502 | D40: =((F39*$A$28)/12) -> 413.61813 | F40: =F39-C40 -> 34463.282 | G40: =C40*$D$4 -> 7853.869 | H40: =D40*$D$4 -> 287.92395 | J40: =J39-G40 -> 23913.829 | K40: =C40*$D$5 -> 3428.6329 | L40: =D40*$D$5 -> 125.69417 | N40: =N39-K40 -> 10549.453
A41: =EOMONTH(A40,1) -> 45900 | B41: =$A$29 -> 11696.12 | C41: =B41-D41 -> 11384.514 | D41: =((F40*$A$28)/12) -> 311.6055 | F41: =F40-C41 -> 23078.767 | G41: =C41*$D$4 -> 7924.881 | H41: =D41*$D$4 -> 216.91189 | J41: =J40-G41 -> 15988.948 | K41: =C41*$D$5 -> 3459.6335 | L41: =D41*$D$5 -> 94.693615 | N41: =N40-K41 -> 7089.8196
A42: =EOMONTH(A41,1) -> 45930 | B42: =$A$29 -> 11696.12 | C42: =B42-D42 -> 11487.449 | D42: =((F41*$A$28)/12) -> 208.67052 | F42: =F41-C42 -> 11591.318 | G42: =C42*$D$4 -> 7996.5352 | H42: =D42*$D$4 -> 145.25776 | J42: =J41-G42 -> 7992.4124 | K42: =C42*$D$5 -> 3490.9143 | L42: =D42*$D$5 -> 63.412763 | N42: =N41-K42 -> 3598.9052
B43: =7905.37 -> 7905.37 | C43: =B43-D43 -> 7905.37 | D43: 0 | F43: =F42-C43-E43 -> 3685.9477 | G43: =C43*$D$4 -> 5503.0117 | H43: =D43*$D$4 -> 0 | J43: =J42-G43 -> 2489.4007 | K43: =C43*$D$5 -> 2402.3583 | L43: =D43*$D$5 -> 0 | N43: =N42-K43 -> 1196.5469
A44: 45961 | D44: 0 | E44: =F43--2455 -> 6140.9477 | F44: =F43-C44-E44 -> -2455 | I44: =-J44+J43 -> 4198.3522 | J44: =C47 -> -1708.9515 | M44: =-N44+N43 -> 1942.5955 | N44: =C48 -> -746.04852
A46: EMAIL CONFIRMATION | C46: -2455 | E46: ADJUSTMENT WILL BE MADE TO INSURANCE (SEE PREPAID EXPENSE)
A47: SOCAL | B47: =D4 -> 0.69611058 | C47: =C46*B47 -> -1708.9515
A48: CAREFREE | B48: =D5 -> 0.30388942 | C48: =C46*B48 -> -746.04852

Sheet 23500 - Insurance Payable
A2: First Insurance Policy | D2: Agency Fees
B3: Total Policy Amount | C3: Per Entity | D3: 1000 | F3: Total Amount Per Entity
A4: OMO0038329 | B4: 94637 | C4: =61104+15130 -> 76234 | D4: =C4/C7 -> 0.66401874 | E4: =D3*D4 -> 664.01874 | F4: =C4+E4 -> 76898.019
A5: XLO0034678 | B5: 20170 | C5: =33533+5040 -> 38573 | D5: =C5/C7 -> 0.33598126 | E5: =D5*D3 -> 335.98126 | F5: =C5+E5 -> 38908.981
A6: AGENCY FEE | B6: 1000
B7: =SUM(B4:B6) -> 115807 | C7: =SUM(C4:C5) -> 114807
K9: 115807
A10: Socal(SD) Portion 70% | B10: =F4 -> 76898.019 | D10: Carefreee(Newport) Portion 30% | E10: =F5 -> 38908.981 | J10: Socal Insurance Liability | K10: =F4 -> 76898.019
A11: Amortization | B11: =B10/12 -> 6408.1682 | D11: Amortization | E11: =E10/12 -> 3242.4151 | J11: Carefree Insurance Liabilty | K11: =F5 -> 38908.981
A13: January | B13: =$B$11 -> 6408.1682 | D13: January | E13: =$E$11 -> 3242.4151 | K13: Downpayment | L13: Fees | M13: DOWNPAYMENT PER ENTITY
A14: February | B14: =$B$11 -> 6408.1682 | D14: February | E14: =$E$11 -> 3242.4151 | J14: Down payment | K14: 23161.4 | L14: 752.75
A15: March | B15: =$B$11 -> 6408.1682 | D15: March | E15: =$E$11 -> 3242.4151 | J15: Socal Portion | K15: =K14*D4 -> 15379.604 | L15: =L14*D4 -> 499.84011 | M15: =SUM(K15:L15) -> 15879.444
A16: April | B16: =$B$11 -> 6408.1682 | D16: April | E16: =$E$11 -> 3242.4151 | J16: Carefree Portion | K16: =K14*D5 -> 7781.7963 | L16: =L14*D5 -> 252.90989 | M16: =SUM(K16:L16) -> 8034.7061
A17: May | B17: =$B$11 -> 6408.1682 | D17: May | E17: =$E$11 -> 3242.4151
A18: June | B18: =$B$11 -> 6408.1682 | D18: June | E18: =$E$11 -> 3242.4151
A19: July | B19: =$B$11 -> 6408.1682 | D19: July | E19: =$E$11 -> 3242.4151
A20: August | B20: =$B$11 -> 6408.1682 | D20: August | E20: =$E$11 -> 3242.4151
A21: September | B21: =$B$11 -> 6408.1682 | D21: September | E21: =$E$11 -> 3242.4151
A22: October | B22: =$B$11 -> 6408.1682 | D22: October | E22: =$E$11 -> 3242.4151
A23: November | B23: =$B$11 -> 6408.1682 | D23: November | E23: =$E$11 -> 3242.4151
A24: December | B24: =$B$11 -> 6408.1682 | D24: December | E24: =$E$11 -> 3242.4151
B26: =SUM(B13:B25) -> 76898.019 | E26: =SUM(E13:E25) -> 38908.981
A28: 92645.6
A29: 0.1052
A30: 9717.11
C31: =SUM(C36:C37)*0.4 -> 7155.1601
F32: Ending Balance | R32: SoCal | S32: Carefree
B33: PAYMENT | C33: PRINCIPAL | D33: INTEREST | F33: =A28 -> 92645.6 | G33: SOCAL PORTION | H33: SOCAL PORTION | I33: ADJUSTMENT | J33: SOCAL END BALANCE | K33: CAREFREE PORTION | L33: CAREFREE PORTION | M33: ADJUSTMENT | N33: CAREFREE END BALANCE | R33: =D4 -> 0.66401874 | S33: =D5 -> 0.33598126
A34: 45991 | J34: =K10-K15 -> 61518.415 | N34: =E10-K16 -> 31127.185
A35: =EOMONTH(A34,1) -> 46022 | F35: =F33 -> 92645.6 | J35: =J34 -> 61518.415 | N35: =N34 -> 31127.185
A36: =EOMONTH(A35,1) -> 46053 | B36: =$A$30 -> 9717.11 | C36: =B36-D36 -> 8904.9169 | D36: =((F33*$A$29)/12) -> 812.19309 | F36: =F33-C36 -> 83740.683 | G36: =C36*$D$4 -> 5913.0317 | H36: =D36*$D$4 -> 539.31144 | J36: =J34-G36 -> 55605.383 | K36: =C36*$D$5 -> 2991.8852 | L36: =D36*$D$5 -> 272.88166 | N36: =N34-K36 -> 28135.3 | P36: Over-Payment Late Fee | R36: =Q36*R33 -> 0 | S36: =Q36*S33 -> 0
A37: =EOMONTH(A36,1) -> 46081 | B37: =$A$30 -> 9717.11 | C37: =B37-D37 -> 8982.9833 | D37: =((F36*$A$29)/12) -> 734.12666 | F37: =F36-C37 -> 74757.7 | G37: =C37*$D$4 -> 5964.8693 | H37: =D37*$D$4 -> 487.47386 | J37: =J36-G37 -> 49640.514 | K37: =C37*$D$5 -> 3018.114 | L37: =D37*$D$5 -> 246.6528 | N37: =N36-K37 -> 25117.186 | P37: Security & Delivery Fee | R37: =Q37*R33 -> 0 | S37: =Q37*S33 -> 0
A38: =EOMONTH(A37,1) -> 46112 | B38: =$A$30 -> 9717.11 | C38: =B38-D38 -> 9061.7342 | D38: =((F37*$A$29)/12) -> 655.37583 | F38: =F37-C38 -> 65695.966 | G38: =C38*$D$4 -> 6017.1613 | H38: =D38*$D$4 -> 435.18184 | J38: =J37-G38 -> 43623.353 | K38: =C38*$D$5 -> 3044.5728 | L38: =D38*$D$5 -> 220.194 | N38: =N37-K38 -> 22072.613
A39: =EOMONTH(A38,1) -> 46142 | B39: =$A$30 -> 9717.11 | C39: =B39-D39 -> 9141.1754 | D39: =((F38*$A$29)/12) -> 575.93463 | F39: =F38-C39 -> 56554.79 | G39: =C39*$D$4 -> 6069.9118 | H39: =D39*$D$4 -> 382.43139 | J39: =J38-G39 -> 37553.441 | K39: =C39*$D$5 -> 3071.2636 | L39: =D39*$D$5 -> 193.50324 | N39: =N38-K39 -> 19001.349 | R39: =SUM(R36:R38) -> 0 | S39: =SUM(S36:S38) -> 0
A40: =EOMONTH(A39,1) -> 46173 | B40: =$A$30 -> 9717.11 | C40: =B40-D40 -> 9221.313 | D40: =((F39*$A$29)/12) -> 495.79699 | F40: =F39-C40 -> 47333.477 | G40: =C40*$D$4 -> 6123.1247 | H40: =D40*$D$4 -> 329.2185 | J40: =J39-G40 -> 31430.316 | K40: =C40*$D$5 -> 3098.1883 | L40: =D40*$D$5 -> 166.5785 | N40: =N39-K40 -> 15903.161
A41: =EOMONTH(A40,1) -> 46203 | B41: =$A$30 -> 9717.11 | C41: =B41-D41 -> 9302.1532 | D41: =((F40*$A$29)/12) -> 414.95682 | F41: =F40-C41 -> 38031.324 | G41: =C41*$D$4 -> 6176.8041 | H41: =D41*$D$4 -> 275.5391 | J41: =J40-G41 -> 25253.512 | K41: =C41*$D$5 -> 3125.3491 | L41: =D41*$D$5 -> 139.41771 | N41: =N40-K41 -> 12777.812
A42: =EOMONTH(A41,1) -> 46234 | B42: =$A$30 -> 9717.11 | C42: =B42-D42 -> 9383.7021 | D42: =((F41*$A$29)/12) -> 333.40794 | F42: =F41-C42 -> 28647.622 | G42: =C42*$D$4 -> 6230.9541 | H42: =D42*$D$4 -> 221.38912 | J42: =J41-G42 -> 19022.558 | K42: =C42*$D$5 -> 3152.748 | L42: =D42*$D$5 -> 112.01882 | N42: =N41-K42 -> 9625.064
A43: =EOMONTH(A42,1) -> 46265 | B43: =$A$30 -> 9717.11 | C43: =B43-D43 -> 9465.9658 | D43: =((F42*$A$29)/12) -> 251.14415 | F43: =F42-C43 -> 19181.656 | G43: =C43*$D$4 -> 6285.5788 | H43: =D43*$D$4 -> 166.76442 | J43: =J42-G43 -> 12736.979 | K43: =C43*$D$5 -> 3180.3871 | L43: =D43*$D$5 -> 84.379728 | N43: =N42-K43 -> 6444.6769
A44: =EOMONTH(A43,1) -> 46295 | B44: =$A$30 -> 9717.11 | C44: =B44-D44 -> 9548.9508 | D44: =((F43*$A$29)/12) -> 168.15919 | F44: =F43-C44 -> 9632.7053 | G44: =C44*$D$4 -> 6340.6823 | H44: =D44*$D$4 -> 111.66085 | J44: =J43-G44 -> 6396.2969 | K44: =C44*$D$5 -> 3208.2685 | L44: =D44*$D$5 -> 56.498334 | N44: =N43-K44 -> 3236.4084
A45: =EOMONTH(A44,1) -> 46326 | B45: =$A$30 -> 9717.11 | C45: =B45-D45 -> 9632.6633 | D45: =((F44*$A$29)/12) -> 84.446716 | F45: =F44-C45 -> 0.042020603 | G45: =C45*$D$4 -> 6396.269 | H45: =D45*$D$4 -> 56.074203 | J45: =J44-G45 -> 0.027902468 | K45: =C45*$D$5 -> 3236.3943 | L45: =D45*$D$5 -> 28.372514 | N45: =N44-K45 -> 0.014118135

Sheet 22000 & 23000 - Axopar Suntop37
A1: 273000
A2: 60 | B2: # of Periods | C2: 5935.68
A3: 0.11 | B3: APR
A4: =A3/12 -> 0.0091666667 | B4: Interest/Period
J5: Closing Date | K5: 45777 | M5: Current Portion | N5: =SUMIF(H:H,"<="&DATE(YEAR(K5),MONTH(K5)+12,DAY(K5)),D:D)-SUMIF(H:H,"<"&K5+1,D:D) -> 0.00045266328 | P5: =N5-O5 -> 0.00045266328
M6: Long Term Portion | N6: =INDEX(B:F,MATCH(K5,H:H,0),5)-N5 -> -0.0043644141 | P6: =N6-O6 -> -0.0043644141
M7: Total | N7: =N6+N5 -> -0.0039117509
C8: Payment | D8: Principal | E8: Interest | F8: Ending | G8: Accrued interest | H8: Date | M8: Check | N8: =INDEX(B:F,MATCH(K5,H:H,0),5)-N7 -> 0
A9: 44698 | B9: 0 | F9: =A1-C9 -> 273000 | H9: 44698
A10: 44688 | B10: 1 | C10: =$C$2 -> 5935.68 | D10: =C10-E10 -> 3433.18 | E10: =(F9+G9)*(1/12)*$A$3 -> 2502.5 | F10: =F9-D10 -> 269566.82 | H10: 44688
A11: =EOMONTH(A10,1) -> 44742 | B11: 2 | C11: =$C$2 -> 5935.68 | D11: =C11-E11 -> 3464.6508 | E11: =(F10+G10)*(1/12)*$A$3 -> 2471.0292 | F11: =F10-D11 -> 266102.17 | H11: =EOMONTH(H10,1) -> 44742
A12: =EOMONTH(A11,1) -> 44773 | B12: 3 | C12: =$C$2 -> 5935.68 | D12: =C12-E12 -> 3496.4101 | E12: =(F11+G11)*(1/12)*$A$3 -> 2439.2699 | F12: =F11-D12 -> 262605.76 | H12: =EOMONTH(H11,1) -> 44773
A13: =EOMONTH(A12,1) -> 44804 | B13: 4 | C13: =$C$2 -> 5935.68 | D13: =C13-E13 -> 3528.4605 | E13: =(F12+G12)*(1/12)*$A$3 -> 2407.2195 | F13: =F12-D13 -> 259077.3 | H13: =EOMONTH(H12,1) -> 44804
A14: =EOMONTH(A13,1) -> 44834 | B14: 5 | C14: =$C$2 -> 5935.68 | D14: =C14-E14 -> 3560.8048 | E14: =(F13+G13)*(1/12)*$A$3 -> 2374.8752 | F14: =F13-D14 -> 255516.49 | H14: =EOMONTH(H13,1) -> 44834
A15: =EOMONTH(A14,1) -> 44865 | B15: 6 | C15: =$C$2 -> 5935.68 | D15: =C15-E15 -> 3593.4455 | E15: =(F14+G14)*(1/12)*$A$3 -> 2342.2345 | F15: =F14-D15 -> 251923.05 | H15: =EOMONTH(H14,1) -> 44865
A16: =EOMONTH(A15,1) -> 44895 | B16: 7 | C16: =$C$2 -> 5935.68 | D16: =C16-E16 -> 3626.3854 | E16: =(F15+G15)*(1/12)*$A$3 -> 2309.2946 | F16: =F15-D16 -> 248296.66 | H16: =EOMONTH(H15,1) -> 44895
A17: =EOMONTH(A16,1) -> 44926 | B17: 8 | C17: =$C$2 -> 5935.68 | D17: =C17-E17 -> 3659.6273 | E17: =(F16+G16)*(1/12)*$A$3 -> 2276.0527 | F17: =F16-D17 -> 244637.04 | H17: =EOMONTH(H16,1) -> 44926 | K17: =C10/2 -> 2967.84
A18: =EOMONTH(A17,1) -> 44957 | B18: 9 | C18: =$C$2 -> 5935.68 | D18: =C18-E18 -> 3693.1738 | E18: =(F17+G17)*(1/12)*$A$3 -> 2242.5062 | F18: =F17-D18 -> 240943.86 | H18: =EOMONTH(H17,1) -> 44957
A19: =EOMONTH(A18,1) -> 44985 | B19: 10 | C19: =$C$2 -> 5935.68 | D19: =C19-E19 -> 3727.0279 | E19: =(F18+G18)*(1/12)*$A$3 -> 2208.6521 | F19: =F18-D19 -> 237216.83 | H19: =EOMONTH(H18,1) -> 44985
A20: =EOMONTH(A19,1) -> 45016 | B20: 11 | C20: =$C$2 -> 5935.68 | D20: =C20-E20 -> 3761.1924 | E20: =(F19+G19)*(1/12)*$A$3 -> 2174.4876 | F20: =F19-D20 -> 233455.64 | H20: =EOMONTH(H19,1) -> 45016
A21: =EOMONTH(A20,1) -> 45046 | B21: 12 | C21: =$C$2 -> 5935.68 | D21: =C21-E21 -> 3795.67 | E21: =(F20+G20)*(1/12)*$A$3 -> 2140.01 | F21: =F20-D21 -> 229659.97 | H21: =EOMONTH(H20,1) -> 45046
A22: =EOMONTH(A21,1) -> 45077 | B22: 13 | C22: =$C$2 -> 5935.68 | D22: =C22-E22 -> 3830.4636 | E22: =(F21+G21)*(1/12)*$A$3 -> 2105.2164 | F22: =F21-D22 -> 225829.51 | H22: =EOMONTH(H21,1) -> 45077
A23: =EOMONTH(A22,1) -> 45107 | B23: 14 | C23: =$C$2 -> 5935.68 | D23: =C23-E23 -> 3865.5762 | E23: =(F22+G22)*(1/12)*$A$3 -> 2070.1038 | F23: =F22-D23 -> 221963.93 | H23: =EOMONTH(H22,1) -> 45107
A24: =EOMONTH(A23,1) -> 45138 | B24: 15 | C24: =$C$2 -> 5935.68 | D24: =C24-E24 -> 3901.0106 | E24: =(F23+G23)*(1/12)*$A$3 -> 2034.6694 | F24: =F23-D24 -> 218062.92 | H24: =EOMONTH(H23,1) -> 45138
A25: =EOMONTH(A24,1) -> 45169 | B25: 16 | C25: =$C$2 -> 5935.68 | D25: =C25-E25 -> 3936.7699 | E25: =(F24+G24)*(1/12)*$A$3 -> 1998.9101 | F25: =F24-D25 -> 214126.15 | H25: =EOMONTH(H24,1) -> 45169
A26: =EOMONTH(A25,1) -> 45199 | B26: 17 | C26: =$C$2 -> 5935.68 | D26: =C26-E26 -> 3972.8569 | E26: =(F25+G25)*(1/12)*$A$3 -> 1962.8231 | F26: =F25-D26 -> 210153.29 | H26: =EOMONTH(H25,1) -> 45199
A27: =EOMONTH(A26,1) -> 45230 | B27: 18 | C27: =$C$2 -> 5935.68 | D27: =C27-E27 -> 4009.2748 | E27: =(F26+G26)*(1/12)*$A$3 -> 1926.4052 | F27: =F26-D27 -> 206144.02 | H27: =EOMONTH(H26,1) -> 45230
A28: =EOMONTH(A27,1) -> 45260 | B28: 19 | C28: =$C$2 -> 5935.68 | D28: =C28-E28 -> 4046.0265 | E28: =(F27+G27)*(1/12)*$A$3 -> 1889.6535 | F28: =F27-D28 -> 202097.99 | H28: =EOMONTH(H27,1) -> 45260
A29: =EOMONTH(A28,1) -> 45291 | B29: 20 | C29: =$C$2 -> 5935.68 | D29: =C29-E29 -> 4083.1151 | E29: =(F28+G28)*(1/12)*$A$3 -> 1852.5649 | F29: =F28-D29 -> 198014.88 | H29: =EOMONTH(H28,1) -> 45291
... A38: =EOMONTH(A37,1) -> 45565 | B38: 29 | C38: =$C$2 -> 5935.68 | D38: =C38-E38 -> 4432.5913 | E38: =(F37+G37)*(1/12)*$A$3 -> 1503.0887 | F38: =F37-D38 -> 159540.72 | H38: =EOMONTH(H37,1) -> 45565
A39: =EOMONTH(A38,1) -> 45596 | B39: 30 | C39: =5985.68 -> 5985.68 | D39: =C39-E39 -> 4523.2234 | E39: =(F38+G38)*(1/12)*$A$3 -> 1462.4566 | F39: =F38-D39 -> 155017.49 | H39: =EOMONTH(H38,1) -> 45596
A40: =EOMONTH(A39,1) -> 45626 | B40: 31 | C40: =$C$2 -> 5935.68 | D40: =C40-E40 -> 4514.6863 | E40: =(F39+G39)*(1/12)*$A$3 -> 1420.9937 | F40: =F39-D40 -> 150502.81 | H40: =EOMONTH(H39,1) -> 45626
A41: =EOMONTH(A40,1) -> 45657 | B41: 32 | C41: =$C$2 -> 5935.68 | D41: =C41-E41 -> 4556.0709 | E41: =(F40+G40)*(1/12)*$A$3 -> 1379.6091 | F41: =F40-D41 -> 145946.74 | H41: =EOMONTH(H40,1) -> 45657
A42: =EOMONTH(A41,1) -> 45688 | B42: 33 | C42: =$C$2 -> 5935.68 | D42: =C42-E42 -> 4597.8349 | E42: =(F41+G41)*(1/12)*$A$3 -> 1337.8451 | F42: =F41-D42 -> 141348.9 | H42: =EOMONTH(H41,1) -> 45688 | I42: =D43-D42 -> 42.14682
A43: =EOMONTH(A42,1) -> 45716 | B43: 34 | C43: =$C$2 -> 5935.68 | D43: =C43-E43 -> 4639.9817 | E43: =(F42+G42)*(1/12)*$A$3 -> 1295.6983 | F43: =F42-D43 -> 136708.92 | H43: =EOMONTH(H42,1) -> 45716
A44: =EOMONTH(A43,1) -> 45747 | B44: 35 | C44: =$C$2 -> 5935.68 | D44: =C44-E44 -> 4682.5149 | E44: =(F43+G43)*(1/12)*$A$3 -> 1253.1651 | F44: =F43-D44 -> 132026.41 | H44: =EOMONTH(H43,1) -> 45747 | I44: =D44-D42 -> 84.679986 | K44: Homebuilders | M44: 67084.94
A45: =EOMONTH(A44,1) -> 45777 | B45: 36 | C45: =67084.94+64941.47 -> 132026.41 | D45: =C45-E45 -> 132026.41 | E45: 0 | F45: =F44-D45 -> -0.0039117509 | H45: =EOMONTH(H44,1) -> 45777 | I45: PAYOFF | K45: John Tomalsoff | M45: 47791.03
A46: =EOMONTH(A45,1) -> 45808 | B46: 37 | D46: =C46-E46 -> 3.5857716e-05 | E46: =(F45+G45)*(1/12)*$A$3 -> -3.5857716e-05 | F46: =F45-D46 -> -0.0039476086 | H46: =EOMONTH(H45,1) -> 45808 | K46: Loanmaker | M46: 231392.67
A47: =EOMONTH(A46,1) -> 45838 | B47: 38 | D47: =C47-E47 -> 3.6186412e-05 | E47: =(F46+G46)*(1/12)*$A$3 -> -3.6186412e-05 | F47: =F46-D47 -> -0.003983795 | H47: =EOMONTH(H46,1) -> 45838 | K47: Total Payments Made | M47: =SUM(M44:M46) -> 346268.64 | N47: Need statements
A48: =EOMONTH(A47,1) -> 45869 | B48: 39 | D48: =C48-E48 -> 3.6518121e-05 | E48: =(F47+G47)*(1/12)*$A$3 -> -3.6518121e-05 | F48: =F47-D48 -> -0.0040203131 | H48: =EOMONTH(H47,1) -> 45869 | K48: Axopar 37 Outstanding 31 Mar | M48: =F44 -> 132026.41
A49: =EOMONTH(A48,1) -> 45900 | B49: 40 | D49: =C49-E49 -> 3.685287e-05 | E49: =(F48+G48)*(1/12)*$A$3 -> -3.685287e-05 | F49: =F48-D49 -> -0.004057166 | H49: =EOMONTH(H48,1) -> 45900 | K49: Beneteau Outstanding 31 Mar | M49: ='22050 & 23050 - Beneteau'!F44 -> 114758.2
A50: =EOMONTH(A49,1) -> 45930 | B50: 41 | D50: =C50-E50 -> 3.7190688e-05 | E50: =(F49+G49)*(1/12)*$A$3 -> -3.7190688e-05 | F50: =F49-D50 -> -0.0040943567 | H50: =EOMONTH(H49,1) -> 45930 | K50: Axopar 28 Outstanding 31 Mar | M50: ='22300 & 23300 - Axopar T-TOP28'!G28 -> 93839.35
A51: =EOMONTH(A50,1) -> 45961 | B51: 42 | D51: =C51-E51 -> 3.7531603e-05 | E51: =(F50+G50)*(1/12)*$A$3 -> -3.7531603e-05 | F51: =F50-D51 -> -0.0041318883 | H51: =EOMONTH(H50,1) -> 45961 | K51: Remainder - Interest | M51: =M47-SUM(M48:M50) -> 5644.6854 | N51: Assumed for interest - to verify
A52: =EOMONTH(A51,1) -> 45991 | B52: 43 | D52: =C52-E52 -> 3.7875642e-05 | E52: =(F51+G51)*(1/12)*$A$3 -> -3.7875642e-05 | F52: =F51-D52 -> -0.0041697639 | H52: =EOMONTH(H51,1) -> 45991
A53: =EOMONTH(A52,1) -> 46022 | B53: 44 | D53: =C53-E53 -> 3.8222836e-05 | E53: =(F52+G52)*(1/12)*$A$3 -> -3.8222836e-05 | F53: =F52-D53 -> -0.0042079867 | H53: =EOMONTH(H52,1) -> 46022
A54: =EOMONTH(A53,1) -> 46053 | B54: 45 | D54: =C54-E54 -> 3.8573212e-05 | E54: =(F53+G53)*(1/12)*$A$3 -> -3.8573212e-05 | F54: =F53-D54 -> -0.00424656 | H54: =EOMONTH(H53,1) -> 46053
A55: =EOMONTH(A54,1) -> 46081 | B55: 46 | D55: =C55-E55 -> 3.89268e-05 | E55: =(F54+G54)*(1/12)*$A$3 -> -3.89268e-05 | F55: =F54-D55 -> -0.0042854868 | H55: =EOMONTH(H54,1) -> 46081
A56: =EOMONTH(A55,1) -> 46112 | B56: 47 | D56: =C56-E56 -> 3.9283629e-05 | E56: =(F55+G55)*(1/12)*$A$3 -> -3.9283629e-05 | F56: =F55-D56 -> -0.0043247704 | H56: =EOMONTH(H55,1) -> 46112
A57: =EOMONTH(A56,1) -> 46142 | B57: 48 | D57: =C57-E57 -> 3.9643729e-05 | E57: =(F56+G56)*(1/12)*$A$3 -> -3.9643729e-05 | F57: =F56-D57 -> -0.0043644141 | H57: =EOMONTH(H56,1) -> 46142
A58: =EOMONTH(A57,1) -> 46173 | B58: 49 | D58: =C58-E58 -> 4.0007129e-05 | E58: =(F57+G57)*(1/12)*$A$3 -> -4.0007129e-05 | F58: =F57-D58 -> -0.0044044212 | H58: =EOMONTH(H57,1) -> 46173
A59: =EOMONTH(A58,1) -> 46203 | B59: 50 | D59: =C59-E59 -> 4.0373861e-05 | E59: =(F58+G58)*(1/12)*$A$3 -> -4.0373861e-05 | F59: =F58-D59 -> -0.0044447951 | H59: =EOMONTH(H58,1) -> 46203
A60: =EOMONTH(A59,1) -> 46234 | B60: 51 | D60: =C60-E60 -> 4.0743955e-05 | E60: =(F59+G59)*(1/12)*$A$3 -> -4.0743955e-05 | F60: =F59-D60 -> -0.0044855391 | H60: =EOMONTH(H59,1) -> 46234
A61: =EOMONTH(A60,1) -> 46265 | B61: 52 | D61: =C61-E61 -> 4.1117441e-05 | E61: =(F60+G60)*(1/12)*$A$3 -> -4.1117441e-05 | F61: =F60-D61 -> -0.0045266565 | H61: =EOMONTH(H60,1) -> 46265
A62: =EOMONTH(A61,1) -> 46295 | B62: 53 | D62: =C62-E62 -> 4.1494351e-05 | E62: =(F61+G61)*(1/12)*$A$3 -> -4.1494351e-05 | F62: =F61-D62 -> -0.0045681509 | H62: =EOMONTH(H61,1) -> 46295
A63: =EOMONTH(A62,1) -> 46326 | B63: 54 | D63: =C63-E63 -> 4.1874716e-05 | E63: =(F62+G62)*(1/12)*$A$3 -> -4.1874716e-05 | F63: =F62-D63 -> -0.0046100256 | H63: =EOMONTH(H62,1) -> 46326
... A69: =EOMONTH(A68,1) -> 46507 | B69: 60 | D69: =C69-E69 -> 4.4231255e-05 | E69: =(F68+G68)*(1/12)*$A$3 -> -4.4231255e-05 | F69: =F68-D69 -> -0.004869459 | H69: =EOMONTH(H68,1) -> 46507

Sheet 22050 & 23050 - Beneteau
A1: 237000
A2: 60 | B2: # of Periods | C2: 5152.95
A3: 0.11 | B3: APR
A4: =A3/12 -> 0.0091666667 | B4: Interest/Period
J5: Closing Date | K5: 45777 | M5: Current Portion | N5: =SUMIF(H:H,"<="&DATE(YEAR(K5),MONTH(K5)+12,DAY(K5)),D:D)-SUMIF(H:H,"<"&K5+1,D:D) -> 0.00012240116 | P5: =N5-O5 -> 0.00012240116
M6: Long Term Portion | N6: =INDEX(B:F,MATCH(K5,H:H,0),5)-N5 -> -0.0011801475 | P6: =N6-O6 -> -0.0011801475
M7: Total | N7: =N6+N5 -> -0.0010577464
C8: Payment | D8: Principal | E8: Interest | F8: Ending | G8: Accrued interest | H8: Date | M8: Check | N8: =INDEX(B:F,MATCH(K5,H:H,0),5)-N7 -> 0
A9: 44652 | B9: 0 | F9: =A1-C9 -> 237000 | H9: 44652
A10: 44711 | B10: 1 | C10: 4911.22 | D10: =C10-E10 -> 2738.72 | E10: =(F9+G9)*(1/12)*$A$3 -> 2172.5 | F10: =F9-D10 -> 234261.28 | H10: 44711
A11: =EOMONTH(A10,1) -> 44742 | B11: 2 | C11: 5144.89 | D11: =C11-E11 -> 2997.4949 | E11: =(F10+G10)*(1/12)*$A$3 -> 2147.3951 | F11: =F10-D11 -> 231263.79 | H11: =EOMONTH(H10,1) -> 44742
A12: =EOMONTH(A11,1) -> 44773 | B12: 3 | C12: =$C$2 -> 5152.95 | D12: =C12-E12 -> 3033.032 | E12: =(F11+G11)*(1/12)*$A$3 -> 2119.918 | F12: =F11-D12 -> 228230.75 | H12: =EOMONTH(H11,1) -> 44773
A13: =EOMONTH(A12,1) -> 44804 | B13: 4 | C13: =$C$2 -> 5152.95 | D13: =C13-E13 -> 3060.8348 | E13: =(F12+G12)*(1/12)*$A$3 -> 2092.1152 | F13: =F12-D13 -> 225169.92 | H13: =EOMONTH(H12,1) -> 44804
A14: =EOMONTH(A13,1) -> 44834 | B14: 5 | C14: =$C$2 -> 5152.95 | D14: =C14-E14 -> 3088.8924 | E14: =(F13+G13)*(1/12)*$A$3 -> 2064.0576 | F14: =F13-D14 -> 222081.03 | H14: =EOMONTH(H13,1) -> 44834
A15: =EOMONTH(A14,1) -> 44865 | B15: 6 | C15: =$C$2 -> 5152.95 | D15: =C15-E15 -> 3117.2073 | E15: =(F14+G14)*(1/12)*$A$3 -> 2035.7427 | F15: =F14-D15 -> 218963.82 | H15: =EOMONTH(H14,1) -> 44865
A16: =EOMONTH(A15,1) -> 44895 | B16: 7 | C16: =$C$2 -> 5152.95 | D16: =C16-E16 -> 3145.7817 | E16: =(F15+G15)*(1/12)*$A$3 -> 2007.1683 | F16: =F15-D16 -> 215818.04 | H16: =EOMONTH(H15,1) -> 44895
A17: =EOMONTH(A16,1) -> 44926 | B17: 8 | C17: =$C$2+150 -> 5302.95 | D17: =C17-E17 -> 3324.618 | E17: =(F16+G16)*(1/12)*$A$3 -> 1978.332 | F17: =F16-D17 -> 212493.42 | H17: =EOMONTH(H16,1) -> 44926
A18: =EOMONTH(A17,1) -> 44957 | B18: 9 | C18: =$C$2 -> 5152.95 | D18: =C18-E18 -> 3205.0937 | E18: =(F17+G17)*(1/12)*$A$3 -> 1947.8563 | F18: =F17-D18 -> 209288.33 | H18: =EOMONTH(H17,1) -> 44957
A19: =EOMONTH(A18,1) -> 44985 | B19: 10 | C19: =$C$2 -> 5152.95 | D19: =C19-E19 -> 3234.4737 | E19: =(F18+G18)*(1/12)*$A$3 -> 1918.4763 | F19: =F18-D19 -> 206053.85 | H19: =EOMONTH(H18,1) -> 44985
A20: =EOMONTH(A19,1) -> 45016 | B20: 11 | C20: =$C$2 -> 5152.95 | D20: =C20-E20 -> 3264.123 | E20: =(F19+G19)*(1/12)*$A$3 -> 1888.827 | F20: =F19-D20 -> 202789.73 | H20: =EOMONTH(H19,1) -> 45016
A21: =EOMONTH(A20,1) -> 45046 | B21: 12 | C21: =$C$2 -> 5152.95 | D21: =C21-E21 -> 3294.0442 | E21: =(F20+G20)*(1/12)*$A$3 -> 1858.9058 | F21: =F20-D21 -> 199495.68 | H21: =EOMONTH(H20,1) -> 45046
A22: =EOMONTH(A21,1) -> 45077 | B22: 13 | C22: =$C$2 -> 5152.95 | D22: =C22-E22 -> 3324.2396 | E22: =(F21+G21)*(1/12)*$A$3 -> 1828.7104 | F22: =F21-D22 -> 196171.44 | H22: =EOMONTH(H21,1) -> 45077
A23: =EOMONTH(A22,1) -> 45107 | B23: 14 | C23: =$C$2 -> 5152.95 | D23: =C23-E23 -> 3354.7118 | E23: =(F22+G22)*(1/12)*$A$3 -> 1798.2382 | F23: =F22-D23 -> 192816.73 | H23: =EOMONTH(H22,1) -> 45107
A24: =EOMONTH(A23,1) -> 45138 | B24: 15 | C24: =$C$2 -> 5152.95 | D24: =C24-E24 -> 3385.4633 | E24: =(F23+G23)*(1/12)*$A$3 -> 1767.4867 | F24: =F23-D24 -> 189431.27 | H24: =EOMONTH(H23,1) -> 45138
A25: =EOMONTH(A24,1) -> 45169 | B25: 16 | C25: =$C$2 -> 5152.95 | D25: =C25-E25 -> 3416.4967 | E25: =(F24+G24)*(1/12)*$A$3 -> 1736.4533 | F25: =F24-D25 -> 186014.77 | H25: =EOMONTH(H24,1) -> 45169
A26: =EOMONTH(A25,1) -> 45199 | B26: 17 | C26: =$C$2 -> 5152.95 | D26: =C26-E26 -> 3447.8146 | E26: =(F25+G25)*(1/12)*$A$3 -> 1705.1354 | F26: =F25-D26 -> 182566.96 | H26: =EOMONTH(H25,1) -> 45199
A27: =EOMONTH(A26,1) -> 45230 | B27: 18 | C27: =$C$2 -> 5152.95 | D27: =C27-E27 -> 3479.4195 | E27: =(F26+G26)*(1/12)*$A$3 -> 1673.5305 | F27: =F26-D27 -> 179087.54 | H27: =EOMONTH(H26,1) -> 45230
A28: =EOMONTH(A27,1) -> 45260 | B28: 19 | C28: =$C$2 -> 5152.95 | D28: =C28-E28 -> 3511.3142 | E28: =(F27+G27)*(1/12)*$A$3 -> 1641.6358 | F28: =F27-D28 -> 175576.22 | H28: =EOMONTH(H27,1) -> 45260
A29: =EOMONTH(A28,1) -> 45291 | B29: 20 | C29: =$C$2 -> 5152.95 | D29: =C29-E29 -> 3543.5013 | E29: =(F28+G28)*(1/12)*$A$3 -> 1609.4487 | F29: =F28-D29 -> 172032.72 | H29: =EOMONTH(H28,1) -> 45291
... A38: =EOMONTH(A37,1) -> 45565 | B38: 29 | C38: =$C$2 -> 5152.95 | D38: =C38-E38 -> 3846.7917 | E38: =(F37+G37)*(1/12)*$A$3 -> 1306.1583 | F38: =F37-D38 -> 138643.21 | H38: =EOMONTH(H37,1) -> 45565
A39: =EOMONTH(A38,1) -> 45596 | B39: 30 | C39: =5202.95 -> 5202.95 | D39: =C39-E39 -> 3932.0539 | E39: =(F38+G38)*(1/12)*$A$3 -> 1270.8961 | F39: =F38-D39 -> 134711.15 | H39: =EOMONTH(H38,1) -> 45596
A40: =EOMONTH(A39,1) -> 45626 | B40: 31 | C40: =$C$2 -> 5152.95 | D40: =C40-E40 -> 3918.0978 | E40: =(F39+G39)*(1/12)*$A$3 -> 1234.8522 | F40: =F39-D40 -> 130793.06 | H40: =EOMONTH(H39,1) -> 45626
A41: =EOMONTH(A40,1) -> 45657 | B41: 32 | C41: =$C$2 -> 5152.95 | D41: =C41-E41 -> 3954.0137 | E41: =(F40+G40)*(1/12)*$A$3 -> 1198.9363 | F41: =F40-D41 -> 126839.04 | H41: =EOMONTH(H40,1) -> 45657
A42: =EOMONTH(A41,1) -> 45688 | B42: 33 | C42: =$C$2 -> 5152.95 | D42: =C42-E42 -> 3990.2588 | E42: =(F41+G41)*(1/12)*$A$3 -> 1162.6912 | F42: =F41-D42 -> 122848.78 | H42: =EOMONTH(H41,1) -> 45688 | I42: =D43-D42 -> 36.577372
A43: =EOMONTH(A42,1) -> 45716 | B43: 34 | C43: =$C$2 -> 5152.95 | D43: =C43-E43 -> 4026.8361 | E43: =(F42+G42)*(1/12)*$A$3 -> 1126.1139 | F43: =F42-D43 -> 118821.95 | H43: =EOMONTH(H42,1) -> 45716
A44: =EOMONTH(A43,1) -> 45747 | B44: 35 | C44: =$C$2 -> 5152.95 | D44: =C44-E44 -> 4063.7488 | E44: =(F43+G43)*(1/12)*$A$3 -> 1089.2012 | F44: =F43-D44 -> 114758.2 | H44: =EOMONTH(H43,1) -> 45747 | I44: =D44-D42 -> 73.490037
A45: =EOMONTH(A44,1) -> 45777 | B45: 36 | C45: =114758.2 -> 114758.2 | D45: =C45-E45 -> 114758.2 | E45: 0 | F45: =F44-D45 -> -0.0010577464 | H45: =EOMONTH(H44,1) -> 45777 | I45: PAYOFF
A46: =EOMONTH(A45,1) -> 45808 | B46: 37 | D46: =C46-E46 -> 9.6960084e-06 | E46: =(F45+G45)*(1/12)*$A$3 -> -9.6960084e-06 | F46: =F45-D46 -> -0.0010674424 | H46: =EOMONTH(H45,1) -> 45808
A47: =EOMONTH(A46,1) -> 45838 | B47: 38 | D47: =C47-E47 -> 9.7848885e-06 | E47: =(F46+G46)*(1/12)*$A$3 -> -9.7848885e-06 | F47: =F46-D47 -> -0.0010772273 | H47: =EOMONTH(H46,1) -> 45838
A48: =EOMONTH(A47,1) -> 45869 | B48: 39 | D48: =C48-E48 -> 9.8745833e-06 | E48: =(F47+G47)*(1/12)*$A$3 -> -9.8745833e-06 | F48: =F47-D48 -> -0.0010871018 | H48: =EOMONTH(H47,1) -> 45869
A49: =EOMONTH(A48,1) -> 45900 | B49: 40 | D49: =C49-E49 -> 9.9651003e-06 | E49: =(F48+G48)*(1/12)*$A$3 -> -9.9651003e-06 | F49: =F48-D49 -> -0.0010970669 | H49: =EOMONTH(H48,1) -> 45900
A50: =EOMONTH(A49,1) -> 45930 | B50: 41 | D50: =C50-E50 -> 1.0056447e-05 | E50: =(F49+G49)*(1/12)*$A$3 -> -1.0056447e-05 | F50: =F49-D50 -> -0.0011071234 | H50: =EOMONTH(H49,1) -> 45930
A51: =EOMONTH(A50,1) -> 45961 | B51: 42 | D51: =C51-E51 -> 1.0148631e-05 | E51: =(F50+G50)*(1/12)*$A$3 -> -1.0148631e-05 | F51: =F50-D51 -> -0.001117272 | H51: =EOMONTH(H50,1) -> 45961
A52: =EOMONTH(A51,1) -> 45991 | B52: 43 | D52: =C52-E52 -> 1.024166e-05 | E52: =(F51+G51)*(1/12)*$A$3 -> -1.024166e-05 | F52: =F51-D52 -> -0.0011275137 | H52: =EOMONTH(H51,1) -> 45991
A53: =EOMONTH(A52,1) -> 46022 | B53: 44 | D53: =C53-E53 -> 1.0335542e-05 | E53: =(F52+G52)*(1/12)*$A$3 -> -1.0335542e-05 | F53: =F52-D53 -> -0.0011378492 | H53: =EOMONTH(H52,1) -> 46022
A54: =EOMONTH(A53,1) -> 46053 | B54: 45 | D54: =C54-E54 -> 1.0430285e-05 | E54: =(F53+G53)*(1/12)*$A$3 -> -1.0430285e-05 | F54: =F53-D54 -> -0.0011482795 | H54: =EOMONTH(H53,1) -> 46053
A55: =EOMONTH(A54,1) -> 46081 | B55: 46 | D55: =C55-E55 -> 1.0525896e-05 | E55: =(F54+G54)*(1/12)*$A$3 -> -1.0525896e-05 | F55: =F54-D55 -> -0.0011588054 | H55: =EOMONTH(H54,1) -> 46081
A56: =EOMONTH(A55,1) -> 46112 | B56: 47 | D56: =C56-E56 -> 1.0622383e-05 | E56: =(F55+G55)*(1/12)*$A$3 -> -1.0622383e-05 | F56: =F55-D56 -> -0.0011694278 | H56: =EOMONTH(H55,1) -> 46112
A57: =EOMONTH(A56,1) -> 46142 | B57: 48 | D57: =C57-E57 -> 1.0719755e-05 | E57: =(F56+G56)*(1/12)*$A$3 -> -1.0719755e-05 | F57: =F56-D57 -> -0.0011801475 | H57: =EOMONTH(H56,1) -> 46142
... A70: =EOMONTH(A69,1) -> 46538 | B70: 61 | D70: =C70-E70 -> 1.2069868e-05 | E70: =(F69+G69)*(1/12)*$A$3 -> -1.2069868e-05 | F70: =F69-D70 -> -0.0013287827 | H70: =EOMONTH(H69,1) -> 46538

Sheet 22300 & 23300 - Axopar T-TOP28
A1: 126000
A2: 60 | B2: # of Periods | C2: Payment | D2: 2802.8
A3: 0.12 | B3: APR
A4: =A3/12 -> 0.01 | B4: Interest/Period
K5: Closing Date | L5: 45777 | N5: Current Portion | O5: =SUMIF(I:I,"<="&DATE(YEAR(L5),MONTH(L5)+12,DAY(L5)),E:E)-SUMIF(I:I,"<"&L5+1,E:E) -> 4.9079157e-05 | Q5: =P5-O5 -> -4.9079157e-05
N6: Long Term Portion | O6: =INDEX(C:G,MATCH(L5,I:I,0),5)-O5 -> -0.00043606231 | Q6: =P6-O6 -> 0.00043606231
N7: Total | O7: =O6+O5 -> -0.00038698316
C8: Beginning | D8: Payment | E8: Principal | F8: Interest | G8: Ending | H8: Accrued interest | I8: Date | N8: Check | O8: =INDEX(C:G,MATCH(L5,I:I,0),5)-O7 -> 0
A9: 45170 | B9: 0 | C9: =A1 -> 126000 | G9: =A1-D9 -> 126000 | I9: 45170
A10: 45199 | B10: 1 | C10: =G9 -> 126000 | D10: 2802.8 | E10: =D10-F10 -> 1542.8 | F10: =(G9+H9)*(1/12)*$A$3 -> 1260 | G10: =G9-E10 -> 124457.2 | I10: 45199
A11: =EOMONTH(A10,1) -> 45230 | B11: 2 | C11: =G10 -> 124457.2 | D11: =$D$2 -> 2802.8 | E11: =D11-F11 -> 1558.228 | F11: =(G10+H10)*(1/12)*$A$3 -> 1244.572 | G11: =G10-E11 -> 122898.97 | I11: =EOMONTH(I10,1) -> 45230
A12: =EOMONTH(A11,1) -> 45260 | B12: 3 | C12: =G11 -> 122898.97 | D12: =$D$2 -> 2802.8 | E12: =D12-F12 -> 1573.8103 | F12: =(G11+H11)*(1/12)*$A$3 -> 1228.9897 | G12: =G11-E12 -> 121325.16 | I12: =EOMONTH(I11,1) -> 45260
A13: =EOMONTH(A12,1) -> 45291 | B13: 4 | C13: =G12 -> 121325.16 | D13: =$D$2 -> 2802.8 | E13: =D13-F13 -> 1589.5484 | F13: =(G12+H12)*(1/12)*$A$3 -> 1213.2516 | G13: =G12-E13 -> 119735.61 | I13: =EOMONTH(I12,1) -> 45291
A14: =EOMONTH(A13,1) -> 45322 | B14: 5 | C14: =G13 -> 119735.61 | D14: =$D$2 -> 2802.8 | E14: =D14-F14 -> 1605.4439 | F14: =(G13+H13)*(1/12)*$A$3 -> 1197.3561 | G14: =G13-E14 -> 118130.17 | I14: =EOMONTH(I13,1) -> 45322
A15: =EOMONTH(A14,1) -> 45351 | B15: 6 | C15: =G14 -> 118130.17 | D15: =$D$2 -> 2802.8 | E15: =D15-F15 -> 1621.4983 | F15: =(G14+H14)*(1/12)*$A$3 -> 1181.3017 | G15: =G14-E15 -> 116508.67 | I15: =EOMONTH(I14,1) -> 45351
A16: =EOMONTH(A15,1) -> 45382 | B16: 7 | C16: =G15 -> 116508.67 | D16: =$D$2 -> 2802.8 | E16: =D16-F16 -> 1637.7133 | F16: =(G15+H15)*(1/12)*$A$3 -> 1165.0867 | G16: =G15-E16 -> 114870.96 | I16: =EOMONTH(I15,1) -> 45382
A17: =EOMONTH(A16,1) -> 45412 | B17: 8 | C17: =G16 -> 114870.96 | D17: =$D$2 -> 2802.8 | E17: =D17-F17 -> 1654.0904 | F17: =(G16+H16)*(1/12)*$A$3 -> 1148.7096 | G17: =G16-E17 -> 113216.87 | I17: =EOMONTH(I16,1) -> 45412
A18: =EOMONTH(A17,1) -> 45443 | B18: 9 | C18: =G17 -> 113216.87 | D18: =$D$2 -> 2802.8 | E18: =D18-F18 -> 1670.6313 | F18: =(G17+H17)*(1/12)*$A$3 -> 1132.1687 | G18: =G17-E18 -> 111546.24 | I18: =EOMONTH(I17,1) -> 45443
A19: =EOMONTH(A18,1) -> 45473 | B19: 10 | C19: =G18 -> 111546.24 | D19: =$D$2 -> 2802.8 | E19: =D19-F19 -> 1687.3376 | F19: =(G18+H18)*(1/12)*$A$3 -> 1115.4624 | G19: =G18-E19 -> 109858.9 | I19: =EOMONTH(I18,1) -> 45473
A20: =EOMONTH(A19,1) -> 45504 | B20: 11 | C20: =G19 -> 109858.9 | D20: =$D$2 -> 2802.8 | E20: =D20-F20 -> 1704.211 | F20: =(G19+H19)*(1/12)*$A$3 -> 1098.589 | G20: =G19-E20 -> 108154.69 | I20: =EOMONTH(I19,1) -> 45504
A21: =EOMONTH(A20,1) -> 45535 | B21: 12 | C21: =G20 -> 108154.69 | D21: =$D$2 -> 2802.8 | E21: =D21-F21 -> 1721.2531 | F21: =(G20+H20)*(1/12)*$A$3 -> 1081.5469 | G21: =G20-E21 -> 106433.43 | I21: =EOMONTH(I20,1) -> 45535
A22: =EOMONTH(A21,1) -> 45565 | B22: 13 | C22: =G21 -> 106433.43 | D22: =$D$2 -> 2802.8 | E22: =D22-F22 -> 1738.4657 | F22: =(G21+H21)*(1/12)*$A$3 -> 1064.3343 | G22: =G21-E22 -> 104694.97 | I22: =EOMONTH(I21,1) -> 45565
A23: =EOMONTH(A22,1) -> 45596 | B23: 14 | C23: =G22 -> 104694.97 | D23: =2853.8 -> 2853.8 | E23: =D23-F23 -> 1806.8503 | F23: =(G22+H22)*(1/12)*$A$3 -> 1046.9497 | G23: =G22-E23 -> 102888.12 | I23: =EOMONTH(I22,1) -> 45596
A24: =EOMONTH(A23,1) -> 45626 | B24: 15 | C24: =G23 -> 102888.12 | D24: =$D$2 -> 2802.8 | E24: =D24-F24 -> 1773.9188 | F24: =(G23+H23)*(1/12)*$A$3 -> 1028.8812 | G24: =G23-E24 -> 101114.2 | I24: =EOMONTH(I23,1) -> 45626
A25: =EOMONTH(A24,1) -> 45657 | B25: 16 | C25: =G24 -> 101114.2 | D25: =$D$2 -> 2802.8 | E25: =D25-F25 -> 1791.658 | F25: =(G24+H24)*(1/12)*$A$3 -> 1011.142 | G25: =G24-E25 -> 99322.542 | I25: =EOMONTH(I24,1) -> 45657
A26: =EOMONTH(A25,1) -> 45688 | B26: 17 | C26: =G25 -> 99322.542 | D26: =$D$2 -> 2802.8 | E26: =D26-F26 -> 1809.5746 | F26: =(G25+H25)*(1/12)*$A$3 -> 993.22542 | G26: =G25-E26 -> 97512.967 | I26: =EOMONTH(I25,1) -> 45688
A27: =EOMONTH(A26,1) -> 45716 | B27: 18 | C27: =G26 -> 97512.967 | D27: =$D$2 -> 2802.8 | E27: =D27-F27 -> 1827.6703 | F27: =(G26+H26)*(1/12)*$A$3 -> 975.12967 | G27: =G26-E27 -> 95685.297 | I27: =EOMONTH(I26,1) -> 45716 | K27: =E27-1823.59 -> 4.0803302
A28: =EOMONTH(A27,1) -> 45747 | B28: 19 | C28: =G27 -> 95685.297 | D28: =$D$2 -> 2802.8 | E28: =D28-F28 -> 1845.947 | F28: =(G27+H27)*(1/12)*$A$3 -> 956.85297 | G28: =G27-E28 -> 93839.35 | I28: =EOMONTH(I27,1) -> 45747 | K28: =E28-1823.59 -> 22.357034
A29: =EOMONTH(A28,1) -> 45777 | B29: 20 | C29: =G28 -> 93839.35 | D29: =47791.03+46048.32 -> 93839.35 | E29: =D29-F29 -> 93839.35 | F29: 0 | G29: =G28-E29 -> -0.00038698316 | I29: =EOMONTH(I28,1) -> 45777 | J29: PAYOFF | K29: =G28-D29 -> -0.00038698316
A30: =EOMONTH(A29,1) -> 45808 | B30: 21 | C30: =G29 -> -0.00038698316 | E30: =D30-F30 -> 3.8698316e-06 | F30: =(G29+H29)*(1/12)*$A$3 -> -3.8698316e-06 | G30: =G29-E30 -> -0.00039085299 | I30: =EOMONTH(I29,1) -> 45808
A31: =EOMONTH(A30,1) -> 45838 | B31: 22 | C31: =G30 -> -0.00039085299 | E31: =D31-F31 -> 3.9085299e-06 | F31: =(G30+H30)*(1/12)*$A$3 -> -3.9085299e-06 | G31: =G30-E31 -> -0.00039476152 | I31: =EOMONTH(I30,1) -> 45838
A32: =EOMONTH(A31,1) -> 45869 | B32: 23 | C32: =G31 -> -0.00039476152 | E32: =D32-F32 -> 3.9476152e-06 | F32: =(G31+H31)*(1/12)*$A$3 -> -3.9476152e-06 | G32: =G31-E32 -> -0.00039870913 | I32: =EOMONTH(I31,1) -> 45869
A33: =EOMONTH(A32,1) -> 45900 | B33: 24 | C33: =G32 -> -0.00039870913 | E33: =D33-F33 -> 3.9870913e-06 | F33: =(G32+H32)*(1/12)*$A$3 -> -3.9870913e-06 | G33: =G32-E33 -> -0.00040269622 | I33: =EOMONTH(I32,1) -> 45900
A34: =EOMONTH(A33,1) -> 45930 | B34: 25 | C34: =G33 -> -0.00040269622 | E34: =D34-F34 -> 4.0269622e-06 | F34: =(G33+H33)*(1/12)*$A$3 -> -4.0269622e-06 | G34: =G33-E34 -> -0.00040672319 | I34: =EOMONTH(I33,1) -> 45930
A35: =EOMONTH(A34,1) -> 45961 | B35: 26 | C35: =G34 -> -0.00040672319 | E35: =D35-F35 -> 4.0672319e-06 | F35: =(G34+H34)*(1/12)*$A$3 -> -4.0672319e-06 | G35: =G34-E35 -> -0.00041079042 | I35: =EOMONTH(I34,1) -> 45961
A36: =EOMONTH(A35,1) -> 45991 | B36: 27 | C36: =G35 -> -0.00041079042 | E36: =D36-F36 -> 4.1079042e-06 | F36: =(G35+H35)*(1/12)*$A$3 -> -4.1079042e-06 | G36: =G35-E36 -> -0.00041489832 | I36: =EOMONTH(I35,1) -> 45991
A37: =EOMONTH(A36,1) -> 46022 | B37: 28 | C37: =G36 -> -0.00041489832 | E37: =D37-F37 -> 4.1489832e-06 | F37: =(G36+H36)*(1/12)*$A$3 -> -4.1489832e-06 | G37: =G36-E37 -> -0.00041904731 | I37: =EOMONTH(I36,1) -> 46022
A38: =EOMONTH(A37,1) -> 46053 | B38: 29 | C38: =G37 -> -0.00041904731 | E38: =D38-F38 -> 4.1904731e-06 | F38: =(G37+H37)*(1/12)*$A$3 -> -4.1904731e-06 | G38: =G37-E38 -> -0.00042323778 | I38: =EOMONTH(I37,1) -> 46053
A39: =EOMONTH(A38,1) -> 46081 | B39: 30 | C39: =G38 -> -0.00042323778 | E39: =D39-F39 -> 4.2323778e-06 | F39: =(G38+H38)*(1/12)*$A$3 -> -4.2323778e-06 | G39: =G38-E39 -> -0.00042747016 | I39: =EOMONTH(I38,1) -> 46081
A40: =EOMONTH(A39,1) -> 46112 | B40: 31 | C40: =G39 -> -0.00042747016 | E40: =D40-F40 -> 4.2747016e-06 | F40: =(G39+H39)*(1/12)*$A$3 -> -4.2747016e-06 | G40: =G39-E40 -> -0.00043174486 | I40: =EOMONTH(I39,1) -> 46112
A41: =EOMONTH(A40,1) -> 46142 | B41: 32 | C41: =G40 -> -0.00043174486 | E41: =D41-F41 -> 4.3174486e-06 | F41: =(G40+H40)*(1/12)*$A$3 -> -4.3174486e-06 | G41: =G40-E41 -> -0.00043606231 | I41: =EOMONTH(I40,1) -> 46142
... A69: =EOMONTH(A68,1) -> 46996 | B69: 60 | C69: =G68 -> -0.00057046058 | E69: =D69-F69 -> 5.7046058e-06 | F69: =(G68+H68)*(1/12)*$A$3 -> -5.7046058e-06 | G69: =G68-E69 -> -0.00057616519 | I69: =EOMONTH(I68,1) -> 46996

Sheet 22100 & 23100 -Manitou (Stacey)
A1: 70000
A2: 48 | B2: # of Periods | C2: 1775.38
A3: 0.1 | B3: APR
A4: =A3/12 -> 0.0083333333 | B4: Interest/Period
J5: Closing Date | K5: 45808 | M5: Current Portion | N5: =SUMIF(H:H,"<="&DATE(YEAR(K5),MONTH(K5)+12,DAY(K5)),D:D)-SUMIF(H:H,"<"&K5+1,D:D) -> 0.00041830339
M6: Long Term Portion | N6: =INDEX(B:F,MATCH(K5,H:H,0),5)-N5 -> -0.0052525712
M7: Total | N7: =N6+N5 -> -0.0048342679
C8: Payment | D8: Principal | E8: Interest | F8: Ending | G8: Accrued interest | H8: Date | M8: Check | N8: =INDEX(B:F,MATCH(K5,H:H,0),5)-N7 -> 0
A9: 44440 | B9: 0 | F9: =A1-C9 -> 70000 | H9: 44440
A10: 44469 | B10: 1 | C10: =$C$2 -> 1775.38 | D10: =C10-E10 -> 1192.0467 | E10: =(F9+G9)*(1/12)*$A$3 -> 583.33333 | F10: =F9-D10 -> 68807.953 | H10: 44469
A11: =EOMONTH(A10,1) -> 44500 | B11: 2 | C11: =$C$2 -> 1775.38 | D11: =C11-E11 -> 1201.9804 | E11: =(F10+G10)*(1/12)*$A$3 -> 573.39961 | F11: =F10-D11 -> 67605.973 | H11: =EOMONTH(H10,1) -> 44500
A12: =EOMONTH(A11,1) -> 44530 | B12: 3 | C12: =$C$2 -> 1775.38 | D12: =C12-E12 -> 1211.9969 | E12: =(F11+G11)*(1/12)*$A$3 -> 563.38311 | F12: =F11-D12 -> 66393.976 | H12: =EOMONTH(H11,1) -> 44530
A13: =EOMONTH(A12,1) -> 44561 | B13: 4 | C13: =$C$2 -> 1775.38 | D13: =C13-E13 -> 1222.0969 | E13: =(F12+G12)*(1/12)*$A$3 -> 553.28313 | F13: =F12-D13 -> 65171.879 | H13: =EOMONTH(H12,1) -> 44561
A14: =EOMONTH(A13,1) -> 44592 | B14: 5 | C14: =$C$2 -> 1775.38 | D14: =C14-E14 -> 1232.281 | E14: =(F13+G13)*(1/12)*$A$3 -> 543.09899 | F14: =F13-D14 -> 63939.598 | H14: =EOMONTH(H13,1) -> 44592
A15: =EOMONTH(A14,1) -> 44620 | B15: 6 | C15: =$C$2 -> 1775.38 | D15: =C15-E15 -> 1242.55 | E15: =(F14+G14)*(1/12)*$A$3 -> 532.82998 | F15: =F14-D15 -> 62697.048 | H15: =EOMONTH(H14,1) -> 44620
A16: =EOMONTH(A15,1) -> 44651 | B16: 7 | C16: =$C$2 -> 1775.38 | D16: =C16-E16 -> 1252.9046 | E16: =(F15+G15)*(1/12)*$A$3 -> 522.4754 | F16: =F15-D16 -> 61444.144 | H16: =EOMONTH(H15,1) -> 44651
A17: =EOMONTH(A16,1) -> 44681 | B17: 8 | C17: =$C$2 -> 1775.38 | D17: =C17-E17 -> 1263.3455 | E17: =(F16+G16)*(1/12)*$A$3 -> 512.03453 | F17: =F16-D17 -> 60180.798 | H17: =EOMONTH(H16,1) -> 44681
A18: =EOMONTH(A17,1) -> 44712 | B18: 9 | C18: =$C$2 -> 1775.38 | D18: =C18-E18 -> 1273.8733 | E18: =(F17+G17)*(1/12)*$A$3 -> 501.50665 | F18: =F17-D18 -> 58906.925 | H18: =EOMONTH(H17,1) -> 44712
A19: =EOMONTH(A18,1) -> 44742 | B19: 10 | C19: 0 | D19: 0 | E19: =(F18+G18)*(1/12)*$A$3 -> 490.89104 | F19: =F18-D19 -> 58906.925 | G19: =E19 -> 490.89104 | H19: =EOMONTH(H18,1) -> 44742
A20: =EOMONTH(A19,1) -> 44773 | B20: 11 | C20: =$C$2 -> 1775.38 | D20: =C20-E19 -> 1284.489 | E20: =(F19+G19)*(1/12)*$A$3 -> 494.9818 | F20: =F19-D20 -> 57622.436 | G20: =E20 -> 494.9818 | H20: =EOMONTH(H19,1) -> 44773
A21: =EOMONTH(A20,1) -> 44804 | B21: 12 | C21: 3550.76 | D21: =C21-E20-E21 -> 2571.4664 | E21: =(F20+G20)*(1/12)*$A$3 -> 484.31181 | F21: =F20-D21 -> 55050.969 | G21: 0 | H21: =EOMONTH(H20,1) -> 44804
A22: =EOMONTH(A21,1) -> 44834 | B22: 13 | C22: =$C$2 -> 1775.38 | D22: =C22-E22 -> 1316.6219 | E22: =(F21+G21)*(1/12)*$A$3 -> 458.75808 | F22: =F21-D22 -> 53734.347 | G22: 0 | H22: =EOMONTH(H21,1) -> 44834
A23: =EOMONTH(A22,1) -> 44865 | B23: 14 | C23: 2225.38 | D23: =C23-E23 -> 1777.5938 | E23: =(F22+G22)*(1/12)*$A$3 -> 447.78623 | F23: =F22-D23 -> 51956.754 | G23: 0 | H23: =EOMONTH(H22,1) -> 44865
A24: =EOMONTH(A23,1) -> 44895 | B24: 15 | C24: =$C$2 -> 1775.38 | D24: =C24-E24 -> 1342.4071 | E24: =(F23+G23)*(1/12)*$A$3 -> 432.97295 | F24: =F23-D24 -> 50614.347 | H24: =EOMONTH(H23,1) -> 44895
A25: =EOMONTH(A24,1) -> 44926 | B25: 16 | C25: 0 | D25: 0 | E25: =(F24+G24)*(1/12)*$A$3 -> 421.78622 | F25: =F24-D25 -> 50614.347 | G25: =E25 -> 421.78622 | H25: =EOMONTH(H24,1) -> 44926
A26: =EOMONTH(A25,1) -> 44957 | B26: 17 | C26: =$C$2 -> 1775.38 | D26: =C26-E25 -> 1353.5938 | E26: =(F25+G25)*(1/12)*$A$3 -> 425.30111 | F26: =F25-D26 -> 49260.753 | G26: =E26 -> 425.30111 | H26: =EOMONTH(H25,1) -> 44957
A27: =EOMONTH(A26,1) -> 44985 | B27: 18 | C27: =$C$2 -> 1775.38 | D27: =C27-E26 -> 1350.0789 | E27: =(F26+G26)*(1/12)*$A$3 -> 414.05045 | F27: =F26-D27 -> 47910.674 | G27: =E27 -> 414.05045 | H27: =EOMONTH(H26,1) -> 44985
A28: =EOMONTH(A27,1) -> 45016 | B28: 19 | C28: =$C$2 -> 1775.38 | D28: =C28-E27 -> 1361.3296 | E28: =(F27+G27)*(1/12)*$A$3 -> 402.70604 | F28: =F27-D28 -> 46549.344 | G28: =E28 -> 402.70604 | H28: =EOMONTH(H27,1) -> 45016
A29: =EOMONTH(A28,1) -> 45046 | B29: 20 | C29: =$C$2 -> 1775.38 | D29: =C29-E28 -> 1372.674 | E29: =(F28+G28)*(1/12)*$A$3 -> 391.26709 | F29: =F28-D29 -> 45176.67 | G29: =E29 -> 391.26709 | H29: =EOMONTH(H28,1) -> 45046
A30: =EOMONTH(A29,1) -> 45077 | B30: 21 | C30: =$C$2 -> 1775.38 | D30: =C30-E29 -> 1384.1129 | E30: =(F29+G29)*(1/12)*$A$3 -> 379.73281 | F30: =F29-D30 -> 43792.558 | G30: =E30 -> 379.73281 | H30: =EOMONTH(H29,1) -> 45077
A31: =EOMONTH(A30,1) -> 45107 | B31: 22 | C31: =$C$2 -> 1775.38 | D31: =C31-E30 -> 1395.6472 | E31: =(F30+G30)*(1/12)*$A$3 -> 368.10242 | F31: =F30-D31 -> 42396.91 | G31: =E31 -> 368.10242 | H31: =EOMONTH(H30,1) -> 45107
A32: =EOMONTH(A31,1) -> 45138 | B32: 23 | C32: =$C$2 -> 1775.38 | D32: =C32-E31 -> 1407.2776 | E32: =(F31+G31)*(1/12)*$A$3 -> 356.37511 | F32: =F31-D32 -> 40989.633 | G32: =E32 -> 356.37511 | H32: =EOMONTH(H31,1) -> 45138
A33: =EOMONTH(A32,1) -> 45169 | B33: 24 | C33: =$C$2 -> 1775.38 | D33: =C33-E32 -> 1419.0049 | E33: =(F32+G32)*(1/12)*$A$3 -> 344.55007 | F33: =F32-D33 -> 39570.628 | G33: =E33 -> 344.55007 | H33: =EOMONTH(H32,1) -> 45169
A34: =EOMONTH(A33,1) -> 45199 | B34: 25 | C34: =$C$2 -> 1775.38 | D34: 0 | E34: =(F33+G33)*(1/12)*$A$3 -> 332.62648 | F34: =F33-D34 -> 39570.628 | G34: =G33+E34 -> 677.17655 | H34: =EOMONTH(H33,1) -> 45199
A35: =EOMONTH(A34,1) -> 45230 | B35: 26 | C35: =$C$2 -> 1775.38 | D35: =C35-E33 -> 1430.8299 | E35: =(F34+G34)*(1/12)*$A$3 -> 335.39837 | F35: =F34-D35 -> 38139.798 | G35: =E35+E34 -> 668.02485 | H35: =EOMONTH(H34,1) -> 45230
A36: =EOMONTH(A35,1) -> 45260 | B36: 27 | C36: =$C$2 -> 1775.38 | D36: 0 | E36: =(F35+G35)*(1/12)*$A$3 -> 323.39852 | F36: =F35-D36 -> 38139.798 | G36: =G35+E36 -> 991.42338 | H36: =EOMONTH(H35,1) -> 45260
A37: =EOMONTH(A36,1) -> 45291 | B37: 28 | C37: =$C$2 -> 1775.38 | D37: 0 | E37: =(F36+G36)*(1/12)*$A$3 -> 326.09351 | F37: =F36-D37 -> 38139.798 | G37: =G36+E37 -> 1317.5169 | H37: =EOMONTH(H36,1) -> 45291
A38: =EOMONTH(A37,1) -> 45322 | B38: 29 | C38: 5326.14 | D38: =C38-E36-E35-E34 -> 4334.7166 | E38: =(F37+G37)*(1/12)*$A$3 -> 328.81096 | F38: =F37-D38 -> 33805.081 | G38: =E37+E38 -> 654.90447 | H38: =EOMONTH(H37,1) -> 45322
A39: =EOMONTH(A38,1) -> 45351 | B39: 30 | C39: =$C$2 -> 1775.38 | D39: 0 | E39: =(F38+G38)*(1/12)*$A$3 -> 287.16655 | F39: =F38-D39 -> 33805.081 | G39: =G38+E39 -> 942.07102 | H39: =EOMONTH(H38,1) -> 45351
A40: =EOMONTH(A39,1) -> 45382 | B40: 31 | C40: =$C$2 -> 1775.38 | D40: 0 | E40: =(F39+G39)*(1/12)*$A$3 -> 289.5596 | F40: =F39-D40 -> 33805.081 | G40: =G39+E40 -> 1231.6306 | H40: =EOMONTH(H39,1) -> 45382
A41: =EOMONTH(A40,1) -> 45412 | B41: 32 | C41: 7101.52 | D41: =C41-E39-E38-E37-E40 -> 5869.8894 | E41: =(F40+G40)*(1/12)*$A$3 -> 291.9726 | F41: =F40-D41 -> 27935.192 | G41: =E41 -> 291.9726 | H41: =EOMONTH(H40,1) -> 45412
A42: =EOMONTH(A41,1) -> 45443 | B42: 33 | C42: =$C$2 -> 1775.38 | D42: 0 | E42: =(F41+G41)*(1/12)*$A$3 -> 235.22637 | F42: =F41-D42 -> 27935.192 | G42: =G41+E42 -> 527.19897 | H42: =EOMONTH(H41,1) -> 45443
A43: =EOMONTH(A42,1) -> 45473 | B43: 34 | C43: =$C$2 -> 1775.38 | D43: 0 | E43: =(F42+G42)*(1/12)*$A$3 -> 237.18659 | F43: =F42-D43 -> 27935.192 | G43: =G42+E43 -> 764.38556 | H43: =EOMONTH(H42,1) -> 45473
A44: =EOMONTH(A43,1) -> 45504 | B44: 35 | C44: =$C$2 -> 1775.38 | D44: 0 | E44: =(F43+G43)*(1/12)*$A$3 -> 239.16315 | F44: =F43-D44 -> 27935.192 | G44: =G43+E44 -> 1003.5487 | H44: =EOMONTH(H43,1) -> 45504
A45: =EOMONTH(A44,1) -> 45535 | B45: 36 | C45: 0 | D45: 0 | E45: =(F44+G44)*(1/12)*$A$3 -> 241.15617 | F45: =F44-D45 -> 27935.192 | G45: =G44+E45 -> 1244.7049 | H45: =EOMONTH(H44,1) -> 45535
A46: =EOMONTH(A45,1) -> 45565 | B46: 37 | C46: 3550.76 | D46: =C46-E41-E42 -> 3023.561 | E46: =(F45+G45)*(1/12)*$A$3 -> 243.16581 | F46: =F45-D46 -> 24911.631 | G46: =G45+E46-E41-E42 -> 960.67172 | H46: =EOMONTH(H45,1) -> 45565
A47: =EOMONTH(A46,1) -> 45596 | B47: 38 | C47: 0 | D47: 0 | E47: =(F46+G46)*(1/12)*$A$3 -> 215.60252 | F47: =F46-D47 -> 24911.631 | G47: =G46+E47 -> 1176.2742 | H47: =EOMONTH(H46,1) -> 45596
A48: =EOMONTH(A47,1) -> 45626 | B48: 39 | C48: 5326.14 | D48: =C48-E43-E44-E45 -> 4608.6341 | E48: =(F47+G47)*(1/12)*$A$3 -> 217.39921 | F48: =F47-D48 -> 20302.997 | G48: =G47+E48-E43-E44-E45 -> 676.16754 | H48: =EOMONTH(H47,1) -> 45626
A49: =EOMONTH(A48,1) -> 45657 | B49: 40 | C49: 0 | D49: 0 | E49: =(F48+G48)*(1/12)*$A$3 -> 174.82637 | F49: =F48-D49 -> 20302.997 | G49: =G48+E49 -> 850.99391 | H49: =EOMONTH(H48,1) -> 45657
A50: =EOMONTH(A49,1) -> 45688 | B50: 41 | C50: 0 | D50: 0 | E50: =(F49+G49)*(1/12)*$A$3 -> 176.28326 | F50: =F49-D50 -> 20302.997 | G50: =G49+E50 -> 1027.2772 | H50: =EOMONTH(H49,1) -> 45688
A51: =EOMONTH(A50,1) -> 45716 | B51: 42 | C51: 3552 | D51: =C51-E46-E47 -> 3093.2317 | E51: =(F50+G50)*(1/12)*$A$3 -> 177.75228 | F51: =F50-D51 -> 17209.765 | G51: =G50+E51-E46-E47 -> 746.26112 | H51: =EOMONTH(H50,1) -> 45716
A52: =EOMONTH(A51,1) -> 45747 | B52: 43 | D52: 0 | E52: =(F51+G51)*(1/12)*$A$3 -> 149.63355 | F52: =F51-D52 -> 17209.765 | G52: =G51+E52 -> 895.89467 | H52: =EOMONTH(H51,1) -> 45747
A53: =EOMONTH(A52,1) -> 45777 | B53: 44 | C53: 0 | D53: 0 | E53: =(F52+G52)*(1/12)*$A$3 -> 150.8805 | F53: =F52-D53 -> 17209.765 | G53: =G52+E53-0.01 -> 1046.7652 | H53: =EOMONTH(H52,1) -> 45777
A54: =EOMONTH(A53,1) -> 45808 | B54: 45 | C54: 18256.55 | D54: 17209.77 | E54: =(F53+G53)*(1/12)*$A$3 -> 152.13775 | F54: =F53-D54 -> -0.0048342679 | G54: 0 | H54: =EOMONTH(H53,1) -> 45808 | I54: PAYOFF
A55: =EOMONTH(A54,1) -> 45838 | B55: 46 | C55: 0 | D55: =C55-E55 -> 4.0285565e-05 | E55: =(F54+G54)*(1/12)*$A$3 -> -4.0285565e-05 | F55: =F54-D55 -> -0.0048745534 | H55: =EOMONTH(H54,1) -> 45838
A56: =EOMONTH(A55,1) -> 45869 | B56: 47 | C56: 0 | D56: =C56-E56 -> 4.0621279e-05 | E56: =(F55+G55)*(1/12)*$A$3 -> -4.0621279e-05 | F56: =F55-D56 -> -0.0049151747 | H56: =EOMONTH(H55,1) -> 45869
A57: =EOMONTH(A56,1) -> 45900 | B57: 48 | C57: 0 | D57: =C57-E57 -> 4.0959789e-05 | E57: =(F56+G56)*(1/12)*$A$3 -> -4.0959789e-05 | F57: =F56-D57 -> -0.0049561345 | H57: =EOMONTH(H56,1) -> 45900
A58: =EOMONTH(A57,1) -> 45930 | B58: 49 | C58: 0 | D58: =C58-E58 -> 4.1301121e-05 | E58: =(F57+G57)*(1/12)*$A$3 -> -4.1301121e-05 | F58: =F57-D58 -> -0.0049974356 | H58: =EOMONTH(H57,1) -> 45930
A59: =EOMONTH(A58,1) -> 45961 | B59: 50 | C59: 0 | D59: =C59-E59 -> 4.1645297e-05 | E59: =(F58+G58)*(1/12)*$A$3 -> -4.1645297e-05 | F59: =F58-D59 -> -0.0050390809 | H59: =EOMONTH(H58,1) -> 45961
A60: =EOMONTH(A59,1) -> 45991 | B60: 51 | C60: 0 | D60: =C60-E60 -> 4.1992341e-05 | E60: =(F59+G59)*(1/12)*$A$3 -> -4.1992341e-05 | F60: =F59-D60 -> -0.0050810732 | H60: =EOMONTH(H59,1) -> 45991
A61: =EOMONTH(A60,1) -> 46022 | B61: 52 | C61: 0 | D61: =C61-E61 -> 4.2342277e-05 | E61: =(F60+G60)*(1/12)*$A$3 -> -4.2342277e-05 | F61: =F60-D61 -> -0.0051234155 | H61: =EOMONTH(H60,1) -> 46022
A62: =EOMONTH(A61,1) -> 46053 | B62: 53 | C62: 0 | D62: =C62-E62 -> 4.2695129e-05 | E62: =(F61+G61)*(1/12)*$A$3 -> -4.2695129e-05 | F62: =F61-D62 -> -0.0051661107 | H62: =EOMONTH(H61,1) -> 46053
A63: =EOMONTH(A62,1) -> 46081 | B63: 54 | C63: 0 | D63: =C63-E63 -> 4.3050922e-05 | E63: =(F62+G62)*(1/12)*$A$3 -> -4.3050922e-05 | F63: =F62-D63 -> -0.0052091616 | H63: =EOMONTH(H62,1) -> 46081
A64: =EOMONTH(A63,1) -> 46112 | B64: 55 | C64: 0 | D64: =C64-E64 -> 4.340968e-05 | E64: =(F63+G63)*(1/12)*$A$3 -> -4.340968e-05 | F64: =F63-D64 -> -0.0052525713 | H64: =EOMONTH(H63,1) -> 46112

Sheet 22150 & 23150 - Scott Tiernan
A1: 185000
A2: 36 | B2: # of Periods | C2: 5461.92
A3: 0.04 | B3: APR
A4: =A3/12 -> 0.0033333333 | B4: Interest/Period
J5: Closing Date | K5: 45930 | M5: Current Portion | N5: =SUMIF(H:H,"<="&DATE(YEAR(K5),MONTH(K5)+12,DAY(K5)),D:D)-SUMIF(H:H,"<"&K5+1,D:D) -> 0
M6: Long Term Portion | N6: =INDEX(B:F,MATCH(K5,H:H,0),5)-N5 -> 5990.5163
M7: Total | N7: =N6+N5 -> 5990.5163
C8: Payment | D8: Principal | E8: Interest | F8: Ending | G8: Accrued interest | H8: Date | M8: Check | N8: =INDEX(B:F,MATCH(K5,H:H,0),5)-N7 -> 0
A9: 44440 | B9: 0 | F9: =A1-C9 -> 185000 | H9: 44440
A10: 44469 | B10: 1 | C10: =$C$2 -> 5461.92 | D10: =C10-E10 -> 4845.2533 | E10: =(F9+G9)*(1/12)*$A$3 -> 616.66667 | F10: =F9-D10 -> 180154.75 | H10: 44469
A11: =EOMONTH(A10,1) -> 44500 | B11: 2 | C11: =$C$2 -> 5461.92 | D11: =C11-E11 -> 4861.4042 | E11: =(F10+G10)*(1/12)*$A$3 -> 600.51582 | F11: =F10-D11 -> 175293.34 | H11: =EOMONTH(H10,1) -> 44500
A12: =EOMONTH(A11,1) -> 44530 | B12: 3 | C12: =$C$2 -> 5461.92 | D12: =C12-E12 -> 4877.6089 | E12: =(F11+G11)*(1/12)*$A$3 -> 584.31114 | F12: =F11-D12 -> 170415.73 | H12: =EOMONTH(H11,1) -> 44530
A13: =EOMONTH(A12,1) -> 44561 | B13: 4 | C13: =$C$2 -> 5461.92 | D13: =C13-E13 -> 4893.8676 | E13: =(F12+G12)*(1/12)*$A$3 -> 568.05245 | F13: =F12-D13 -> 165521.87 | H13: =EOMONTH(H12,1) -> 44561
A14: =EOMONTH(A13,1) -> 44592 | B14: 5 | C14: =$C$2 -> 5461.92 | D14: =C14-E14 -> 4910.1804 | E14: =(F13+G13)*(1/12)*$A$3 -> 551.73955 | F14: =F13-D14 -> 160611.69 | H14: =EOMONTH(H13,1) -> 44592
A15: =EOMONTH(A14,1) -> 44620 | B15: 6 | C15: =$C$2 -> 5461.92 | D15: =C15-E15 -> 4926.5477 | E15: =(F14+G14)*(1/12)*$A$3 -> 535.37229 | F15: =F14-D15 -> 155685.14 | H15: =EOMONTH(H14,1) -> 44620
A16: =EOMONTH(A15,1) -> 44651 | B16: 7 | C16: =$C$2 -> 5461.92 | D16: =C16-E16 -> 4942.9695 | E16: =(F15+G15)*(1/12)*$A$3 -> 518.95046 | F16: =F15-D16 -> 150742.17 | H16: =EOMONTH(H15,1) -> 44651
A17: =EOMONTH(A16,1) -> 44681 | B17: 8 | C17: =$C$2 -> 5461.92 | D17: =C17-E17 -> 4959.4461 | E17: =(F16+G16)*(1/12)*$A$3 -> 502.47389 | F17: =F16-D17 -> 145782.72 | H17: =EOMONTH(H16,1) -> 44681
A18: =EOMONTH(A17,1) -> 44712 | B18: 9 | C18: =$C$2 -> 5461.92 | D18: =C18-E18 -> 4975.9776 | E18: =(F17+G17)*(1/12)*$A$3 -> 485.94241 | F18: =F17-D18 -> 140806.74 | H18: =EOMONTH(H17,1) -> 44712
A19: =EOMONTH(A18,1) -> 44742 | B19: 10 | C19: =$C$2 -> 5461.92 | D19: =C19-E19 -> 4992.5642 | E19: =(F18+G18)*(1/12)*$A$3 -> 469.35582 | F19: =F18-D19 -> 135814.18 | H19: =EOMONTH(H18,1) -> 44742
A20: =EOMONTH(A19,1) -> 44773 | B20: 11 | C20: 0 | D20: 0 | E20: =(F19+G19)*(1/12)*$A$3 -> 452.71393 | F20: =F19-D20 -> 135814.18 | G20: =E20 -> 452.71393 | H20: =EOMONTH(H19,1) -> 44773
A21: =EOMONTH(A20,1) -> 44804 | B21: 12 | C21: =$C$2 -> 5461.92 | D21: =C21-E20 -> 5009.2061 | E21: =(F20+G20)*(1/12)*$A$3 -> 454.22298 | F21: =F20-D21 -> 130804.97 | G21: =E21 -> 454.22298 | H21: =EOMONTH(H20,1) -> 44804
A22: =EOMONTH(A21,1) -> 44834 | B22: 13 | C22: =$C$2 -> 5461.92 | D22: =C22-E21 -> 5007.697 | E22: =(F21+G21)*(1/12)*$A$3 -> 437.53066 | F22: =F21-D22 -> 125797.28 | G22: =E22 -> 437.53066 | H22: =EOMONTH(H21,1) -> 44834
A23: =EOMONTH(A22,1) -> 44865 | B23: 14 | C23: =$C$2 -> 5461.92 | D23: =C23-E22 -> 5024.3893 | E23: =(F22+G22)*(1/12)*$A$3 -> 420.78269 | F23: =F22-D23 -> 120772.89 | G23: =E23 -> 420.78269 | H23: =EOMONTH(H22,1) -> 44865
A24: =EOMONTH(A23,1) -> 44895 | B24: 15 | C24: =$C$2 -> 5461.92 | D24: =C24-E23 -> 5041.1373 | E24: =(F23+G23)*(1/12)*$A$3 -> 403.9789 | F24: =F23-D24 -> 115731.75 | G24: =E24 -> 403.9789 | H24: =EOMONTH(H23,1) -> 44895
A25: =EOMONTH(A24,1) -> 44926 | B25: 16 | C25: =$C$2 -> 5461.92 | D25: =C25-E24 -> 5057.9411 | E25: =(F24+G24)*(1/12)*$A$3 -> 387.1191 | F25: =F24-D25 -> 110673.81 | G25: =E25 -> 387.1191 | H25: =EOMONTH(H24,1) -> 44926
A26: =EOMONTH(A25,1) -> 44957 | B26: 17 | C26: =$C$2 -> 5461.92 | D26: =C26-E25 -> 5074.8009 | E26: =(F25+G25)*(1/12)*$A$3 -> 370.2031 | F26: =F25-D26 -> 105599.01 | G26: =E26 -> 370.2031 | H26: =EOMONTH(H25,1) -> 44957
A27: =EOMONTH(A26,1) -> 44985 | B27: 18 | C27: =$C$2 -> 5461.92 | D27: =C27-E26 -> 5091.7169 | E27: =(F26+G26)*(1/12)*$A$3 -> 353.23071 | F27: =F26-D27 -> 100507.29 | G27: =E27 -> 353.23071 | H27: =EOMONTH(H26,1) -> 44985
A28: =EOMONTH(A27,1) -> 45016 | B28: 19 | C28: =$C$2 -> 5461.92 | D28: =C28-E27 -> 5108.6893 | E28: =(F27+G27)*(1/12)*$A$3 -> 336.20174 | F28: =F27-D28 -> 95398.603 | G28: =E28 -> 336.20174 | H28: =EOMONTH(H27,1) -> 45016
A29: =EOMONTH(A28,1) -> 45046 | B29: 20 | C29: =$C$2 -> 5461.92 | D29: =C29-E28 -> 5125.7183 | E29: =(F28+G28)*(1/12)*$A$3 -> 319.11601 | F29: =F28-D29 -> 90272.884 | G29: =E29 -> 319.11601 | H29: =EOMONTH(H28,1) -> 45046
A30: =EOMONTH(A29,1) -> 45077 | B30: 21 | C30: =$C$2 -> 5461.92 | D30: =C30-E29 -> 5142.804 | E30: =(F29+G29)*(1/12)*$A$3 -> 301.97333 | F30: =F29-D30 -> 85130.08 | G30: =E30 -> 301.97333 | H30: =EOMONTH(H29,1) -> 45077
A31: =EOMONTH(A30,1) -> 45107 | B31: 22 | C31: =$C$2 -> 5461.92 | D31: =C31-E30 -> 5159.9467 | E31: =(F30+G30)*(1/12)*$A$3 -> 284.77351 | F31: =F30-D31 -> 79970.134 | G31: =E31 -> 284.77351 | H31: =EOMONTH(H30,1) -> 45107
A32: =EOMONTH(A31,1) -> 45138 | B32: 23 | C32: =$C$2 -> 5461.92 | D32: =C32-E31 -> 5177.1465 | E32: =(F31+G31)*(1/12)*$A$3 -> 267.51636 | F32: =F31-D32 -> 74792.987 | G32: =E32 -> 267.51636 | H32: =EOMONTH(H31,1) -> 45138
... A37: =EOMONTH(A36,1) -> 45291 | B37: 28 | C37: =$C$2 -> 5461.92 | D37: =C37-E36 -> 5264.0094 | E37: =(F36+G36)*(1/12)*$A$3 -> 180.36388 | F37: =F36-D37 -> 48647.244 | G37: =E37 -> 180.36388 | H37: =EOMONTH(H36,1) -> 45291
A38: =EOMONTH(A37,1) -> 45322 | B38: 29 | C38: 0 | D38: 0 | E38: =(F37+G37)*(1/12)*$A$3 -> 162.75869 | F38: =F37-D38 -> 48647.244 | G38: =G37+E38 -> 343.12257 | H38: =EOMONTH(H37,1) -> 45322
A39: =EOMONTH(A38,1) -> 45351 | B39: 30 | C39: =$C$2 -> 5461.92 | D39: =C39-E37 -> 5281.5561 | E39: =(F38+G38)*(1/12)*$A$3 -> 163.30122 | F39: =F38-D39 -> 43365.688 | G39: =E39+E38 -> 326.05992 | H39: =EOMONTH(H38,1) -> 45351
A40: =EOMONTH(A39,1) -> 45382 | B40: 31 | C40: =$C$2 -> 5461.92 | D40: =C40-E38 -> 5299.1613 | E40: =(F39+G39)*(1/12)*$A$3 -> 145.63916 | F40: =F39-D40 -> 38066.527 | G40: =E40+E39 -> 308.94038 | H40: =EOMONTH(H39,1) -> 45382
A41: =EOMONTH(A40,1) -> 45412 | B41: 32 | C41: =$C$2 -> 5461.92 | D41: =C41-E39 -> 5298.6188 | E41: =(F40+G40)*(1/12)*$A$3 -> 127.91822 | F41: =F40-D41 -> 32767.908 | G41: =E41+E40 -> 273.55738 | H41: =EOMONTH(H40,1) -> 45412
A42: =EOMONTH(A41,1) -> 45443 | B42: 33 | C42: =$C$2 -> 5461.92 | D42: =C42-E40 -> 5316.2808 | E42: =(F41+G41)*(1/12)*$A$3 -> 110.13822 | F42: =F41-D42 -> 27451.627 | G42: =G41+E42-E40 -> 238.05644 | H42: =EOMONTH(H41,1) -> 45443
A43: =EOMONTH(A42,1) -> 45473 | B43: 34 | C43: 10923.82 | D43: =C43-E42-E41 -> 10685.764 | E43: =(F42+G42)*(1/12)*$A$3 -> 92.298945 | F43: =F42-D43 -> 16765.863 | G43: =E43 -> 92.298945 | H43: =EOMONTH(H42,1) -> 45473
A44: =EOMONTH(A43,1) -> 45504 | B44: 35 | C44: =$C$2 -> 5461.92 | D44: =C44-E43 -> 5369.6211 | E44: =(F43+G43)*(1/12)*$A$3 -> 56.193875 | F44: =F43-D44 -> 11396.242 | G44: =E44 -> 56.193875 | H44: =EOMONTH(H43,1) -> 45504
A45: =EOMONTH(A44,1) -> 45535 | B45: 36 | C45: =$C$2 -> 5461.92 | D45: =C45-E44 -> 5405.7261 | E45: =(F44+G44)*(1/12)*$A$3 -> 38.174788 | F45: =F44-D45 -> 5990.5163 | G45: =E45 -> 38.174788 | H45: =EOMONTH(H44,1) -> 45535
A46: =EOMONTH(A45,1) -> 45565 | B46: 37 | C46: 0 | E46: =(F45+G45)*(1/12)*$A$3 -> 20.095637 | F46: =F45-D46 -> 5990.5163 | G46: =G45+E46 -> 58.270424 | H46: =EOMONTH(H45,1) -> 45565
A47: =EOMONTH(A46,1) -> 45596 | B47: 38 | C47: 0 | E47: =(F46+G46)*(1/12)*$A$3 -> 20.162622 | F47: =F46-D47 -> 5990.5163 | G47: =G46+E47 -> 78.433047 | H47: =EOMONTH(H46,1) -> 45596
A48: =EOMONTH(A47,1) -> 45626 | B48: 39 | C48: 0 | D48: 0 | E48: =(F47+G47)*(1/12)*$A$3 -> 20.229831 | F48: =F47-D48 -> 5990.5163 | G48: =G47+E48 -> 98.662878 | H48: =EOMONTH(H47,1) -> 45626
A49: =EOMONTH(A48,1) -> 45657 | B49: 40 | C49: 0 | D49: 0 | E49: =(F48+G48)*(1/12)*$A$3 -> 20.297264 | F49: =F48-D49 -> 5990.5163 | G49: =G48+E49 -> 118.96014 | H49: =EOMONTH(H48,1) -> 45657
A50: =EOMONTH(A49,1) -> 45688 | B50: 41 | C50: 0 | D50: 0 | E50: =(F49+G49)*(1/12)*$A$3 -> 20.364921 | F50: =F49-D50 -> 5990.5163 | G50: =G49+E50 -> 139.32506 | H50: =EOMONTH(H49,1) -> 45688
A51: =EOMONTH(A50,1) -> 45716 | B51: 42 | C51: 0 | D51: 0 | E51: =(F50+G50)*(1/12)*$A$3 -> 20.432804 | F51: =F50-D51 -> 5990.5163 | G51: =G50+E51 -> 159.75787 | H51: =EOMONTH(H50,1) -> 45716
A52: =EOMONTH(A51,1) -> 45747 | B52: 43 | C52: 0 | D52: 0 | E52: =(F51+G51)*(1/12)*$A$3 -> 20.500914 | F52: =F51-D52 -> 5990.5163 | G52: =G51+E52 -> 180.25878 | H52: =EOMONTH(H51,1) -> 45747
A53: =EOMONTH(A52,1) -> 45777 | B53: 44 | C53: 0 | D53: 0 | E53: =(F52+G52)*(1/12)*$A$3 -> 20.56925 | F53: =F52-D53 -> 5990.5163 | G53: =G52+E53 -> 200.82803 | H53: =EOMONTH(H52,1) -> 45777
A54: =EOMONTH(A53,1) -> 45808 | B54: 45 | C54: 0 | D54: 0 | E54: =(F53+G53)*(1/12)*$A$3 -> 20.637814 | F54: =F53-D54 -> 5990.5163 | G54: =G53+E54 -> 221.46585 | H54: =EOMONTH(H53,1) -> 45808
A55: =EOMONTH(A54,1) -> 45838 | B55: 46 | C55: 0 | D55: 0 | E55: =(F54+G54)*(1/12)*$A$3 -> 20.706607 | F55: =F54-D55 -> 5990.5163 | G55: =G54+E55 -> 242.17245 | H55: =EOMONTH(H54,1) -> 45838
A56: =EOMONTH(A55,1) -> 45869 | B56: 47 | C56: 0 | D56: 0 | E56: =(F55+G55)*(1/12)*$A$3 -> 20.775629 | F56: =F55-D56 -> 5990.5163 | G56: =G55+E56 -> 262.94808 | H56: =EOMONTH(H55,1) -> 45869
A57: =EOMONTH(A56,1) -> 45900 | B57: 48 | C57: 0 | D57: 0 | E57: =(F56+G56)*(1/12)*$A$3 -> 20.844881 | F57: =F56-D57 -> 5990.5163 | G57: =G56+E57 -> 283.79296 | H57: =EOMONTH(H56,1) -> 45900
A58: =EOMONTH(A57,1) -> 45930 | B58: 49 | C58: 0 | D58: 0 | E58: =(F57+G57)*(1/12)*$A$3 -> 20.914364 | F58: =F57-D58 -> 5990.5163 | G58: =G57+E58 -> 304.70733 | H58: =EOMONTH(H57,1) -> 45930
A59: =EOMONTH(A58,1) -> 45961 | B59: 50 | C59: 0 | D59: 0 | E59: =(F58+G58)*(1/12)*$A$3 -> 20.984079 | F59: =F58-D59 -> 5990.5163 | G59: =G58+E59 -> 325.69141 | H59: =EOMONTH(H58,1) -> 45961
... A61: =EOMONTH(A60,1) -> 46022 | B61: 52 | C61: 0 | D61: 0 | E61: =(F60+G60)*(1/12)*$A$3 -> 21.124206 | F61: =F60-D61 -> 5990.5163 | G61: =G60+E61 -> 367.86964 | H61: =EOMONTH(H60,1) -> 46022
A62: =EOMONTH(A61,1) -> 46053 | B62: 53 | C62: 0 | D62: 0 | E62: =(F61+G61)*(1/12)*$A$3 -> 21.19462 | F62: =F61-D62 -> 5990.5163 | H62: =EOMONTH(H61,1) -> 46053
A63: =EOMONTH(A62,1) -> 46081 | B63: 54 | C63: 0 | D63: 0 | E63: =(F62+G62)*(1/12)*$A$3 -> 19.968388 | F63: =F62-D63 -> 5990.5163 | H63: =EOMONTH(H62,1) -> 46081
A64: =EOMONTH(A63,1) -> 46112 | B64: 55 | C64: 0 | D64: 0 | E64: =(F63+G63)*(1/12)*$A$3 -> 19.968388 | F64: =F63-D64 -> 5990.5163 | H64: =EOMONTH(H63,1) -> 46112
A65: =EOMONTH(A64,1) -> 46142 | B65: 56 | C65: 0 | D65: 0 | E65: =(F64+G64)*(1/12)*$A$3 -> 19.968388 | F65: =F64-D65 -> 5990.5163 | H65: =EOMONTH(H64,1) -> 46142
A66: =EOMONTH(A65,1) -> 46173 | B66: 57 | C66: 0 | D66: 0 | E66: =(F65+G65)*(1/12)*$A$3 -> 19.968388 | F66: =F65-D66 -> 5990.5163 | H66: =EOMONTH(H65,1) -> 46173
A67: =EOMONTH(A66,1) -> 46203 | B67: 58 | C67: 0 | D67: 0 | E67: =(F66+G66)*(1/12)*$A$3 -> 19.968388 | F67: =F66-D67 -> 5990.5163 | H67: =EOMONTH(H66,1) -> 46203
A68: =EOMONTH(A67,1) -> 46234 | B68: 59 | C68: 0 | D68: 0 | E68: =(F67+G67)*(1/12)*$A$3 -> 19.968388 | F68: =F67-D68 -> 5990.5163 | H68: =EOMONTH(H67,1) -> 46234
A69: =EOMONTH(A68,1) -> 46265 | B69: 60 | C69: 0 | D69: 0 | E69: =(F68+G68)*(1/12)*$A$3 -> 19.968388 | F69: =F68-D69 -> 5990.5163 | H69: =EOMONTH(H68,1) -> 46265

Sheet 22250 & 23250 - NX 340
A1: 272754.5
A2: 60 | B2: # of Periods | C2: 5661.93
A3: 0.09 | B3: APR
A4: =A3/12 -> 0.0075 | B4: Interest/Period
J5: Closing Date | K5: 45777 | M5: Current Portion | N5: =SUMIF(H:H,"<="&DATE(YEAR(K5),MONTH(K5)+12,DAY(K5)),D:D)-SUMIF(H:H,"<"&K5+1,D:D) -> -0.00020420778 | P5: =N5-O5 -> -0.00020420778
M6: Long Term Portion | N6: =INDEX(B:F,MATCH(K5,H:H,0),5)-N5 -> 0.0023811026 | P6: =N6-O6 -> 0.0023811026
M7: Total | N7: =N6+N5 -> 0.0021768948
C8: Payment | D8: Principal | E8: Interest | F8: Ending | G8: Accrued interest | H8: Date | M8: Check | N8: =INDEX(B:F,MATCH(K5,H:H,0),5)-N7 -> 0
A9: 45139 | B9: 0 | F9: =A1-C9 -> 272754.5 | H9: 45139
A10: 45169 | B10: 1 | C10: 10687.86 | D10: =C10-E10 -> 8642.2013 | E10: =(F9+G9)*(1/12)*$A$3 -> 2045.6587 | F10: =F9-D10 -> 264112.3 | H10: 45169
A11: =EOMONTH(A10,1) -> 45199 | B11: 2 | C11: =$C$2 -> 5661.93 | D11: =C11-E11 -> 3681.0878 | E11: =(F10+G10)*(1/12)*$A$3 -> 1980.8422 | F11: =F10-D11 -> 260431.21 | H11: =EOMONTH(H10,1) -> 45199
A12: =EOMONTH(A11,1) -> 45230 | B12: 3 | C12: =$C$2 -> 5661.93 | D12: =C12-E12 -> 3708.6959 | E12: =(F11+G11)*(1/12)*$A$3 -> 1953.2341 | F12: =F11-D12 -> 256722.52 | H12: =EOMONTH(H11,1) -> 45230
A13: =EOMONTH(A12,1) -> 45260 | B13: 4 | C13: =$C$2 -> 5661.93 | D13: =C13-E13 -> 3736.5111 | E13: =(F12+G12)*(1/12)*$A$3 -> 1925.4189 | F13: =F12-D13 -> 252986 | H13: =EOMONTH(H12,1) -> 45260
A14: =EOMONTH(A13,1) -> 45291 | B14: 5 | C14: =$C$2 -> 5661.93 | D14: =C14-E14 -> 3764.535 | E14: =(F13+G13)*(1/12)*$A$3 -> 1897.395 | F14: =F13-D14 -> 249221.47 | H14: =EOMONTH(H13,1) -> 45291
A15: =EOMONTH(A14,1) -> 45322 | B15: 6 | C15: =$C$2 -> 5661.93 | D15: =C15-E15 -> 3792.769 | E15: =(F14+G14)*(1/12)*$A$3 -> 1869.161 | F15: =F14-D15 -> 245428.7 | H15: =EOMONTH(H14,1) -> 45322
A16: =EOMONTH(A15,1) -> 45351 | B16: 7 | C16: =$C$2 -> 5661.93 | D16: =C16-E16 -> 3821.2148 | E16: =(F15+G15)*(1/12)*$A$3 -> 1840.7152 | F16: =F15-D16 -> 241607.49 | H16: =EOMONTH(H15,1) -> 45351
A17: =EOMONTH(A16,1) -> 45382 | B17: 8 | C17: =$C$2 -> 5661.93 | D17: =C17-E17 -> 3849.8739 | E17: =(F16+G16)*(1/12)*$A$3 -> 1812.0561 | F17: =F16-D17 -> 237757.61 | H17: =EOMONTH(H16,1) -> 45382
A18: =EOMONTH(A17,1) -> 45412 | B18: 9 | C18: =$C$2 -> 5661.93 | D18: =C18-E18 -> 3878.7479 | E18: =(F17+G17)*(1/12)*$A$3 -> 1783.1821 | F18: =F17-D18 -> 233878.86 | H18: =EOMONTH(H17,1) -> 45412
A19: =EOMONTH(A18,1) -> 45443 | B19: 10 | C19: =$C$2 -> 5661.93 | D19: =C19-E19 -> 3907.8385 | E19: =(F18+G18)*(1/12)*$A$3 -> 1754.0915 | F19: =F18-D19 -> 229971.02 | H19: =EOMONTH(H18,1) -> 45443
A20: =EOMONTH(A19,1) -> 45473 | B20: 11 | C20: =$C$2 -> 5661.93 | D20: =C20-E20 -> 3937.1473 | E20: =(F19+G19)*(1/12)*$A$3 -> 1724.7827 | F20: =F19-D20 -> 226033.88 | H20: =EOMONTH(H19,1) -> 45473
A21: =EOMONTH(A20,1) -> 45504 | B21: 12 | C21: =$C$2 -> 5661.93 | D21: =C21-E21 -> 3966.6759 | E21: =(F20+G20)*(1/12)*$A$3 -> 1695.2541 | F21: =F20-D21 -> 222067.2 | H21: =EOMONTH(H20,1) -> 45504
A22: =EOMONTH(A21,1) -> 45535 | B22: 13 | C22: =$C$2 -> 5661.93 | D22: =C22-E22 -> 3996.426 | E22: =(F21+G21)*(1/12)*$A$3 -> 1665.504 | F22: =F21-D22 -> 218070.78 | H22: =EOMONTH(H21,1) -> 45535
... A26: =EOMONTH(A25,1) -> 45657 | B26: 17 | C26: =$C$2 -> 5661.93 | D26: =C26-E26 -> 4117.6743 | E26: =(F25+G25)*(1/12)*$A$3 -> 1544.2557 | F26: =F25-D26 -> 201783.08 | H26: =EOMONTH(H25,1) -> 45657
A27: =EOMONTH(A26,1) -> 45688 | B27: 18 | C27: 6228.12 | D27: =C27-E27 -> 4714.7469 | E27: =(F26+G26)*(1/12)*$A$3 -> 1513.3731 | F27: =F26-D27 -> 197068.34 | H27: =EOMONTH(H26,1) -> 45688
A28: =EOMONTH(A27,1) -> 45716 | B28: 19 | C28: =$C$2 -> 5661.93 | D28: =C28-E28 -> 4183.9175 | E28: =(F27+G27)*(1/12)*$A$3 -> 1478.0125 | F28: =F27-D28 -> 192884.42 | H28: =EOMONTH(H27,1) -> 45716
A29: =EOMONTH(A28,1) -> 45747 | B29: 20 | C29: =$C$2 -> 5661.93 | D29: =C29-E29 -> 4215.2969 | E29: =(F28+G28)*(1/12)*$A$3 -> 1446.6331 | F29: =F28-D29 -> 188669.12 | H29: =EOMONTH(H28,1) -> 45747 | J29: Loan payment | K29: 200379.11
A30: =EOMONTH(A29,1) -> 45777 | B30: 21 | C30: =$C$2+200379.11 -> 206041.04 | D30: =C30-E30 -> 188669.12 | E30: =15956.9+1415.02 -> 17371.92 | F30: =F29-D30 -> 0.0021768948 | H30: =EOMONTH(H29,1) -> 45777 | I30: PAYOFF | J30: Outstanding as of 4/11/25 | K30: 184422.21
A31: =EOMONTH(A30,1) -> 45808 | B31: 22 | D31: =C31-E31 -> -1.6326711e-05 | E31: =(F30+G30)*(1/12)*$A$3 -> 1.6326711e-05 | F31: =F30-D31 -> 0.0021932215 | H31: =EOMONTH(H30,1) -> 45808 | J31: Assumed Interest - to verify | K31: =K29-K30 -> 15956.899 | L31: Need statement
A32: =EOMONTH(A31,1) -> 45838 | B32: 23 | D32: =C32-E32 -> -1.6449161e-05 | E32: =(F31+G31)*(1/12)*$A$3 -> 1.6449161e-05 | F32: =F31-D32 -> 0.0022096706 | H32: =EOMONTH(H31,1) -> 45838
A33: =EOMONTH(A32,1) -> 45869 | B33: 24 | D33: =C33-E33 -> -1.657253e-05 | E33: =(F32+G32)*(1/12)*$A$3 -> 1.657253e-05 | F33: =F32-D33 -> 0.0022262432 | H33: =EOMONTH(H32,1) -> 45869
A34: =EOMONTH(A33,1) -> 45900 | B34: 25 | D34: =C34-E34 -> -1.6696824e-05 | E34: =(F33+G33)*(1/12)*$A$3 -> 1.6696824e-05 | F34: =F33-D34 -> 0.00224294 | H34: =EOMONTH(H33,1) -> 45900
A35: =EOMONTH(A34,1) -> 45930 | B35: 26 | D35: =C35-E35 -> -1.682205e-05 | E35: =(F34+G34)*(1/12)*$A$3 -> 1.682205e-05 | F35: =F34-D35 -> 0.0022597621 | H35: =EOMONTH(H34,1) -> 45930
A36: =EOMONTH(A35,1) -> 45961 | B36: 27 | D36: =C36-E36 -> -1.6948215e-05 | E36: =(F35+G35)*(1/12)*$A$3 -> 1.6948215e-05 | F36: =F35-D36 -> 0.0022767103 | H36: =EOMONTH(H35,1) -> 45961
A37: =EOMONTH(A36,1) -> 45991 | B37: 28 | D37: =C37-E37 -> -1.7075327e-05 | E37: =(F36+G36)*(1/12)*$A$3 -> 1.7075327e-05 | F37: =F36-D37 -> 0.0022937856 | H37: =EOMONTH(H36,1) -> 45991
A38: =EOMONTH(A37,1) -> 46022 | B38: 29 | D38: =C38-E38 -> -1.7203392e-05 | E38: =(F37+G37)*(1/12)*$A$3 -> 1.7203392e-05 | F38: =F37-D38 -> 0.002310989 | H38: =EOMONTH(H37,1) -> 46022
A39: =EOMONTH(A38,1) -> 46053 | B39: 30 | D39: =C39-E39 -> -1.7332417e-05 | E39: =(F38+G38)*(1/12)*$A$3 -> 1.7332417e-05 | F39: =F38-D39 -> 0.0023283214 | H39: =EOMONTH(H38,1) -> 46053
A40: =EOMONTH(A39,1) -> 46081 | B40: 31 | D40: =C40-E40 -> -1.7462411e-05 | E40: =(F39+G39)*(1/12)*$A$3 -> 1.7462411e-05 | F40: =F39-D40 -> 0.0023457838 | H40: =EOMONTH(H39,1) -> 46081
A41: =EOMONTH(A40,1) -> 46112 | B41: 32 | D41: =C41-E41 -> -1.7593379e-05 | E41: =(F40+G40)*(1/12)*$A$3 -> 1.7593379e-05 | F41: =F40-D41 -> 0.0023633772 | H41: =EOMONTH(H40,1) -> 46112
A42: =EOMONTH(A41,1) -> 46142 | B42: 33 | D42: =C42-E42 -> -1.7725329e-05 | E42: =(F41+G41)*(1/12)*$A$3 -> 1.7725329e-05 | F42: =F41-D42 -> 0.0023811025 | H42: =EOMONTH(H41,1) -> 46142
A43: =EOMONTH(A42,1) -> 46173 | B43: 34 | D43: =C43-E43 -> -1.7858269e-05 | E43: =(F42+G42)*(1/12)*$A$3 -> 1.7858269e-05 | F43: =F42-D43 -> 0.0023989608 | H43: =EOMONTH(H42,1) -> 46173
... A68: =EOMONTH(A67,1) -> 46934 | B68: 59 | D68: =C68-E68 -> -2.1526119e-05 | E68: =(F67+G67)*(1/12)*$A$3 -> 2.1526119e-05 | F68: =F67-D68 -> 0.0028916753 | H68: =EOMONTH(H67,1) -> 46934

Sheet 23350 - CCJ True Loan
A1: 555000
A2: 48 | B2: # of Periods | C2: 13365
A3: 0.0723 | B3: APR | C3: Average SOFR 4.48% + 2.75% based on the written agreement
A4: =A3/12 -> 0.006025 | B4: Interest/Period
J5: Closing Date | K5: ='TB Match'!B1 -> 46022 | M5: Current Portion | N5: =SUMIF(H:H,"<="&DATE(YEAR(K5),MONTH(K5)+12,DAY(K5)),D:D)-SUMIF(H:H,"<"&K5+1,D:D) -> 130327.01 | O5: 128908.44 | P5: =O5-N5 -> -1418.5729
M6: Long Term Portion | N6: =INDEX(B:F,MATCH(K5,H:H,0),5)-N5 -> 332358.97 | O6: 333777.54 | P6: =O6-N6 -> 1418.5705
M7: Total | N7: =N6+N5 -> 462685.98
C8: Payment | D8: Principal | E8: Interest | F8: Ending | G8: Accrued interest | H8: Date | M8: Check | N8: =INDEX(B:F,MATCH(K5,H:H,0),5)-N7 -> 0
A9: 45747 | B9: 0 | F9: =A1-C9 -> 555000 | H9: 45747
A10: 45777 | B10: 1 | C10: =$C$2 -> 13365 | D10: =C10-E10 -> 10021.125 | E10: =(F9+G9)*(1/12)*$A$3 -> 3343.875 | F10: =F9-D10 -> 544978.88 | H10: 45777
A11: =EOMONTH(A10,1) -> 45808 | B11: 2 | C11: =$C$2 -> 13365 | D11: =C11-E11 -> 10081.502 | E11: =(F10+G10)*(1/12)*$A$3 -> 3283.4977 | F11: =F10-D11 -> 534897.37 | H11: =EOMONTH(H10,1) -> 45808
A12: =EOMONTH(A11,1) -> 45838 | B12: 3 | C12: =$C$2 -> 13365 | D12: =C12-E12 -> 10142.243 | E12: =(F11+G11)*(1/12)*$A$3 -> 3222.7567 | F12: =F11-D12 -> 524755.13 | H12: =EOMONTH(H11,1) -> 45838
A13: =EOMONTH(A12,1) -> 45869 | B13: 4 | C13: =$C$2 -> 13365 | D13: =C13-E13 -> 10203.35 | E13: =(F12+G12)*(1/12)*$A$3 -> 3161.6497 | F13: =F12-D13 -> 514551.78 | H13: =EOMONTH(H12,1) -> 45869
A14: =EOMONTH(A13,1) -> 45900 | B14: 5 | C14: =$C$2 -> 13365 | D14: =C14-E14 -> 10264.826 | E14: =(F13+G13)*(1/12)*$A$3 -> 3100.1745 | F14: =F13-D14 -> 504286.95 | H14: =EOMONTH(H13,1) -> 45900 | J14: =C14+'23400 - CCJ True Loan (2)'!C14 -> 15268
A15: =EOMONTH(A14,1) -> 45930 | B15: 6 | C15: =$C$2 -> 13365 | D15: =C15-E15 -> 10326.671 | E15: =(F14+G14)*(1/12)*$A$3 -> 3038.3289 | F15: =F14-D15 -> 493960.28 | H15: =EOMONTH(H14,1) -> 45930
A16: =EOMONTH(A15,1) -> 45961 | B16: 7 | C16: =$C$2 -> 13365 | D16: =C16-E16 -> 10388.889 | E16: =(F15+G15)*(1/12)*$A$3 -> 2976.1107 | F16: =F15-D16 -> 483571.39 | H16: =EOMONTH(H15,1) -> 45961
A17: =EOMONTH(A16,1) -> 45991 | B17: 8 | C17: 0 | D17: 0 | E17: =(F16+G16)*(1/12)*$A$3 -> 2913.5176 | F17: =F16-D17 -> 483571.39 | G17: =E17 -> 2913.5176 | H17: =EOMONTH(H16,1) -> 45991 | I17: paid 12/3/25
A18: =EOMONTH(A17,1) -> 46022 | B18: 9 | C18: =$C$2*2 -> 26730 | D18: =C18-E17-E18 -> 20885.411 | E18: =(F17+G17)*(1/12)*$A$3 -> 2931.0716 | F18: =F17-D18 -> 462685.98 | G18: 0 | H18: =EOMONTH(H17,1) -> 46022
A19: =EOMONTH(A18,1) -> 46053 | B19: 10 | C19: =$C$2 -> 13365 | D19: =C19-E18 -> 10433.928 | E19: =(F18+G18)*(1/12)*$A$3 -> 2787.683 | F19: =F18-D19 -> 452252.05 | H19: =EOMONTH(H18,1) -> 46053
A20: =EOMONTH(A19,1) -> 46081 | B20: 11 | C20: =$C$2 -> 13365 | D20: =C20-E19 -> 10577.317 | E20: =(F19+G19)*(1/12)*$A$3 -> 2724.8186 | F20: =F19-D20 -> 441674.74 | H20: =EOMONTH(H19,1) -> 46081
A21: =EOMONTH(A20,1) -> 46112 | B21: 12 | C21: =$C$2 -> 13365 | D21: =C21-E20 -> 10640.181 | E21: =(F20+G20)*(1/12)*$A$3 -> 2661.0903 | F21: =F20-D21 -> 431034.56 | H21: =EOMONTH(H20,1) -> 46112
A22: =EOMONTH(A21,1) -> 46142 | B22: 13 | C22: =$C$2 -> 13365 | D22: =C22-E21 -> 10703.91 | E22: =(F21+G21)*(1/12)*$A$3 -> 2596.9832 | F22: =F21-D22 -> 420330.65 | H22: =EOMONTH(H21,1) -> 46142
A23: =EOMONTH(A22,1) -> 46173 | B23: 14 | C23: =$C$2 -> 13365 | D23: =C23-E22 -> 10768.017 | E23: =(F22+G22)*(1/12)*$A$3 -> 2532.4921 | F23: =F22-D23 -> 409562.63 | H23: =EOMONTH(H22,1) -> 46173
A24: =EOMONTH(A23,1) -> 46203 | B24: 15 | C24: =$C$2 -> 13365 | D24: =C24-E23 -> 10832.508 | E24: =(F23+G23)*(1/12)*$A$3 -> 2467.6148 | F24: =F23-D24 -> 398730.12 | H24: =EOMONTH(H23,1) -> 46203
A25: =EOMONTH(A24,1) -> 46234 | B25: 16 | C25: =$C$2 -> 13365 | D25: =C25-E24 -> 10897.385 | E25: =(F24+G24)*(1/12)*$A$3 -> 2402.349 | F25: =F24-D25 -> 387832.74 | H25: =EOMONTH(H24,1) -> 46234
A26: =EOMONTH(A25,1) -> 46265 | B26: 17 | C26: =$C$2 -> 13365 | D26: =C26-E25 -> 10962.651 | E26: =(F25+G25)*(1/12)*$A$3 -> 2336.6922 | F26: =F25-D26 -> 376870.09 | H26: =EOMONTH(H25,1) -> 46265
A27: =EOMONTH(A26,1) -> 46295 | B27: 18 | C27: =$C$2 -> 13365 | D27: =C27-E26 -> 11028.308 | E27: =(F26+G26)*(1/12)*$A$3 -> 2270.6423 | F27: =F26-D27 -> 365841.78 | H27: =EOMONTH(H26,1) -> 46295
A28: =EOMONTH(A27,1) -> 46326 | B28: 19 | C28: =$C$2 -> 13365 | D28: =C28-E27 -> 11094.358 | E28: =(F27+G27)*(1/12)*$A$3 -> 2204.1967 | F28: =F27-D28 -> 354747.42 | H28: =EOMONTH(H27,1) -> 46326
A29: =EOMONTH(A28,1) -> 46356 | B29: 20 | C29: =$C$2 -> 13365 | D29: =C29-E28 -> 11160.803 | E29: =(F28+G28)*(1/12)*$A$3 -> 2137.3532 | F29: =F28-D29 -> 343586.62 | H29: =EOMONTH(H28,1) -> 46356
A30: =EOMONTH(A29,1) -> 46387 | B30: 21 | C30: =$C$2 -> 13365 | D30: =C30-E29 -> 11227.647 | E30: =(F29+G29)*(1/12)*$A$3 -> 2070.1094 | F30: =F29-D30 -> 332358.97 | H30: =EOMONTH(H29,1) -> 46387
... A42: =EOMONTH(A41,1) -> 46752 | B42: 33 | C42: =$C$2 -> 13365 | D42: =C42-E41 -> 12061.691 | E42: =(F41+G41)*(1/12)*$A$3 -> 1231.0699 | F42: =F41-D42 -> 192265.26 | H42: =EOMONTH(H41,1) -> 46752
A43: =EOMONTH(A42,1) -> 46783 | B43: 34 | C43: 10923.82 | D43: =C43-E42 -> 9692.7501 | E43: =(F42+G42)*(1/12)*$A$3 -> 1158.3982 | F43: =F42-D43 -> 182572.51 | H43: =EOMONTH(H42,1) -> 46783
A44: =EOMONTH(A43,1) -> 46812 | B44: 35 | C44: =$C$2 -> 13365 | D44: =C44-E43 -> 12206.602 | E44: =(F43+G43)*(1/12)*$A$3 -> 1099.9994 | F44: =F43-D44 -> 170365.91 | H44: =EOMONTH(H43,1) -> 46812
A45: =EOMONTH(A44,1) -> 46843 | B45: 36 | C45: =$C$2 -> 13365 | D45: =C45-E44 -> 12265.001 | E45: =(F44+G44)*(1/12)*$A$3 -> 1026.4546 | F45: =F44-D45 -> 158100.91 | H45: =EOMONTH(H44,1) -> 46843
A46: =EOMONTH(A45,1) -> 46873 | B46: 37 | C46: =$C$2 -> 13365 | D46: =C46-E45 -> 12338.545 | E46: =(F45+G45)*(1/12)*$A$3 -> 952.55799 | F46: =F45-D46 -> 145762.37 | H46: =EOMONTH(H45,1) -> 46873
A47: =EOMONTH(A46,1) -> 46904 | B47: 38 | C47: =$C$2 -> 13365 | D47: =C47-E46 -> 12412.442 | E47: =(F46+G46)*(1/12)*$A$3 -> 878.21825 | F47: =F46-D47 -> 133349.92 | H47: =EOMONTH(H46,1) -> 46904
A48: =EOMONTH(A47,1) -> 46934 | B48: 39 | C48: =$C$2 -> 13365 | D48: =C48-E47 -> 12486.782 | E48: =(F47+G47)*(1/12)*$A$3 -> 803.43329 | F48: =F47-D48 -> 120863.14 | H48: =EOMONTH(H47,1) -> 46934
A49: =EOMONTH(A48,1) -> 46965 | B49: 40 | C49: =$C$2 -> 13365 | D49: =C49-E48 -> 12561.567 | E49: =(F48+G48)*(1/12)*$A$3 -> 728.20043 | F49: =F48-D49 -> 108301.58 | H49: =EOMONTH(H48,1) -> 46965
A50: =EOMONTH(A49,1) -> 46996 | B50: 41 | C50: =$C$2 -> 13365 | D50: =C50-E49 -> 12636.8 | E50: =(F49+G49)*(1/12)*$A$3 -> 652.51699 | F50: =F49-D50 -> 95664.776 | H50: =EOMONTH(H49,1) -> 46996
A51: =EOMONTH(A50,1) -> 47026 | B51: 42 | C51: =$C$2 -> 13365 | D51: =C51-E50 -> 12712.483 | E51: =(F50+G50)*(1/12)*$A$3 -> 576.38027 | F51: =F50-D51 -> 82952.293 | H51: =EOMONTH(H50,1) -> 47026
A52: =EOMONTH(A51,1) -> 47057 | B52: 43 | C52: =$C$2 -> 13365 | D52: =C52-E51 -> 12788.62 | E52: =(F51+G51)*(1/12)*$A$3 -> 499.78756 | F52: =F51-D52 -> 70163.673 | H52: =EOMONTH(H51,1) -> 47057
A53: =EOMONTH(A52,1) -> 47087 | B53: 44 | C53: =$C$2 -> 13365 | D53: =C53-E52 -> 12865.212 | E53: =(F52+G52)*(1/12)*$A$3 -> 422.73613 | F53: =F52-D53 -> 57298.461 | H53: =EOMONTH(H52,1) -> 47087
A54: =EOMONTH(A53,1) -> 47118 | B54: 45 | C54: =$C$2 -> 13365 | D54: =C54-E53 -> 12942.264 | E54: =(F53+G53)*(1/12)*$A$3 -> 345.22323 | F54: =F53-D54 -> 44356.197 | H54: =EOMONTH(H53,1) -> 47118
A55: =EOMONTH(A54,1) -> 47149 | B55: 46 | C55: =$C$2 -> 13365 | D55: =C55-E54 -> 13019.777 | E55: =(F54+G54)*(1/12)*$A$3 -> 267.24609 | F55: =F54-D55 -> 31336.42 | H55: =EOMONTH(H54,1) -> 47149
... A57: =EOMONTH(A56,1) -> 47208 | B57: 48 | C57: =$C$2 -> 13365 | D57: =C57-E56 -> 13176.198 | E57: =(F56+G56)*(1/12)*$A$3 -> 109.88796 | F57: =F56-D57 -> 5062.468 | H57: =EOMONTH(H56,1) -> 47208

Sheet 23400 - CCJ True Loan (2)
A1: 79000
A2: 48 | B2: # of Periods | C2: 1903
A3: 0.0723 | B3: APR | C3: Average SOFR 4.48% + 2.75% based on the written agreement
A4: =A3/12 -> 0.006025 | B4: Interest/Period
J5: Closing Date | K5: ='TB Match'!B1 -> 46022 | M5: Current Portion | N5: =SUMIF(H:H,"<="&DATE(YEAR(K5),MONTH(K5)+12,DAY(K5)),D:D)-SUMIF(H:H,"<"&K5+1,D:D) -> 18327.425 | O5: 18137.63 | P5: =O5-N5 -> -189.79463
M6: Long Term Portion | N6: =INDEX(B:F,MATCH(K5,H:H,0),5)-N5 -> 49058.992 | O6: 49248.8 | P6: =O6-N6 -> 189.80816
M7: Total | N7: =N6+N5 -> 67386.416
C8: Payment | D8: Principal | E8: Interest | F8: Ending | G8: Accrued interest | H8: Date | M8: Check | N8: =INDEX(B:F,MATCH(K5,H:H,0),5)-N7 -> 0
A9: 45747 | B9: 0 | F9: =A1-C9 -> 79000 | H9: 45747
A10: 45777 | B10: 1 | C10: =$C$2 -> 1903 | D10: =C10-E10 -> 1427.025 | E10: =(F9+G9)*(1/12)*$A$3 -> 475.975 | F10: =F9-D10 -> 77572.975 | H10: 45777
A11: =EOMONTH(A10,1) -> 45808 | B11: 2 | C11: =$C$2 -> 1903 | D11: =C11-E11 -> 1435.6228 | E11: =(F10+G10)*(1/12)*$A$3 -> 467.37717 | F11: =F10-D11 -> 76137.352 | H11: =EOMONTH(H10,1) -> 45808
A12: =EOMONTH(A11,1) -> 45838 | B12: 3 | C12: =$C$2 -> 1903 | D12: =C12-E12 -> 1444.2725 | E12: =(F11+G11)*(1/12)*$A$3 -> 458.72755 | F12: =F11-D12 -> 74693.08 | H12: =EOMONTH(H11,1) -> 45838
A13: =EOMONTH(A12,1) -> 45869 | B13: 4 | C13: 0 | D13: 0 | E13: =(F12+G12)*(1/12)*$A$3 -> 450.02581 | F13: =F12-D13 -> 74693.08 | G13: =E13 -> 450.02581 | H13: =EOMONTH(H12,1) -> 45869
A14: =EOMONTH(A13,1) -> 45900 | B14: 5 | C14: =$C$2 -> 1903 | D14: =C14-E13 -> 1452.9742 | E14: =(F13+G13)*(1/12)*$A$3 -> 452.73721 | F14: =F13-D14 -> 73240.106 | G14: =E14-E13+G13 -> 452.73721 | H14: =EOMONTH(H13,1) -> 45900
A15: =EOMONTH(A14,1) -> 45930 | B15: 6 | C15: =$C$2 -> 1903 | D15: =C15-E14 -> 1450.2628 | E15: =(F14+G14)*(1/12)*$A$3 -> 443.99938 | F15: =F14-D15 -> 71789.843 | G15: =E15-E14+G14 -> 443.99938 | H15: =EOMONTH(H14,1) -> 45930
A16: =EOMONTH(A15,1) -> 45961 | B16: 7 | C16: =$C$2 -> 1903 | D16: =C16-E15 -> 1459.0006 | E16: =(F15+G15)*(1/12)*$A$3 -> 435.2089 | F16: =F15-D16 -> 70330.842 | G16: =E16-E15+G15 -> 435.2089 | H16: =EOMONTH(H15,1) -> 45961
A17: =EOMONTH(A16,1) -> 45991 | B17: 8 | C17: 0 | D17: 0 | E17: =(F16+G16)*(1/12)*$A$3 -> 426.36546 | F17: =F16-D17 -> 70330.842 | G17: =E17-E16+G16 -> 426.36546 | H17: =EOMONTH(H16,1) -> 45991 | I17: paid 12/3/25
A18: =EOMONTH(A17,1) -> 46022 | B18: 9 | C18: =$C$2*2 -> 3806 | D18: =C18-E16-E17 -> 2944.4256 | E18: =(F17+G17)*(1/12)*$A$3 -> 426.31218 | F18: =F17-D18 -> 67386.416 | G18: =E18-E17+G17 -> 426.31218 | H18: =EOMONTH(H17,1) -> 46022
A19: =EOMONTH(A18,1) -> 46053 | B19: 10 | C19: =$C$2 -> 1903 | D19: =C19-E17 -> 1476.6345 | E19: =(F18+G18)*(1/12)*$A$3 -> 408.57169 | F19: =F18-D19 -> 65909.782 | H19: =EOMONTH(H18,1) -> 46053
A20: =EOMONTH(A19,1) -> 46081 | B20: 11 | C20: =$C$2 -> 1903 | D20: =C20-E18 -> 1476.6878 | E20: =(F19+G19)*(1/12)*$A$3 -> 397.10644 | F20: =F19-D20 -> 64433.094 | H20: =EOMONTH(H19,1) -> 46081
A21: =EOMONTH(A20,1) -> 46112 | B21: 12 | C21: =$C$2 -> 1903 | D21: =C21-E19 -> 1494.4283 | E21: =(F20+G20)*(1/12)*$A$3 -> 388.20939 | F21: =F20-D21 -> 62938.666 | H21: =EOMONTH(H20,1) -> 46112
A22: =EOMONTH(A21,1) -> 46142 | B22: 13 | C22: =$C$2 -> 1903 | D22: =C22-E20 -> 1505.8936 | E22: =(F21+G21)*(1/12)*$A$3 -> 379.20546 | F22: =F21-D22 -> 61432.772 | H22: =EOMONTH(H21,1) -> 46142
A23: =EOMONTH(A22,1) -> 46173 | B23: 14 | C23: =$C$2 -> 1903 | D23: =C23-E21 -> 1514.7906 | E23: =(F22+G22)*(1/12)*$A$3 -> 370.13245 | F23: =F22-D23 -> 59917.982 | H23: =EOMONTH(H22,1) -> 46173
A24: =EOMONTH(A23,1) -> 46203 | B24: 15 | C24: =$C$2 -> 1903 | D24: =C24-E22 -> 1523.7945 | E24: =(F23+G23)*(1/12)*$A$3 -> 361.00584 | F24: =F23-D24 -> 58394.187 | H24: =EOMONTH(H23,1) -> 46203
A25: =EOMONTH(A24,1) -> 46234 | B25: 16 | C25: =$C$2 -> 1903 | D25: =C25-E23 -> 1532.8675 | E25: =(F24+G24)*(1/12)*$A$3 -> 351.82498 | F25: =F24-D25 -> 56861.32 | H25: =EOMONTH(H24,1) -> 46234
A26: =EOMONTH(A25,1) -> 46265 | B26: 17 | C26: =$C$2 -> 1903 | D26: =C26-E24 -> 1541.9942 | E26: =(F25+G25)*(1/12)*$A$3 -> 342.58945 | F26: =F25-D26 -> 55319.325 | H26: =EOMONTH(H25,1) -> 46265
A27: =EOMONTH(A26,1) -> 46295 | B27: 18 | C27: =$C$2 -> 1903 | D27: =C27-E25 -> 1551.175 | E27: =(F26+G26)*(1/12)*$A$3 -> 333.29894 | F27: =F26-D27 -> 53768.15 | H27: =EOMONTH(H26,1) -> 46295
A28: =EOMONTH(A27,1) -> 46326 | B28: 19 | C28: =$C$2 -> 1903 | D28: =C28-E26 -> 1560.4105 | E28: =(F27+G27)*(1/12)*$A$3 -> 323.95311 | F28: =F27-D28 -> 52207.74 | H28: =EOMONTH(H27,1) -> 46326
A29: =EOMONTH(A28,1) -> 46356 | B29: 20 | C29: =$C$2 -> 1903 | D29: =C29-E27 -> 1569.7011 | E29: =(F28+G28)*(1/12)*$A$3 -> 314.55163 | F29: =F28-D29 -> 50638.039 | H29: =EOMONTH(H28,1) -> 46356
A30: =EOMONTH(A29,1) -> 46387 | B30: 21 | C30: =$C$2 -> 1903 | D30: =C30-E28 -> 1579.0469 | E30: =(F29+G29)*(1/12)*$A$3 -> 305.09418 | F30: =F29-D30 -> 49058.992 | H30: =EOMONTH(H29,1) -> 46387
... A57: =EOMONTH(A56,1) -> 47208 | B57: 48 | C57: =$C$2 -> 1903 | D57: =C57-E55 -> 1853.5446 | E57: =(F56+G56)*(1/12)*$A$3 -> 27.318042 | F57: =F56-D57 -> 2680.5702 | H57: =EOMONTH(H56,1) -> 47208
